{"profile_pic_edit_sync_props": null, "show_view_shop": false, "toast_content_on_load": null, "graphql": {"user": {"biography": "Slu\u017ebeni instagram profil \u017eenskog lifestyle portala", "edge_followed_by": {"count": 148122}, "username": "zadovoljnahr", "is_joined_recently": false, "blocked_by_viewer": false, "external_url": "https://zadovoljna.dnevnik.hr/", "has_channel": false, "edge_mutual_followed_by": {"count": 0, "edges": []}, "edge_felix_video_timeline": {"count": 0, "edges": [], "page_info": {"has_next_page": false, "end_cursor": null}}, "edge_owner_to_timeline_media": {"count": 13501, "edges": [{"node": {"__typename": "GraphImage", "taken_at_timestamp": 1603555256, "edge_media_to_comment": {"count": 0}, "dimensions": {"height": 1080, "width": 1080}, "edge_media_preview_like": {"count": 633}, "fact_check_information": null, "gating_info": null, "comments_disabled": false, "display_url": "https://scontent-ber1-1.cdninstagram.com/v/t51.2885-15/fr/e15/s1080x1080/122401260_190776896011596_2105842666081585722_n.jpg?_nc_ht=scontent-ber1-1.cdninstagram.com&_nc_cat=100&_nc_ohc=StEmiWS2bs4AX_taGNA&oh=83566ebff851e8a94dcc8f816667dc55&oe=5FBCE61B", "thumbnail_resources": [{"src": "https://scontent-ber1-1.cdninstagram.com/v/t51.2885-15/e15/s150x150/122401260_190776896011596_2105842666081585722_n.jpg?_nc_ht=scontent-ber1-1.cdninstagram.com&_nc_cat=100&_nc_ohc=StEmiWS2bs4AX_taGNA&_nc_tp=15&oh=c198f3478dfb353b9cc2c13868182d0a&oe=5FBE12EF", "config_height": 150, "config_width": 150}, {"src": "https://scontent-ber1-1.cdninstagram.com/v/t51.2885-15/e15/s240x240/122401260_190776896011596_2105842666081585722_n.jpg?_nc_ht=scontent-ber1-1.cdninstagram.com&_nc_cat=100&_nc_ohc=StEmiWS2bs4AX_taGNA&_nc_tp=15&oh=382dfeb346f167310f87fac8d35b517f&oe=5FBCF069", "config_height": 240, "config_width": 240}, {"src": "https://scontent-ber1-1.cdninstagram.com/v/t51.2885-15/e15/s320x320/122401260_190776896011596_2105842666081585722_n.jpg?_nc_ht=scontent-ber1-1.cdninstagram.com&_nc_cat=100&_nc_ohc=StEmiWS2bs4AX_taGNA&_nc_tp=15&oh=518fb982d816a57ac78bbe661e7ef6a5&oe=5FBD9D97", "config_height": 320, "config_width": 320}, {"src": "https://scontent-ber1-1.cdninstagram.com/v/t51.2885-15/e15/s480x480/122401260_190776896011596_2105842666081585722_n.jpg?_nc_ht=scontent-ber1-1.cdninstagram.com&_nc_cat=100&_nc_ohc=StEmiWS2bs4AX_taGNA&_nc_tp=15&oh=93dafbdc1e399befdf8af4761e74d079&oe=5FBE32D2", "config_height": 480, "config_width": 480}, {"src": "https://scontent-ber1-1.cdninstagram.com/v/t51.2885-15/sh0.08/e35/s640x640/122401260_190776896011596_2105842666081585722_n.jpg?_nc_ht=scontent-ber1-1.cdninstagram.com&_nc_cat=100&_nc_ohc=StEmiWS2bs4AX_taGNA&_nc_tp=24&oh=764c99a7893b8bbeab737d5396f62e5c&oe=5FBF8454", "config_height": 640, "config_width": 640}], "owner": {"id": "1428643188", "username": "zadovoljnahr"}, "shortcode": "CGu3KhYqu2u", "is_video": false, "media_overlay_info": null, "id": "2427119864799489454", "thumbnail_src": "https://scontent-ber1-1.cdninstagram.com/v/t51.2885-15/sh0.08/e35/s640x640/122401260_190776896011596_2105842666081585722_n.jpg?_nc_ht=scontent-ber1-1.cdninstagram.com&_nc_cat=100&_nc_ohc=StEmiWS2bs4AX_taGNA&_nc_tp=24&oh=764c99a7893b8bbeab737d5396f62e5c&oe=5FBF8454", "edge_liked_by": {"count": 633}, "media_preview": "ACoq6aimNSf570ASUhNJzSN+dADgc0tNFOoAawpMZ/8A1UEc0gH+cUAPAxTexp2aaOtAwHWn0zoafQAhIFIeelOooEMyfSjcfQ0+igYwAnrS806igD//2Q==", "fact_check_overall_rating": null, "edge_media_to_caption": {"edges": [{"node": {"text": "Odustajanje nije opcija. \u2764\ufe0f Jo\u0161 jednom vas podsje\u0107amo na inicijativu #brinemoZAjedno u kojoj vas pozivamo da objavite otografiju jedne strane tijela, od trupa na gore u odje\u0107i, s fokusom na dojku te umetnite cvijet na mjesto bradavice. U opisu dodajte hashtag #brinemoZAjedno i tako poka\u017eimo da zaista brinemo jedni o drugima podi\u017eu\u0107i svijest o ovoj zlo\u0107udnoj bolesti protiv koje se mo\u017eemo za\u0161titi pravovremenom prevencijom. \u2764\ufe0f #zadovoljnahr"}}]}, "edge_media_to_tagged_user": {"edges": []}, "accessibility_caption": "Photo by zadovoljna.hr on October 24, 2020.", "location": null}}, {"node": {"__typename": "GraphImage", "taken_at_timestamp": 1603544445, "edge_media_to_comment": {"count": 2}, "dimensions": {"height": 1349, "width": 1080}, "edge_media_preview_like": {"count": 947}, "fact_check_information": null, "gating_info": null, "comments_disabled": false, "display_url": "https://scontent-ber1-1.cdninstagram.com/v/t51.2885-15/fr/e15/p1080x1080/122448636_2713905482173360_8849224175421690922_n.jpg?_nc_ht=scontent-ber1-1.cdninstagram.com&_nc_cat=1&_nc_ohc=WygDZj0iuJsAX-01ODk&oh=ede4fadf42d4cf59ccc0540d69222db7&oe=5FBD70BC", "thumbnail_resources": [{"src": "https://scontent-ber1-1.cdninstagram.com/v/t51.2885-15/e15/c0.134.1080.1080a/s150x150/122448636_2713905482173360_8849224175421690922_n.jpg?_nc_ht=scontent-ber1-1.cdninstagram.com&_nc_cat=1&_nc_ohc=WygDZj0iuJsAX-01ODk&tp=16&oh=f9073f92263cb991e680305164e27ac5&oe=5FBC8AD8", "config_height": 150, "config_width": 150}, {"src": "https://scontent-ber1-1.cdninstagram.com/v/t51.2885-15/e15/c0.134.1080.1080a/s240x240/122448636_2713905482173360_8849224175421690922_n.jpg?_nc_ht=scontent-ber1-1.cdninstagram.com&_nc_cat=1&_nc_ohc=WygDZj0iuJsAX-01ODk&tp=16&oh=5a8d034e9d922fd1127432c4d06e1d78&oe=5FBF52A0", "config_height": 240, "config_width": 240}, {"src": "https://scontent-ber1-1.cdninstagram.com/v/t51.2885-15/e15/c0.134.1080.1080a/s320x320/122448636_2713905482173360_8849224175421690922_n.jpg?_nc_ht=scontent-ber1-1.cdninstagram.com&_nc_cat=1&_nc_ohc=WygDZj0iuJsAX-01ODk&tp=16&oh=2c8e472ffae9f32a58550fe4e36eb480&oe=5FBD71C1", "config_height": 320, "config_width": 320}, {"src": "https://scontent-ber1-1.cdninstagram.com/v/t51.2885-15/e15/c0.134.1080.1080a/s480x480/122448636_2713905482173360_8849224175421690922_n.jpg?_nc_ht=scontent-ber1-1.cdninstagram.com&_nc_cat=1&_nc_ohc=WygDZj0iuJsAX-01ODk&tp=16&oh=b31dad6de36c5cb1a3d6c75477e2d822&oe=5FBDC083", "config_height": 480, "config_width": 480}, {"src": "https://scontent-ber1-1.cdninstagram.com/v/t51.2885-15/sh0.08/e35/c0.134.1080.1080a/s640x640/122448636_2713905482173360_8849224175421690922_n.jpg?_nc_ht=scontent-ber1-1.cdninstagram.com&_nc_cat=1&_nc_ohc=WygDZj0iuJsAX-01ODk&oh=a794820ee9aef96ee8959d3580f16781&oe=5FBD4574", "config_height": 640, "config_width": 640}], "owner": {"id": "1428643188", "username": "zadovoljnahr"}, "shortcode": "CGuii3yqCgR", "is_video": false, "media_overlay_info": null, "id": "2427029179148544017", "thumbnail_src": "https://scontent-ber1-1.cdninstagram.com/v/t51.2885-15/sh0.08/e35/c0.134.1080.1080a/s640x640/122448636_2713905482173360_8849224175421690922_n.jpg?_nc_ht=scontent-ber1-1.cdninstagram.com&_nc_cat=1&_nc_ohc=WygDZj0iuJsAX-01ODk&oh=a794820ee9aef96ee8959d3580f16781&oe=5FBD4574", "edge_liked_by": {"count": 947}, "media_preview": "ACEqtXA2j6iszYM/XH1rWI3qN3K8kEfp9RWS5wcYJx3GMcjI96Td9RxjZWNdV+Yf7Ix/Un+X61YH3agilTb15PbnNWKzLIti+i/rRUm4ev6iigRj24SfIwQVHHJ5Hrjt/ntVxpEjBjJCltu0fl/nms6xRuWPGeMe1LImboA8jIOPbGf6VYGkjHD+z8fTiqay72x6e/J569/pV8jIx0BNUXjMALfeB/yOfQd/5moHcnyf7v60VR8xvf8AOikUaiRhRgdBULxgSh+5GMfT/wDXVqmkVZAVGxI6VJUZoAZsh/uiilopAf/Z", "fact_check_overall_rating": null, "edge_media_to_caption": {"edges": [{"node": {"text": "Odli\u010dan #outfit za subotnju \u0161etnjicu \ud83d\ude0d #ootd #ootdinspiration #zadovoljnahr / @sta_life"}}]}, "edge_media_to_tagged_user": {"edges": [{"node": {"y": 0.9185185432, "user": {"full_name": "Sta", "id": "756912102", "username": "sta_life", "profile_pic_url": "https://scontent-ber1-1.cdninstagram.com/v/t51.2885-19/s150x150/118691280_234170734598357_6602425997793226097_n.jpg?_nc_ht=scontent-ber1-1.cdninstagram.com&_nc_ohc=DkG8CXMa5H0AX8IsGBC&oh=19212eb97d86bed52e7053f769e290da&oe=5FBE760E", "is_verified": false}, "x": 0.1518518478}}]}, "accessibility_caption": "Photo shared by zadovoljna.hr on October 24, 2020 tagging @sta_life. Image may contain: 1 person, standing, shoes and outdoor.", "location": null}}, {"node": {"__typename": "GraphImage", "taken_at_timestamp": 1603533653, "edge_media_to_comment": {"count": 0}, "dimensions": {"height": 1350, "width": 1080}, "edge_media_preview_like": {"count": 543}, "fact_check_information": null, "gating_info": null, "comments_disabled": false, "display_url": "https://scontent-ber1-1.cdninstagram.com/v/t51.2885-15/fr/e15/p1080x1080/122428061_398092491366206_4152005749037425192_n.jpg?_nc_ht=scontent-ber1-1.cdninstagram.com&_nc_cat=1&_nc_ohc=HFkEUBN-9ykAX-sJ-Kg&oh=49df71bc1b7596e21a5d0897063a604d&oe=5FBCE180", "thumbnail_resources": [{"src": "https://scontent-ber1-1.cdninstagram.com/v/t51.2885-15/e15/c0.135.1080.1080a/s150x150/122428061_398092491366206_4152005749037425192_n.jpg?_nc_ht=scontent-ber1-1.cdninstagram.com&_nc_cat=1&_nc_ohc=HFkEUBN-9ykAX-sJ-Kg&tp=16&oh=7254af2b7ea53ec617df1ef29773500d&oe=5FBE789D", "config_height": 150, "config_width": 150}, {"src": "https://scontent-ber1-1.cdninstagram.com/v/t51.2885-15/e15/c0.135.1080.1080a/s240x240/122428061_398092491366206_4152005749037425192_n.jpg?_nc_ht=scontent-ber1-1.cdninstagram.com&_nc_cat=1&_nc_ohc=HFkEUBN-9ykAX-sJ-Kg&tp=16&oh=4deb5ae6def527bb46852ac4b8a7d3f1&oe=5FBD641B", "config_height": 240, "config_width": 240}, {"src": "https://scontent-ber1-1.cdninstagram.com/v/t51.2885-15/e15/c0.135.1080.1080a/s320x320/122428061_398092491366206_4152005749037425192_n.jpg?_nc_ht=scontent-ber1-1.cdninstagram.com&_nc_cat=1&_nc_ohc=HFkEUBN-9ykAX-sJ-Kg&tp=16&oh=b37b5d6424a55927d8603a16252e6bd3&oe=5FBD7465", "config_height": 320, "config_width": 320}, {"src": "https://scontent-ber1-1.cdninstagram.com/v/t51.2885-15/e15/c0.135.1080.1080a/s480x480/122428061_398092491366206_4152005749037425192_n.jpg?_nc_ht=scontent-ber1-1.cdninstagram.com&_nc_cat=1&_nc_ohc=HFkEUBN-9ykAX-sJ-Kg&tp=16&oh=b96d9ab6459abb58f5bc1c2fc2772adb&oe=5FBC67A4", "config_height": 480, "config_width": 480}, {"src": "https://scontent-ber1-1.cdninstagram.com/v/t51.2885-15/sh0.08/e35/c0.135.1080.1080a/s640x640/122428061_398092491366206_4152005749037425192_n.jpg?_nc_ht=scontent-ber1-1.cdninstagram.com&_nc_cat=1&_nc_ohc=HFkEUBN-9ykAX-sJ-Kg&oh=b35c24e93fe4371934c909c949e95d34&oe=5FBEC54B", "config_height": 640, "config_width": 640}], "owner": {"id": "1428643188", "username": "zadovoljnahr"}, "shortcode": "CGuN9c8K5RA", "is_video": false, "media_overlay_info": null, "id": "2426938646766261312", "thumbnail_src": "https://scontent-ber1-1.cdninstagram.com/v/t51.2885-15/sh0.08/e35/c0.135.1080.1080a/s640x640/122428061_398092491366206_4152005749037425192_n.jpg?_nc_ht=scontent-ber1-1.cdninstagram.com&_nc_cat=1&_nc_ohc=HFkEUBN-9ykAX-sJ-Kg&oh=b35c24e93fe4371934c909c949e95d34&oe=5FBEC54B", "edge_liked_by": {"count": 543}, "media_preview": "ACEqVbtmOML69+341ZtpWn9BjHHNUUjCZJ5PTP8A9apCnlDKEgEY9+ff0/Woui2mkWpJ9j7Bhh6g/mD7im/aP9n9f/rVUHBHp/n+VSLTJJ/tH+z+v/1qKiopgMXnOOg/lSvJtU5/DNS+YNwYAqCSPrz1/H9KhWeQqSTn5gMEAjoexrNK5XMOheMkhhgEfXn+nFSyFCRs6AfrmmlFOSo2soBIHQjHJHpjuKZmtCBaKbmimBckURFWPKjgj1ycA/rVFk2o2Om8Y/Js/iDxWtJ0/AVnTf6kf9dD/NqlbtCHBtkjH+7gH6EgH9KhcbGK+hIqSXrL9V/nTLn/AFjfX+lUMj3UVXzRQB//2Q==", "fact_check_overall_rating": null, "edge_media_to_caption": {"edges": [{"node": {"text": "Kako preslatka teglica \ud83d\udc40 #plantlover #plantsofinstagram #interiordesign #zadovoljnahr / @my_easy_country_living"}}]}, "edge_media_to_tagged_user": {"edges": [{"node": {"y": 0.9425926208, "user": {"full_name": "Ivona", "id": "8128871009", "username": "my_easy_country_living", "profile_pic_url": "https://scontent-ber1-1.cdninstagram.com/v/t51.2885-19/s150x150/75595317_2454636234749878_1006430800184344576_n.jpg?_nc_ht=scontent-ber1-1.cdninstagram.com&_nc_ohc=UfnDeO17feoAX-_QjgG&oh=e816acac59c32f005aefccdf1398fa92&oe=5FBC59CE", "is_verified": false}, "x": 0.1277777851}}]}, "accessibility_caption": "Photo shared by zadovoljna.hr on October 24, 2020 tagging @my_easy_country_living.", "location": null}}, {"node": {"__typename": "GraphImage", "taken_at_timestamp": 1603522807, "edge_media_to_comment": {"count": 1}, "dimensions": {"height": 750, "width": 750}, "edge_media_preview_like": {"count": 780}, "fact_check_information": null, "gating_info": null, "comments_disabled": false, "display_url": "https://scontent-ber1-1.cdninstagram.com/v/t51.2885-15/e15/122473135_135858978270197_7757271545185133204_n.jpg?_nc_ht=scontent-ber1-1.cdninstagram.com&_nc_cat=105&_nc_ohc=motAszfBS9YAX9ss9m1&_nc_tp=18&oh=e35c8eace8c8e85feaf9b894427fab25&oe=5FBBF95A", "thumbnail_resources": [{"src": "https://scontent-ber1-1.cdninstagram.com/v/t51.2885-15/e15/s150x150/122473135_135858978270197_7757271545185133204_n.jpg?_nc_ht=scontent-ber1-1.cdninstagram.com&_nc_cat=105&_nc_ohc=motAszfBS9YAX9ss9m1&_nc_tp=15&oh=f1d4cab838af1ad84603982827b70f8e&oe=5FBD4833", "config_height": 150, "config_width": 150}, {"src": "https://scontent-ber1-1.cdninstagram.com/v/t51.2885-15/e15/s240x240/122473135_135858978270197_7757271545185133204_n.jpg?_nc_ht=scontent-ber1-1.cdninstagram.com&_nc_cat=105&_nc_ohc=motAszfBS9YAX9ss9m1&_nc_tp=15&oh=ea8f8ac7237f35272e8aec894924f269&oe=5FBD76B5", "config_height": 240, "config_width": 240}, {"src": "https://scontent-ber1-1.cdninstagram.com/v/t51.2885-15/e15/s320x320/122473135_135858978270197_7757271545185133204_n.jpg?_nc_ht=scontent-ber1-1.cdninstagram.com&_nc_cat=105&_nc_ohc=motAszfBS9YAX9ss9m1&_nc_tp=15&oh=cfc11f2e314d94247252dae8b8679850&oe=5FBE054B", "config_height": 320, "config_width": 320}, {"src": "https://scontent-ber1-1.cdninstagram.com/v/t51.2885-15/e15/s480x480/122473135_135858978270197_7757271545185133204_n.jpg?_nc_ht=scontent-ber1-1.cdninstagram.com&_nc_cat=105&_nc_ohc=motAszfBS9YAX9ss9m1&_nc_tp=15&oh=3b18e6e154f60866c71a98da2dfc8574&oe=5FBFA80E", "config_height": 480, "config_width": 480}, {"src": "https://scontent-ber1-1.cdninstagram.com/v/t51.2885-15/e15/s640x640/122473135_135858978270197_7757271545185133204_n.jpg?_nc_ht=scontent-ber1-1.cdninstagram.com&_nc_cat=105&_nc_ohc=motAszfBS9YAX9ss9m1&_nc_tp=15&oh=e68747baa3eaccab1187d3e1adc5cf62&oe=5FBE1072", "config_height": 640, "config_width": 640}], "owner": {"id": "1428643188", "username": "zadovoljnahr"}, "shortcode": "CGt5RbUqLhj", "is_video": false, "media_overlay_info": null, "id": "2426847660442433635", "thumbnail_src": "https://scontent-ber1-1.cdninstagram.com/v/t51.2885-15/e15/s640x640/122473135_135858978270197_7757271545185133204_n.jpg?_nc_ht=scontent-ber1-1.cdninstagram.com&_nc_cat=105&_nc_ohc=motAszfBS9YAX9ss9m1&_nc_tp=15&oh=e68747baa3eaccab1187d3e1adc5cf62&oe=5FBE1072", "edge_liked_by": {"count": 780}, "media_preview": "ACoq284qAzfNt/GnucCsqeby5Ax+6OG+h7/hSbGkaqyZNV7iR4XDA5RuMehH+I/lSKwzj15FF8yiAhuvBX1yD2/z0pPVFLR67FpX3DNG4VTti5UccHoT0q1sPotKLbQNWdijc3IX5c8npjqfpWdNKoC7snLfhwcZJ7/Sp4IEdt7/ADN79MegHTFS6hMkaBl6qcADtn37Ubj20JFPyhuKlFyfasqG7Vuuefcf1xU+T5gYYEYHPcn6Dt9aVx2NIS7mwe44NIZWH+RUC/MPX0/mKTeTzincmxipcs3AyfYUtwXYbWGAOcDrUygBgBwOOKepyvPv/Kp2NrX3KYnkjUBQQno358emfWpxIHKhAIwTyck8fjSAZXn1xWen36e5OzsdHHIA3XI9RUZLelRW/MP0JqcE4pCP/9k=", "fact_check_overall_rating": null, "edge_media_to_caption": {"edges": [{"node": {"text": "Jutros malo du\u017ee ostajemo u krevetu \ud83d\ude34 #weekenedvibes #saturdayvibes #saturdaymorning #zadovoljnahr / Pexels"}}]}, "edge_media_to_tagged_user": {"edges": []}, "accessibility_caption": "Photo by zadovoljna.hr on October 24, 2020. Image may contain: indoor.", "location": null}}, {"node": {"__typename": "GraphImage", "taken_at_timestamp": 1603479639, "edge_media_to_comment": {"count": 2}, "dimensions": {"height": 750, "width": 750}, "edge_media_preview_like": {"count": 1133}, "fact_check_information": null, "gating_info": null, "comments_disabled": false, "display_url": "https://scontent-ber1-1.cdninstagram.com/v/t51.2885-15/e15/122417958_2089863834470711_7071292517943672139_n.jpg?_nc_ht=scontent-ber1-1.cdninstagram.com&_nc_cat=111&_nc_ohc=CI_G9h5FHBAAX-ptZIT&_nc_tp=18&oh=365fe375b0ba4fbaad04d7a6d65b3eda&oe=5FBC84C2", "thumbnail_resources": [{"src": "https://scontent-ber1-1.cdninstagram.com/v/t51.2885-15/e15/s150x150/122417958_2089863834470711_7071292517943672139_n.jpg?_nc_ht=scontent-ber1-1.cdninstagram.com&_nc_cat=111&_nc_ohc=CI_G9h5FHBAAX-ptZIT&_nc_tp=15&oh=5e915acb5af4b943c07115d56a5c39e7&oe=5FBE2467", "config_height": 150, "config_width": 150}, {"src": "https://scontent-ber1-1.cdninstagram.com/v/t51.2885-15/e15/s240x240/122417958_2089863834470711_7071292517943672139_n.jpg?_nc_ht=scontent-ber1-1.cdninstagram.com&_nc_cat=111&_nc_ohc=CI_G9h5FHBAAX-ptZIT&_nc_tp=15&oh=5ab28543194181ddf8b9a024fb3bda13&oe=5FBFD82F", "config_height": 240, "config_width": 240}, {"src": "https://scontent-ber1-1.cdninstagram.com/v/t51.2885-15/e15/s320x320/122417958_2089863834470711_7071292517943672139_n.jpg?_nc_ht=scontent-ber1-1.cdninstagram.com&_nc_cat=111&_nc_ohc=CI_G9h5FHBAAX-ptZIT&_nc_tp=15&oh=f160ae87333364c806b9b549215c492a&oe=5FBE7872", "config_height": 320, "config_width": 320}, {"src": "https://scontent-ber1-1.cdninstagram.com/v/t51.2885-15/e15/s480x480/122417958_2089863834470711_7071292517943672139_n.jpg?_nc_ht=scontent-ber1-1.cdninstagram.com&_nc_cat=111&_nc_ohc=CI_G9h5FHBAAX-ptZIT&_nc_tp=15&oh=f3e5a863fc023e8f63a44ada3414d225&oe=5FBE68B4", "config_height": 480, "config_width": 480}, {"src": "https://scontent-ber1-1.cdninstagram.com/v/t51.2885-15/e15/s640x640/122417958_2089863834470711_7071292517943672139_n.jpg?_nc_ht=scontent-ber1-1.cdninstagram.com&_nc_cat=111&_nc_ohc=CI_G9h5FHBAAX-ptZIT&_nc_tp=15&oh=c19f8f8c740dc35f782d916a55a53f73&oe=5FBCB84D", "config_height": 640, "config_width": 640}], "owner": {"id": "1428643188", "username": "zadovoljnahr"}, "shortcode": "CGsm77tqEOC", "is_video": false, "media_overlay_info": null, "id": "2426485543579173762", "thumbnail_src": "https://scontent-ber1-1.cdninstagram.com/v/t51.2885-15/e15/s640x640/122417958_2089863834470711_7071292517943672139_n.jpg?_nc_ht=scontent-ber1-1.cdninstagram.com&_nc_cat=111&_nc_ohc=CI_G9h5FHBAAX-ptZIT&_nc_tp=15&oh=c19f8f8c740dc35f782d916a55a53f73&oe=5FBCB84D", "edge_liked_by": {"count": 1133}, "media_preview": "ACoqijfbyec/54qZmzyfqBVFm2ZB7Zp9sxkHzdeuf6VDNEhXjDHJ7nJqCRM9O9bRs8DI5Pf/AOtVF02Hn+H+dK47FBxt+Qde/wBaTyDVxYtg3t1/r6fX19KrljmqJH3Y7jqeoqvGrxN0OcgGpwhaQIx7ZyeR7/pUkjxIcID9SaT7FLQ2VuAw4/8A1UxIxI+9sHuB2/8Ar1kpOysCTkDtWmsoQ4/L6VnZ9S/QW8hG3eOo7f57/wA6ysLWnNOGXDVklqpMVu5IDwd3Ve/egRDaXx9M56/Sh/vH8ac3RfwqzMryDHI7VYEm4DHUcf4VE3TPfdSsflpDuOZs9aj2+4/Sox96ryouBwPyppCbP//Z", "fact_check_overall_rating": null, "edge_media_to_caption": {"edges": [{"node": {"text": "Nekada petak nave\u010der izgleda i ovako. \u2764\ufe0f #fridaynight #night #weekend #zadovoljnahr / Pexels"}}]}, "edge_media_to_tagged_user": {"edges": []}, "accessibility_caption": "Photo by zadovoljna.hr on October 23, 2020. Image may contain: candles.", "location": null}}, {"node": {"__typename": "GraphImage", "taken_at_timestamp": 1603468815, "edge_media_to_comment": {"count": 16}, "dimensions": {"height": 750, "width": 750}, "edge_media_preview_like": {"count": 1652}, "fact_check_information": null, "gating_info": null, "comments_disabled": false, "display_url": "https://scontent-ber1-1.cdninstagram.com/v/t51.2885-15/e15/122169220_375712366901853_7535694124417294288_n.jpg?_nc_ht=scontent-ber1-1.cdninstagram.com&_nc_cat=109&_nc_ohc=kzB1GOjnZFoAX-HYJKq&_nc_tp=18&oh=79d2a8ea34577e2984f0b0f339bda8e9&oe=5FBEDDCC", "thumbnail_resources": [{"src": "https://scontent-ber1-1.cdninstagram.com/v/t51.2885-15/e15/s150x150/122169220_375712366901853_7535694124417294288_n.jpg?_nc_ht=scontent-ber1-1.cdninstagram.com&_nc_cat=109&_nc_ohc=kzB1GOjnZFoAX-HYJKq&_nc_tp=15&oh=ee9c2b97a2477138197b453b3c63fa6a&oe=5FBDFB21", "config_height": 150, "config_width": 150}, {"src": "https://scontent-ber1-1.cdninstagram.com/v/t51.2885-15/e15/s240x240/122169220_375712366901853_7535694124417294288_n.jpg?_nc_ht=scontent-ber1-1.cdninstagram.com&_nc_cat=109&_nc_ohc=kzB1GOjnZFoAX-HYJKq&_nc_tp=15&oh=5fc5deafa939d8ea3404a727684d0980&oe=5FBCF5A7", "config_height": 240, "config_width": 240}, {"src": "https://scontent-ber1-1.cdninstagram.com/v/t51.2885-15/e15/s320x320/122169220_375712366901853_7535694124417294288_n.jpg?_nc_ht=scontent-ber1-1.cdninstagram.com&_nc_cat=109&_nc_ohc=kzB1GOjnZFoAX-HYJKq&_nc_tp=15&oh=dbc15812ca6c44ebf743026aa1f6466c&oe=5FBBF059", "config_height": 320, "config_width": 320}, {"src": "https://scontent-ber1-1.cdninstagram.com/v/t51.2885-15/e15/s480x480/122169220_375712366901853_7535694124417294288_n.jpg?_nc_ht=scontent-ber1-1.cdninstagram.com&_nc_cat=109&_nc_ohc=kzB1GOjnZFoAX-HYJKq&_nc_tp=15&oh=81fdb7f970e8c903b6bec5554b3460eb&oe=5FBF1CA0", "config_height": 480, "config_width": 480}, {"src": "https://scontent-ber1-1.cdninstagram.com/v/t51.2885-15/e15/s640x640/122169220_375712366901853_7535694124417294288_n.jpg?_nc_ht=scontent-ber1-1.cdninstagram.com&_nc_cat=109&_nc_ohc=kzB1GOjnZFoAX-HYJKq&_nc_tp=15&oh=580bee9fbe7d68314cb2ebd5aebad919&oe=5FBD4364", "config_height": 640, "config_width": 640}], "owner": {"id": "1428643188", "username": "zadovoljnahr"}, "shortcode": "CGsSSq9KlJj", "is_video": false, "media_overlay_info": null, "id": "2426394747156976227", "thumbnail_src": "https://scontent-ber1-1.cdninstagram.com/v/t51.2885-15/e15/s640x640/122169220_375712366901853_7535694124417294288_n.jpg?_nc_ht=scontent-ber1-1.cdninstagram.com&_nc_cat=109&_nc_ohc=kzB1GOjnZFoAX-HYJKq&_nc_tp=15&oh=580bee9fbe7d68314cb2ebd5aebad919&oe=5FBD4364", "edge_liked_by": {"count": 1652}, "media_preview": "ACoq1KSigkDk8CoKEbpUgqm91GOucZ6444q0DkZHQ0APpaBS0xEFMlj3qB/tDP0qXFOUjNIZg3G1Mu+RztC9Mjvz9MnPvVzT3LqT0GRgeh7j+VVb9ctsY5+bn2B5B+hP8qdbTeR8udw3Y+ue4/CgZs7sdaXdRkGkwtBI0DBz60AbjnpSU9aYypJaeazF8EMAOOox7mkjsVVgeoXG0f4nvV400UBcdim4px6UlAj/2Q==", "fact_check_overall_rating": null, "edge_media_to_caption": {"edges": [{"node": {"text": "Ajme, kako je mini \ud83d\udc36\ud83d\ude0d #puppylove #puppiesofinstagram #cutedogs #zadovoljnahr / Pexels"}}]}, "edge_media_to_tagged_user": {"edges": []}, "accessibility_caption": "Photo by zadovoljna.hr on October 23, 2020. Image may contain: dog.", "location": null}}, {"node": {"__typename": "GraphImage", "taken_at_timestamp": 1603458032, "edge_media_to_comment": {"count": 21}, "dimensions": {"height": 1080, "width": 1080}, "edge_media_preview_like": {"count": 2915}, "fact_check_information": null, "gating_info": null, "comments_disabled": false, "display_url": "https://scontent-ber1-1.cdninstagram.com/v/t51.2885-15/fr/e15/s1080x1080/122312214_177211427276536_6479730112884248015_n.jpg?_nc_ht=scontent-ber1-1.cdninstagram.com&_nc_cat=104&_nc_ohc=KGKUX2d1yP0AX9BHe7Y&oh=5d6083ea20b43698e10548239e7b9b73&oe=5FBF9A4C", "thumbnail_resources": [{"src": "https://scontent-ber1-1.cdninstagram.com/v/t51.2885-15/e15/s150x150/122312214_177211427276536_6479730112884248015_n.jpg?_nc_ht=scontent-ber1-1.cdninstagram.com&_nc_cat=104&_nc_ohc=KGKUX2d1yP0AX9BHe7Y&_nc_tp=15&oh=e2bfa1a874581b8e932699c0d0576f76&oe=5FBF0440", "config_height": 150, "config_width": 150}, {"src": "https://scontent-ber1-1.cdninstagram.com/v/t51.2885-15/e15/s240x240/122312214_177211427276536_6479730112884248015_n.jpg?_nc_ht=scontent-ber1-1.cdninstagram.com&_nc_cat=104&_nc_ohc=KGKUX2d1yP0AX9BHe7Y&_nc_tp=15&oh=f3b237048225b2428c468de1f9d8657a&oe=5FBF9CBA", "config_height": 240, "config_width": 240}, {"src": "https://scontent-ber1-1.cdninstagram.com/v/t51.2885-15/e15/s320x320/122312214_177211427276536_6479730112884248015_n.jpg?_nc_ht=scontent-ber1-1.cdninstagram.com&_nc_cat=104&_nc_ohc=KGKUX2d1yP0AX9BHe7Y&_nc_tp=15&oh=8a6235b30abade97f89cb7ee9ba340b2&oe=5FBD50C8", "config_height": 320, "config_width": 320}, {"src": "https://scontent-ber1-1.cdninstagram.com/v/t51.2885-15/e15/s480x480/122312214_177211427276536_6479730112884248015_n.jpg?_nc_ht=scontent-ber1-1.cdninstagram.com&_nc_cat=104&_nc_ohc=KGKUX2d1yP0AX9BHe7Y&_nc_tp=15&oh=aa1e4fe7e7887b4c4505aea7a14982f8&oe=5FBD7481", "config_height": 480, "config_width": 480}, {"src": "https://scontent-ber1-1.cdninstagram.com/v/t51.2885-15/sh0.08/e35/s640x640/122312214_177211427276536_6479730112884248015_n.jpg?_nc_ht=scontent-ber1-1.cdninstagram.com&_nc_cat=104&_nc_ohc=KGKUX2d1yP0AX9BHe7Y&_nc_tp=24&oh=eb8cf37ff5f1feb2f0eb99314b82cd77&oe=5FBE7203", "config_height": 640, "config_width": 640}], "owner": {"id": "1428643188", "username": "zadovoljnahr"}, "shortcode": "CGr9uW0KPHN", "is_video": false, "media_overlay_info": null, "id": "2426304290699669965", "thumbnail_src": "https://scontent-ber1-1.cdninstagram.com/v/t51.2885-15/sh0.08/e35/s640x640/122312214_177211427276536_6479730112884248015_n.jpg?_nc_ht=scontent-ber1-1.cdninstagram.com&_nc_cat=104&_nc_ohc=KGKUX2d1yP0AX9BHe7Y&_nc_tp=24&oh=eb8cf37ff5f1feb2f0eb99314b82cd77&oe=5FBE7203", "edge_liked_by": {"count": 2915}, "media_preview": "ACoq6MCjAoHSloATAowKWigBMCmVJUdADx0phGOgz+NPFBGaAGc/3f1pQM9R+tO2/Wk2/X86AFAplSVHQA8dKWo6KAH80tR0UDJKjopaQH//2Q==", "fact_check_overall_rating": null, "edge_media_to_caption": {"edges": [{"node": {"text": "Izjave dje\u010dice su u isto vrijeme preslatke i presmije\u0161ne \u2764\ufe0f #zadovoljnahr"}}]}, "edge_media_to_tagged_user": {"edges": []}, "accessibility_caption": "Photo by zadovoljna.hr on October 23, 2020. Image may contain: text.", "location": null}}, {"node": {"__typename": "GraphImage", "taken_at_timestamp": 1603448689, "edge_media_to_comment": {"count": 6}, "dimensions": {"height": 1350, "width": 1080}, "edge_media_preview_like": {"count": 997}, "fact_check_information": null, "gating_info": null, "comments_disabled": false, "display_url": "https://scontent-ber1-1.cdninstagram.com/v/t51.2885-15/fr/e15/p1080x1080/122215093_100365908532889_2047769387363958517_n.jpg?_nc_ht=scontent-ber1-1.cdninstagram.com&_nc_cat=101&_nc_ohc=wC_YzVwGEv4AX_AhGKB&oh=f41ca673b35de9fded1f866260731d01&oe=5FBCD74F", "thumbnail_resources": [{"src": "https://scontent-ber1-1.cdninstagram.com/v/t51.2885-15/e15/c0.135.1080.1080a/s150x150/122215093_100365908532889_2047769387363958517_n.jpg?_nc_ht=scontent-ber1-1.cdninstagram.com&_nc_cat=101&_nc_ohc=wC_YzVwGEv4AX_AhGKB&tp=16&oh=23516f4f0f5abd491a8981f55d1015f5&oe=5FBC582E", "config_height": 150, "config_width": 150}, {"src": "https://scontent-ber1-1.cdninstagram.com/v/t51.2885-15/e15/c0.135.1080.1080a/s240x240/122215093_100365908532889_2047769387363958517_n.jpg?_nc_ht=scontent-ber1-1.cdninstagram.com&_nc_cat=101&_nc_ohc=wC_YzVwGEv4AX_AhGKB&tp=16&oh=5d6b91616a138a2e4f15244ff0c2e3ec&oe=5FBC202C", "config_height": 240, "config_width": 240}, {"src": "https://scontent-ber1-1.cdninstagram.com/v/t51.2885-15/e15/c0.135.1080.1080a/s320x320/122215093_100365908532889_2047769387363958517_n.jpg?_nc_ht=scontent-ber1-1.cdninstagram.com&_nc_cat=101&_nc_ohc=wC_YzVwGEv4AX_AhGKB&tp=16&oh=d7c382f935c2309b81b73c71d060f386&oe=5FBFA8D6", "config_height": 320, "config_width": 320}, {"src": "https://scontent-ber1-1.cdninstagram.com/v/t51.2885-15/e15/c0.135.1080.1080a/s480x480/122215093_100365908532889_2047769387363958517_n.jpg?_nc_ht=scontent-ber1-1.cdninstagram.com&_nc_cat=101&_nc_ohc=wC_YzVwGEv4AX_AhGKB&tp=16&oh=48618e309f49f59efa288e35d552cd97&oe=5FBDFA93", "config_height": 480, "config_width": 480}, {"src": "https://scontent-ber1-1.cdninstagram.com/v/t51.2885-15/sh0.08/e35/c0.135.1080.1080a/s640x640/122215093_100365908532889_2047769387363958517_n.jpg?_nc_ht=scontent-ber1-1.cdninstagram.com&_nc_cat=101&_nc_ohc=wC_YzVwGEv4AX_AhGKB&oh=3cf2e4e81dbdf15fbea5447dc64c6a81&oe=5FBF3CFC", "config_height": 640, "config_width": 640}], "owner": {"id": "1428643188", "username": "zadovoljnahr"}, "shortcode": "CGrr52UF72n", "is_video": false, "media_overlay_info": null, "id": "2426225915598454183", "thumbnail_src": "https://scontent-ber1-1.cdninstagram.com/v/t51.2885-15/sh0.08/e35/c0.135.1080.1080a/s640x640/122215093_100365908532889_2047769387363958517_n.jpg?_nc_ht=scontent-ber1-1.cdninstagram.com&_nc_cat=101&_nc_ohc=wC_YzVwGEv4AX_AhGKB&oh=3cf2e4e81dbdf15fbea5447dc64c6a81&oe=5FBF3CFC", "edge_liked_by": {"count": 997}, "media_preview": "ACEqiRAcAdP6/wCentSTsoITGcYJ5/zzU2BG+0cqT+v+elQMmZXz0G4/px+uK5l3Z2FZjnJ7elXPs+ACCcjg/Xr+YzVHDFtucZ6cdfb61eswfnBJYnkk/l+fX8quxMvIZ5Tev8qKl2S/3F/Siq0I18i4gDdO3HTqf89D6VE0YcEr1PDD9eP0p6kn7uM/TPB61KUzyOP6/hT5SebUzxZmQjOQoOT2+lW4QkRwpznknr9MDv8AhSNx8zg4AyP89j/SoUjO7zshgOmP1GfQdKLWBybIPt0vt+tFL5cfp+tFTcqxMs4jQsBk9AAOuOnTsKZEZCyv65Lk8de30AGQBTYDyauDirtci9hk4LAlTnkYPYevp6Zz29ahachQpOcgHOMfX8+v41ISdrf71UZD834UPYFuJvFFQ4oqbFXP/9k=", "fact_check_overall_rating": null, "edge_media_to_caption": {"edges": [{"node": {"text": "Ma petkom se ne broje kalorije \ud83d\ude0b #cake #delicious #foodporn #zadovoljnahr / @marija.h.j"}}]}, "edge_media_to_tagged_user": {"edges": [{"node": {"y": 0.9370370507, "user": {"full_name": "Marija HJ", "id": "16560358942", "username": "marija.h.j", "profile_pic_url": "https://scontent-ber1-1.cdninstagram.com/v/t51.2885-19/s150x150/118072519_114153010261069_7665908767776214109_n.jpg?_nc_ht=scontent-ber1-1.cdninstagram.com&_nc_ohc=T2jV3TT_Kq4AX83ErEZ&oh=7c9ccbfd7750fd9f3013b29b2c7ec6c0&oe=5FBF0931", "is_verified": false}, "x": 0.1333333403}}]}, "accessibility_caption": "Photo shared by zadovoljna.hr on October 23, 2020 tagging @marija.h.j. Image may contain: indoor.", "location": null}}, {"node": {"__typename": "GraphImage", "taken_at_timestamp": 1603437267, "edge_media_to_comment": {"count": 6}, "dimensions": {"height": 1327, "width": 1080}, "edge_media_preview_like": {"count": 1633}, "fact_check_information": null, "gating_info": null, "comments_disabled": false, "display_url": "https://scontent-ber1-1.cdninstagram.com/v/t51.2885-15/e35/121832099_141878247622261_5148796543417883877_n.jpg?_nc_ht=scontent-ber1-1.cdninstagram.com&_nc_cat=101&_nc_ohc=ViAaz16WbGgAX_hO7t2&_nc_tp=18&oh=c141b2a1cc07c55666c668d394c97d37&oe=5FBEF7B7", "thumbnail_resources": [{"src": "https://scontent-ber1-1.cdninstagram.com/v/t51.2885-15/e35/c0.123.1080.1080a/s150x150/121832099_141878247622261_5148796543417883877_n.jpg?_nc_ht=scontent-ber1-1.cdninstagram.com&_nc_cat=101&_nc_ohc=ViAaz16WbGgAX_hO7t2&tp=16&oh=31f1e6a6b3c85ed956b40a735e6cb621&oe=5FBD1D2E", "config_height": 150, "config_width": 150}, {"src": "https://scontent-ber1-1.cdninstagram.com/v/t51.2885-15/e35/c0.123.1080.1080a/s240x240/121832099_141878247622261_5148796543417883877_n.jpg?_nc_ht=scontent-ber1-1.cdninstagram.com&_nc_cat=101&_nc_ohc=ViAaz16WbGgAX_hO7t2&tp=16&oh=d3eb29fe69ace972ab912b3c25cf49d9&oe=5FBD322C", "config_height": 240, "config_width": 240}, {"src": "https://scontent-ber1-1.cdninstagram.com/v/t51.2885-15/e35/c0.123.1080.1080a/s320x320/121832099_141878247622261_5148796543417883877_n.jpg?_nc_ht=scontent-ber1-1.cdninstagram.com&_nc_cat=101&_nc_ohc=ViAaz16WbGgAX_hO7t2&tp=16&oh=a3f3a3023346c13dd3d6736cbd711a1f&oe=5FBD9AD6", "config_height": 320, "config_width": 320}, {"src": "https://scontent-ber1-1.cdninstagram.com/v/t51.2885-15/e35/c0.123.1080.1080a/s480x480/121832099_141878247622261_5148796543417883877_n.jpg?_nc_ht=scontent-ber1-1.cdninstagram.com&_nc_cat=101&_nc_ohc=ViAaz16WbGgAX_hO7t2&tp=16&oh=bc5db9419c382f7c2dcb9c74af8746ac&oe=5FBD3393", "config_height": 480, "config_width": 480}, {"src": "https://scontent-ber1-1.cdninstagram.com/v/t51.2885-15/sh0.08/e35/c0.123.1080.1080a/s640x640/121832099_141878247622261_5148796543417883877_n.jpg?_nc_ht=scontent-ber1-1.cdninstagram.com&_nc_cat=101&_nc_ohc=ViAaz16WbGgAX_hO7t2&oh=1937c56c8333ddd2d74d024f568d137e&oe=5FBDAA9E", "config_height": 640, "config_width": 640}], "owner": {"id": "1428643188", "username": "zadovoljnahr"}, "shortcode": "CGrWHmNn6Ba", "is_video": false, "media_overlay_info": null, "id": "2426130103359479898", "thumbnail_src": "https://scontent-ber1-1.cdninstagram.com/v/t51.2885-15/sh0.08/e35/c0.123.1080.1080a/s640x640/121832099_141878247622261_5148796543417883877_n.jpg?_nc_ht=scontent-ber1-1.cdninstagram.com&_nc_cat=101&_nc_ohc=ViAaz16WbGgAX_hO7t2&oh=1937c56c8333ddd2d74d024f568d137e&oe=5FBDAA9E", "edge_liked_by": {"count": 1633}, "media_preview": "ACIqbIo3lxgKDwvr9KaznLYBAfjjt9aYs6KT5nJHQHp7D8f61DFIyc4OOv4fhUW6myfSxcVt3OfunGDV03aRna2SfQdvrVWM+b0wQevqP0qvNA/mEkZBOQaIqwpu5qfbYvf8qKpCCX1/SiqMikMRnLHKtyD/AEPuKcj7RkAnJ+UfWpTblhjGAfcEZ9c+lL5HkgKQQTzk9/p6D/JqGjdSsLaW42lycZ4Bzgfh6/WtCJQFwOazZLZ7gK0XKjgA8d8kjNW1WS3jA6sOtPzI390u0VAJWx0FFLmQ+R+X3oybcSH7hwPT/wCt/wDqrRiiMv3s56D2Ht9T2qpaH5hWrJxG5HB21RJWjkC/KhHBxjtxUvm7vldfxFYlTqc0r2K5bsvm2Q/x4/GiqNFTfyNLPuf/2Q==", "fact_check_overall_rating": null, "edge_media_to_caption": {"edges": [{"node": {"text": "Kava petkom je posebno slatka \ud83d\ude1c #coffeetime #fridaymood #fridayvibes #zadovoljnahr / @ee_na_na"}}]}, "edge_media_to_tagged_user": {"edges": [{"node": {"y": 0.9037037, "user": {"full_name": "\u1d07\u0274\u1d00", "id": "1077712294", "username": "ee_na_na", "profile_pic_url": "https://scontent-ber1-1.cdninstagram.com/v/t51.2885-19/s150x150/118698039_403072947330858_4209790741161225249_n.jpg?_nc_ht=scontent-ber1-1.cdninstagram.com&_nc_ohc=nKQflIEPe7kAX_tRd9w&oh=2864196a467f931cc9509259d15faa57&oe=5FBC1D3E", "is_verified": false}, "x": 0.07972665}}]}, "accessibility_caption": "Photo shared by zadovoljna.hr on October 23, 2020 tagging @ee_na_na. Image may contain: food and indoor.", "location": null}}, {"node": {"__typename": "GraphImage", "taken_at_timestamp": 1603393217, "edge_media_to_comment": {"count": 13}, "dimensions": {"height": 1350, "width": 1080}, "edge_media_preview_like": {"count": 1840}, "fact_check_information": null, "gating_info": null, "comments_disabled": false, "display_url": "https://scontent-ber1-1.cdninstagram.com/v/t51.2885-15/fr/e15/p1080x1080/122097377_2706586332949269_745478487719977588_n.jpg?_nc_ht=scontent-ber1-1.cdninstagram.com&_nc_cat=109&_nc_ohc=rXS6_aaA778AX9zotYy&oh=94a1b457b77e614b23b0e7bd2142a41a&oe=5FBF73B4", "thumbnail_resources": [{"src": "https://scontent-ber1-1.cdninstagram.com/v/t51.2885-15/e15/c0.135.1080.1080a/s150x150/122097377_2706586332949269_745478487719977588_n.jpg?_nc_ht=scontent-ber1-1.cdninstagram.com&_nc_cat=109&_nc_ohc=rXS6_aaA778AX9zotYy&tp=16&oh=ccae634b5784ab1c124c96b261805437&oe=5FBCD9D1", "config_height": 150, "config_width": 150}, {"src": "https://scontent-ber1-1.cdninstagram.com/v/t51.2885-15/e15/c0.135.1080.1080a/s240x240/122097377_2706586332949269_745478487719977588_n.jpg?_nc_ht=scontent-ber1-1.cdninstagram.com&_nc_cat=109&_nc_ohc=rXS6_aaA778AX9zotYy&tp=16&oh=e66ebb0459ed649489bcd30e60473fa2&oe=5FBCCDD7", "config_height": 240, "config_width": 240}, {"src": "https://scontent-ber1-1.cdninstagram.com/v/t51.2885-15/e15/c0.135.1080.1080a/s320x320/122097377_2706586332949269_745478487719977588_n.jpg?_nc_ht=scontent-ber1-1.cdninstagram.com&_nc_cat=109&_nc_ohc=rXS6_aaA778AX9zotYy&tp=16&oh=5be52fa0513c41987b5a145a870377e6&oe=5FBDA229", "config_height": 320, "config_width": 320}, {"src": "https://scontent-ber1-1.cdninstagram.com/v/t51.2885-15/e15/c0.135.1080.1080a/s480x480/122097377_2706586332949269_745478487719977588_n.jpg?_nc_ht=scontent-ber1-1.cdninstagram.com&_nc_cat=109&_nc_ohc=rXS6_aaA778AX9zotYy&tp=16&oh=ef9dfaeac3bb4537d7896ffe2c744a10&oe=5FBE4770", "config_height": 480, "config_width": 480}, {"src": "https://scontent-ber1-1.cdninstagram.com/v/t51.2885-15/sh0.08/e35/c0.135.1080.1080a/s640x640/122097377_2706586332949269_745478487719977588_n.jpg?_nc_ht=scontent-ber1-1.cdninstagram.com&_nc_cat=109&_nc_ohc=rXS6_aaA778AX9zotYy&oh=605df7a4ad4d97a19454b13c564108e9&oe=5FBE1107", "config_height": 640, "config_width": 640}], "owner": {"id": "1428643188", "username": "zadovoljnahr"}, "shortcode": "CGqCGUeKaMu", "is_video": false, "media_overlay_info": null, "id": "2425760579683197742", "thumbnail_src": "https://scontent-ber1-1.cdninstagram.com/v/t51.2885-15/sh0.08/e35/c0.135.1080.1080a/s640x640/122097377_2706586332949269_745478487719977588_n.jpg?_nc_ht=scontent-ber1-1.cdninstagram.com&_nc_cat=109&_nc_ohc=rXS6_aaA778AX9zotYy&oh=605df7a4ad4d97a19454b13c564108e9&oe=5FBE1107", "edge_liked_by": {"count": 1840}, "media_preview": "ACEqFccA0OFbhgG9+/51BtxyO1PJAHb+v5VFirkL2qt0OPr/AI/45rOdNvJ9cZrXdmAHGfes9xg7TjAOfzpj3KuBRU3lmimFjUSNR2H5VOoA6DH0xVOKLJDDJPX6ZqUsOVPJPAGO/b2p3M+UtSSbAM9z+XuetZs4V1LLzhsVobg+M8H0P+cVlTDyWyOc5/Wp3NUrIh3fWiosD1ophdmhCwjx1KuOvv3H8v8A9dKYTy2R9T/+ukm/1K/UVRcnOO2elMksSXLHI79M/wCFMlbII78fn/nrUD9fzpopFXJNtFNooA//2Q==", "fact_check_overall_rating": null, "edge_media_to_caption": {"edges": [{"node": {"text": "Malo zavidimo na ovom #cozy ugo\u0111aju \ud83d\ude0a #vacation #relaxingtime #zadovoljnahr / @take.you.to"}}]}, "edge_media_to_tagged_user": {"edges": [{"node": {"y": 0.935185194, "user": {"full_name": "Sandra | Croatia", "id": "50862615", "username": "take.you.to", "profile_pic_url": "https://scontent-ber1-1.cdninstagram.com/v/t51.2885-19/s150x150/82075801_199507144524896_6287080231484260352_n.jpg?_nc_ht=scontent-ber1-1.cdninstagram.com&_nc_ohc=C38K3OQiZV8AX_NfzuG&oh=966b999ea9fabc58ca0f4a512823f05e&oe=5FBC4D5F", "is_verified": false}, "x": 0.0962962955}}]}, "accessibility_caption": "Photo shared by zadovoljna.hr on October 22, 2020 tagging @take.you.to. Image may contain: people sitting and table.", "location": null}}, {"node": {"__typename": "GraphImage", "taken_at_timestamp": 1603382411, "edge_media_to_comment": {"count": 1}, "dimensions": {"height": 1350, "width": 1080}, "edge_media_preview_like": {"count": 1489}, "fact_check_information": null, "gating_info": null, "comments_disabled": false, "display_url": "https://scontent-ber1-1.cdninstagram.com/v/t51.2885-15/fr/e15/p1080x1080/122207090_1671546323014163_6151612404103040080_n.jpg?_nc_ht=scontent-ber1-1.cdninstagram.com&_nc_cat=111&_nc_ohc=YQZFzFXUNbQAX_qX8NS&oh=0350042b3d067dda738484be88cae03e&oe=5FBFBF80", "thumbnail_resources": [{"src": "https://scontent-ber1-1.cdninstagram.com/v/t51.2885-15/e15/c0.135.1080.1080a/s150x150/122207090_1671546323014163_6151612404103040080_n.jpg?_nc_ht=scontent-ber1-1.cdninstagram.com&_nc_cat=111&_nc_ohc=YQZFzFXUNbQAX_qX8NS&tp=16&oh=40ed6085342117f65ed6be406a0b3a3c&oe=5FBC4449", "config_height": 150, "config_width": 150}, {"src": "https://scontent-ber1-1.cdninstagram.com/v/t51.2885-15/e15/c0.135.1080.1080a/s240x240/122207090_1671546323014163_6151612404103040080_n.jpg?_nc_ht=scontent-ber1-1.cdninstagram.com&_nc_cat=111&_nc_ohc=YQZFzFXUNbQAX_qX8NS&tp=16&oh=6912b756f5753b5f9406a91320e0b148&oe=5FBD4381", "config_height": 240, "config_width": 240}, {"src": "https://scontent-ber1-1.cdninstagram.com/v/t51.2885-15/e15/c0.135.1080.1080a/s320x320/122207090_1671546323014163_6151612404103040080_n.jpg?_nc_ht=scontent-ber1-1.cdninstagram.com&_nc_cat=111&_nc_ohc=YQZFzFXUNbQAX_qX8NS&tp=16&oh=772bf9cfbc2558c367adc921c2281948&oe=5FBE66E0", "config_height": 320, "config_width": 320}, {"src": "https://scontent-ber1-1.cdninstagram.com/v/t51.2885-15/e15/c0.135.1080.1080a/s480x480/122207090_1671546323014163_6151612404103040080_n.jpg?_nc_ht=scontent-ber1-1.cdninstagram.com&_nc_cat=111&_nc_ohc=YQZFzFXUNbQAX_qX8NS&tp=16&oh=6b2b13ed63c7157c453868257887a58a&oe=5FBF611E", "config_height": 480, "config_width": 480}, {"src": "https://scontent-ber1-1.cdninstagram.com/v/t51.2885-15/sh0.08/e35/c0.135.1080.1080a/s640x640/122207090_1671546323014163_6151612404103040080_n.jpg?_nc_ht=scontent-ber1-1.cdninstagram.com&_nc_cat=111&_nc_ohc=YQZFzFXUNbQAX_qX8NS&oh=185b8688fe7f918435fa14f2ab40303d&oe=5FBE9A6D", "config_height": 640, "config_width": 640}], "owner": {"id": "1428643188", "username": "zadovoljnahr"}, "shortcode": "CGptfRiqWCZ", "is_video": false, "media_overlay_info": null, "id": "2425669935547637913", "thumbnail_src": "https://scontent-ber1-1.cdninstagram.com/v/t51.2885-15/sh0.08/e35/c0.135.1080.1080a/s640x640/122207090_1671546323014163_6151612404103040080_n.jpg?_nc_ht=scontent-ber1-1.cdninstagram.com&_nc_cat=111&_nc_ohc=YQZFzFXUNbQAX_qX8NS&oh=185b8688fe7f918435fa14f2ab40303d&oe=5FBE9A6D", "edge_liked_by": {"count": 1489}, "media_preview": "ACEqCDnJXnvg057kBQBkHGOlU5pmWQgMOuMED/8AXVq4QuoC8HI5qSysiFySDt9fX8fT6Us0ZU8kH36fr0z+VSMojzzuzz+P4dqq3c7I428DHI9eaEDH7m9T/wB9D/GijzPYUUXCwkvLn/eP8q0OpHtzVN59u7K52Yzx6n9KuwDPzYGQvT3NA9iNhyPTH+FZlyxbluCOOmO/+eavB3lQuAFK8Hv9Rj2OPzqrdglQT6en6ULQHqLuoqHJooA2dmckk89enOPwpyrtyMn5hzk/y96KYaZIqoseSOM9ff6/40pUMADyB0pBS0CGeSnpRS0UwP/Z", "fact_check_overall_rating": null, "edge_media_to_caption": {"edges": [{"node": {"text": "Ostavio nas je bez teksta ovaj divan #outfit drage @jelenamarinovic \ud83d\ude0d #ootd #autumnoutfit #zadovoljnahr"}}]}, "edge_media_to_tagged_user": {"edges": [{"node": {"y": 0.9777777791, "user": {"full_name": "", "id": "330396214", "username": "jelenamarinovic", "profile_pic_url": "https://scontent-ber1-1.cdninstagram.com/v/t51.2885-19/s150x150/117439000_191869938971547_21664001807167046_n.jpg?_nc_ht=scontent-ber1-1.cdninstagram.com&_nc_ohc=840MM5pWtpMAX9m_WhS&oh=91c130f68b9525302a92e8f6e5f2ba00&oe=5FBEFB9E", "is_verified": false}, "x": 0.1351851821}}]}, "accessibility_caption": "Photo shared by zadovoljna.hr on October 22, 2020 tagging @jelenamarinovic. Image may contain: 1 person, standing, shoes and outdoor.", "location": null}}, {"node": {"__typename": "GraphImage", "taken_at_timestamp": 1603371646, "edge_media_to_comment": {"count": 5}, "dimensions": {"height": 1080, "width": 1080}, "edge_media_preview_like": {"count": 800}, "fact_check_information": null, "gating_info": null, "comments_disabled": false, "display_url": "https://scontent-ber1-1.cdninstagram.com/v/t51.2885-15/fr/e15/s1080x1080/122372683_1033149037148241_3776094678275513626_n.jpg?_nc_ht=scontent-ber1-1.cdninstagram.com&_nc_cat=109&_nc_ohc=pxrR5zlBtFEAX_s3VF2&oh=6f9651c230e8bb6e15fcb7329f3690a4&oe=5FBC20E7", "thumbnail_resources": [{"src": "https://scontent-ber1-1.cdninstagram.com/v/t51.2885-15/e15/s150x150/122372683_1033149037148241_3776094678275513626_n.jpg?_nc_ht=scontent-ber1-1.cdninstagram.com&_nc_cat=109&_nc_ohc=pxrR5zlBtFEAX_s3VF2&_nc_tp=15&oh=5a4fc916cf687e197ab708d9b5e54a84&oe=5FBEAC7D", "config_height": 150, "config_width": 150}, {"src": "https://scontent-ber1-1.cdninstagram.com/v/t51.2885-15/e15/s240x240/122372683_1033149037148241_3776094678275513626_n.jpg?_nc_ht=scontent-ber1-1.cdninstagram.com&_nc_cat=109&_nc_ohc=pxrR5zlBtFEAX_s3VF2&_nc_tp=15&oh=d616074ab27baef4abdecf00c8cc5ef2&oe=5FBC9335", "config_height": 240, "config_width": 240}, {"src": "https://scontent-ber1-1.cdninstagram.com/v/t51.2885-15/e15/s320x320/122372683_1033149037148241_3776094678275513626_n.jpg?_nc_ht=scontent-ber1-1.cdninstagram.com&_nc_cat=109&_nc_ohc=pxrR5zlBtFEAX_s3VF2&_nc_tp=15&oh=3aea7bbc5735c52ce020d7466deb15d9&oe=5FBCD16C", "config_height": 320, "config_width": 320}, {"src": "https://scontent-ber1-1.cdninstagram.com/v/t51.2885-15/e15/s480x480/122372683_1033149037148241_3776094678275513626_n.jpg?_nc_ht=scontent-ber1-1.cdninstagram.com&_nc_cat=109&_nc_ohc=pxrR5zlBtFEAX_s3VF2&_nc_tp=15&oh=756f9b390505c84cab4d56a961c4039a&oe=5FBF402A", "config_height": 480, "config_width": 480}, {"src": "https://scontent-ber1-1.cdninstagram.com/v/t51.2885-15/sh0.08/e35/s640x640/122372683_1033149037148241_3776094678275513626_n.jpg?_nc_ht=scontent-ber1-1.cdninstagram.com&_nc_cat=109&_nc_ohc=pxrR5zlBtFEAX_s3VF2&_nc_tp=24&oh=df4969453eb7ab7df9b562516aeeebff&oe=5FBE25E3", "config_height": 640, "config_width": 640}], "owner": {"id": "1428643188", "username": "zadovoljnahr"}, "shortcode": "CGpY9M_KeEe", "is_video": false, "media_overlay_info": null, "id": "2425579633264681246", "thumbnail_src": "https://scontent-ber1-1.cdninstagram.com/v/t51.2885-15/sh0.08/e35/s640x640/122372683_1033149037148241_3776094678275513626_n.jpg?_nc_ht=scontent-ber1-1.cdninstagram.com&_nc_cat=109&_nc_ohc=pxrR5zlBtFEAX_s3VF2&_nc_tp=24&oh=df4969453eb7ab7df9b562516aeeebff&oe=5FBE25E3", "edge_liked_by": {"count": 800}, "media_preview": "ACoq1YJCy5PQUnU59TTmx0HHrRUlFaRMg/X+tR2ww34f1qywyPxNVIT84/GkX0Zp5pm8U1qZTuRYdnmmSSbe/wDnFMkfZ+H+NKSJODxkHHrkfypDS6kQnKNiQgBgSAB1x1XOetJ5TLiTjae31qOeFmwCeBjjsfUjv+FaKjIAHakinpsRg7hmmb19RVhjyKb5a+lURcrLBu+Zz26/5/WgBh8w/h5H+fpUrfc/Kj+A/SpKuK4DgZ6A5yO3/wBY0ikphRzUidAPaox98/SmBJt3e49PejkcY6Ug6CpKZJ//2Q==", "fact_check_overall_rating": null, "edge_media_to_caption": {"edges": [{"node": {"text": "Mala princezica \ud83d\ude0d #littlegirl #babygirl #kidsinterior #zadovoljnahr / @mamartiina"}}]}, "edge_media_to_tagged_user": {"edges": [{"node": {"y": 0.9388889074, "user": {"full_name": "Martina\ud83d\udd38Motherhood & Lifestyle", "id": "2021324179", "username": "mamartiina", "profile_pic_url": "https://scontent-ber1-1.cdninstagram.com/v/t51.2885-19/s150x150/72272460_423494284974034_7713898217238167552_n.jpg?_nc_ht=scontent-ber1-1.cdninstagram.com&_nc_ohc=jLGuNJrjeeYAX80NQF4&oh=3844b29365b02d09b988355e25c25f32&oe=5FBC90CF", "is_verified": false}, "x": 0.1018518507}}]}, "accessibility_caption": "Photo shared by zadovoljna.hr on October 22, 2020 tagging @mamartiina. Image may contain: 1 person, wedding.", "location": null}}], "page_info": {"has_next_page": true, "end_cursor": "QVFBVkEyM29YZjhzNWVIOHM0OWVZTU0yMmxfdnJNbVV2V0tydU1NNG42VDZ0MVZyd1FMel92X3BVU1FFLURrTl9nb1d3VTYteHR4ZjRYTlZtNEZlYmtmdA=="}}, "highlight_reel_count": 8, "connected_fb_page": null, "edge_follow": {"count": 1495}, "is_business_account": true, "requested_by_viewer": false, "is_private": false, "business_category_name": "Publishers", "business_email": "zadovoljna@novatv.hr", "is_verified": true, "profile_pic_url": "https://scontent-ber1-1.cdninstagram.com/v/t51.2885-19/s150x150/120371870_880788195782341_1724391512413504889_n.jpg?_nc_ht=scontent-ber1-1.cdninstagram.com&_nc_ohc=yRO7cWLpN0wAX8KpPAH&oh=6f1aee731594c51612df378be658f77b&oe=5FBD65D7", "country_block": false, "overall_category_name": null, "has_ar_effects": false, "follows_viewer": false, "has_guides": false, "profile_pic_url_hd": "https://scontent-ber1-1.cdninstagram.com/v/t51.2885-19/s320x320/120371870_880788195782341_1724391512413504889_n.jpg?_nc_ht=scontent-ber1-1.cdninstagram.com&_nc_ohc=yRO7cWLpN0wAX8KpPAH&oh=35aeadde99e57da98755aff7f922f31f&oe=5FBD2E2F", "has_blocked_viewer": false, "followed_by_viewer": false, "full_name": "zadovoljna.hr", "restricted_by_viewer": null, "has_requested_viewer": false, "has_clips": false, "category_enum": "NEWS_SITE", "external_url_linkshimmed": "https://l.instagram.com/?u=https%3A%2F%2Fzadovoljna.dnevnik.hr%2F&e=ATOZBiymp62AzQFPNonEtj9C7_ZT3N3ZJxRHFNpFKhyJHw35JcI4qvYVDArr3hYsJDsY47_9LF-4LDGh&s=1", "edge_saved_media": {"count": 0, "edges": [], "page_info": {"has_next_page": false, "end_cursor": null}}, "edge_media_collections": {"count": 0, "edges": [], "page_info": {"has_next_page": false, "end_cursor": null}}, "edge_related_profiles": {"edges": [{"node": {"full_name": "miss7", "profile_pic_url": "https://scontent-ber1-1.cdninstagram.com/v/t51.2885-19/s150x150/18722902_1687714104867885_1098139630538063872_a.jpg?_nc_ht=scontent-ber1-1.cdninstagram.com&_nc_ohc=qrE2OurfXRkAX-MyQc-&oh=29e1c9978d9a6eb8928150cbb5146cdf&oe=5FBE55D0", "is_verified": false, "id": "256040562", "username": "miss7.hr", "is_private": false}}, {"node": {"full_name": "\u017eena.hr", "profile_pic_url": "https://scontent-ber1-1.cdninstagram.com/v/t51.2885-19/s150x150/42003943_293301664609456_4371028564061978624_n.jpg?_nc_ht=scontent-ber1-1.cdninstagram.com&_nc_ohc=6xg9X_PUsaAAX9rAhCC&oh=7ea470b86fef632cf0b5054e0d4bc94b&oe=5FBDE261", "is_verified": false, "id": "2086118460", "username": "zenahr", "is_private": false}}, {"node": {"full_name": "Ella Dvornik-Pearce", "profile_pic_url": "https://scontent-ber1-1.cdninstagram.com/v/t51.2885-19/s150x150/69455478_505001186930893_713156027893153792_n.jpg?_nc_ht=scontent-ber1-1.cdninstagram.com&_nc_ohc=I-8C0fanpekAX-mKX8W&oh=2ffcd1e3ad9a3135062dbca37a951f3f&oe=5FBF0C17", "is_verified": true, "id": "174973641", "username": "elladvornik", "is_private": false}}, {"node": {"full_name": "\u25c7\u1d0a\u1d0f\u1d1c\u0280\u0274\u1d00\u029f", "profile_pic_url": "https://scontent-ber1-1.cdninstagram.com/v/t51.2885-19/s150x150/12357774_561605820672308_1784832480_a.jpg?_nc_ht=scontent-ber1-1.cdninstagram.com&_nc_ohc=wProimfYY2kAX8TWfBy&oh=b22727038b704659f03a32751f610242&oe=5FBDFBC8", "is_verified": false, "id": "1678098113", "username": "journal.hr", "is_private": false}}, {"node": {"full_name": "Marijana Batinic", "profile_pic_url": "https://scontent-ber1-1.cdninstagram.com/v/t51.2885-19/s150x150/119220030_446222456298170_8358621088962043634_n.jpg?_nc_ht=scontent-ber1-1.cdninstagram.com&_nc_ohc=cRV1lDWDoRQAX-4oEFz&oh=45be925f7c4458443f37ef15714c182f&oe=5FBD0FB5", "is_verified": false, "id": "243209139", "username": "marijanabatinic", "is_private": false}}, {"node": {"full_name": "missZDRAVA", "profile_pic_url": "https://scontent-ber1-1.cdninstagram.com/v/t51.2885-19/s150x150/43913008_288010178710351_261456507806154752_n.jpg?_nc_ht=scontent-ber1-1.cdninstagram.com&_nc_ohc=wtEb8AxPF4YAX8hZZow&oh=a4aca35d2aa94f46962de98a561009cb&oe=5FBC7090", "is_verified": false, "id": "1072651755", "username": "misszdrava", "is_private": false}}, {"node": {"full_name": "FASHION.HR", "profile_pic_url": "https://scontent-ber1-1.cdninstagram.com/v/t51.2885-19/s150x150/65007712_479565102610388_6949693286101549056_n.jpg?_nc_ht=scontent-ber1-1.cdninstagram.com&_nc_ohc=7HqKYjet0M4AX9NRYju&oh=d9adf676479eaeb643103fdd93dcd36a&oe=5FBDEF08", "is_verified": false, "id": "228933693", "username": "fashionhr", "is_private": false}}, {"node": {"full_name": "Alis Maric\u0301 Booklover&Traveler", "profile_pic_url": "https://scontent-ber1-1.cdninstagram.com/v/t51.2885-19/s150x150/73188176_671097770082128_4674184767611076608_n.jpg?_nc_ht=scontent-ber1-1.cdninstagram.com&_nc_ohc=5pSSxj7JMV4AX-7O_sI&oh=1f3ee338b70094e129ab3d06a646cfe3&oe=5FBD910F", "is_verified": false, "id": "670646291", "username": "citaj_knjigu", "is_private": false}}, {"node": {"full_name": "Cosmopolitan Hrvatska", "profile_pic_url": "https://scontent-ber1-1.cdninstagram.com/v/t51.2885-19/12940898_1046114512150035_871269377_a.jpg?_nc_ht=scontent-ber1-1.cdninstagram.com&_nc_ohc=fn1deQpDuGYAX8ddtuF&oh=b1bea00a57fad25124b8c0a572c8d847&oe=5FBF91C4", "is_verified": false, "id": "1273628408", "username": "cosmopolitanhrvatska", "is_private": false}}, {"node": {"full_name": "majasuput", "profile_pic_url": "https://scontent-ber1-1.cdninstagram.com/v/t51.2885-19/s150x150/74968673_558347948313134_9168086131193937920_n.jpg?_nc_ht=scontent-ber1-1.cdninstagram.com&_nc_ohc=8OP0eYkBUWsAX8kJ7wK&oh=83c60abc3fc2ea436fbd368d414a6846&oe=5FBC9A8D", "is_verified": true, "id": "144689288", "username": "majasuput", "is_private": false}}, {"node": {"full_name": "CroModa", "profile_pic_url": "https://scontent-ber1-1.cdninstagram.com/v/t51.2885-19/s150x150/14334614_598025293703935_255528286_a.jpg?_nc_ht=scontent-ber1-1.cdninstagram.com&_nc_ohc=qxeSvfB01iMAX8vw1Qy&oh=8f0ab1f92d5fbc0f955d9bf41206335b&oe=5FBE5662", "is_verified": false, "id": "208936888", "username": "cromoda", "is_private": false}}, {"node": {"full_name": "Nina Badric\u0301", "profile_pic_url": "https://scontent-ber1-1.cdninstagram.com/v/t51.2885-19/s150x150/106801611_651128645487013_5541688212110727149_n.jpg?_nc_ht=scontent-ber1-1.cdninstagram.com&_nc_ohc=DCJytYJUGM0AX_uNgjx&oh=debcce690004ea0e3808fe0f5adbc62e&oe=5FBEA4BD", "is_verified": true, "id": "39626701", "username": "badrich", "is_private": false}}, {"node": {"full_name": "Story", "profile_pic_url": "https://scontent-ber1-1.cdninstagram.com/v/t51.2885-19/s150x150/12070798_1648122292131801_35105642_a.jpg?_nc_ht=scontent-ber1-1.cdninstagram.com&_nc_ohc=Vr3sWtmyv6wAX_7W5ap&oh=c51078aae521b75e9610848485e4d68a&oe=5FBD5E7E", "is_verified": false, "id": "1725934111", "username": "story.hr", "is_private": false}}, {"node": {"full_name": "Gloria.hr", "profile_pic_url": "https://scontent-ber1-1.cdninstagram.com/v/t51.2885-19/s150x150/61923692_459415041282092_8963717065965830144_n.jpg?_nc_ht=scontent-ber1-1.cdninstagram.com&_nc_ohc=ihqgSRxBe_EAX8hpUc8&oh=4ff1e8c1c9ab14f143e23903b24e7b37&oe=5FBC69E8", "is_verified": false, "id": "4136711514", "username": "gloria.hr", "is_private": false}}, {"node": {"full_name": "\uff2c\uff41\uff4e\uff41   \uff2b\uff4c\uff49\uff4e\uff47\uff4f\uff52   \uff2d\uff49\uff48\uff49c\u0301", "profile_pic_url": "https://scontent-ber1-1.cdninstagram.com/v/t51.2885-19/s150x150/108165045_594588614812874_6343515897890695102_n.jpg?_nc_ht=scontent-ber1-1.cdninstagram.com&_nc_ohc=H8n____Z7tIAX8p7jBN&oh=3ce03bfef26bc191b94e026b1b48521b&oe=5FBCC0D8", "is_verified": true, "id": "205888584", "username": "lanatheklingor", "is_private": false}}, {"node": {"full_name": "*Style Zagreb*", "profile_pic_url": "https://scontent-ber1-1.cdninstagram.com/v/t51.2885-19/12120339_1686593478281402_821346187_a.jpg?_nc_ht=scontent-ber1-1.cdninstagram.com&_nc_ohc=e_14ulVTuDgAX9_7AO2&oh=41222cfe76f78c50aaadf0c2184c0774&oe=5FBE9741", "is_verified": false, "id": "1119447096", "username": "stylezagreb", "is_private": false}}, {"node": {"full_name": "Andrea Andrassy", "profile_pic_url": "https://scontent-ber1-1.cdninstagram.com/v/t51.2885-19/s150x150/101496081_251333989405816_7327640654278819840_n.jpg?_nc_ht=scontent-ber1-1.cdninstagram.com&_nc_ohc=pwG_vQ3cKrEAX8msqHC&oh=18110af82ff3763d3466a158fbe89706&oe=5FBF8256", "is_verified": true, "id": "19924237", "username": "andreaandrassy", "is_private": false}}, {"node": {"full_name": "dm Hrvatska", "profile_pic_url": "https://scontent-ber1-1.cdninstagram.com/v/t51.2885-19/s150x150/42484975_2124412087653733_4930689212484681728_n.jpg?_nc_ht=scontent-ber1-1.cdninstagram.com&_nc_ohc=I9V_R6cxC_MAX_jNLmW&oh=d532bae543997745cab433e5c13c7dd8&oe=5FBC61B0", "is_verified": false, "id": "2102289688", "username": "dm_hrvatska", "is_private": false}}, {"node": {"full_name": "F R A N K A", "profile_pic_url": "https://scontent-ber1-1.cdninstagram.com/v/t51.2885-19/s150x150/118591981_309353870296872_109169185491672056_n.jpg?_nc_ht=scontent-ber1-1.cdninstagram.com&_nc_ohc=aiMb96DCw_MAX8ErrJe&oh=3334cb1eb73c50f413953cbfe825388e&oe=5FBD6045", "is_verified": true, "id": "646060092", "username": "frankaofficial_", "is_private": false}}, {"node": {"full_name": "BURO. Hrvatska", "profile_pic_url": "https://scontent-ber1-1.cdninstagram.com/v/t51.2885-19/s150x150/43105606_337590330139884_5138316036176609280_n.jpg?_nc_ht=scontent-ber1-1.cdninstagram.com&_nc_ohc=ZFPtLB6mEL8AX9l519f&oh=72b4e46550b9b7f01b63b9a364eecf28&oe=5FBEDD34", "is_verified": false, "id": "386884865", "username": "buro247hr", "is_private": false}}, {"node": {"full_name": "Jolie.hr", "profile_pic_url": "https://scontent-ber1-1.cdninstagram.com/v/t51.2885-19/s150x150/41214789_479461665888698_3686338557204496384_n.jpg?_nc_ht=scontent-ber1-1.cdninstagram.com&_nc_ohc=H47yGV2TWh4AX-V8SZg&oh=f1fa056f6c888aa358f40f3001d95421&oe=5FBFAAB6", "is_verified": false, "id": "2001324451", "username": "jolie.hr", "is_private": false}}, {"node": {"full_name": "ljupkagojicmikic", "profile_pic_url": "https://scontent-ber1-1.cdninstagram.com/v/t51.2885-19/s150x150/118336965_923475854804030_3280165814215722352_n.jpg?_nc_ht=scontent-ber1-1.cdninstagram.com&_nc_ohc=ZODxBaYihQUAX_3tk-h&oh=7e09a87e708cc689aeca734c40e6e344&oe=5FBEDF05", "is_verified": false, "id": "182280313", "username": "ljupkagojicmikic", "is_private": false}}, {"node": {"full_name": "Severina", "profile_pic_url": "https://scontent-ber1-1.cdninstagram.com/v/t51.2885-19/s150x150/21689843_308451449563690_7436589328739860480_n.jpg?_nc_ht=scontent-ber1-1.cdninstagram.com&_nc_ohc=Unq1ynnjnrgAX_y91Ae&oh=f106296e86ac29984b0c6766464d3f0b&oe=5FBE0BEE", "is_verified": true, "id": "1550811295", "username": "severina", "is_private": false}}, {"node": {"full_name": "DNEVNIK.hr", "profile_pic_url": "https://scontent-ber1-1.cdninstagram.com/v/t51.2885-19/s150x150/80591709_594524208048662_3589295910045089792_n.jpg?_nc_ht=scontent-ber1-1.cdninstagram.com&_nc_ohc=ZW6P06yUDQQAX-4SUYG&oh=cc6c005bd07655704edf5a360a5225b2&oe=5FBF1E82", "is_verified": true, "id": "3161790736", "username": "dnevnikhr", "is_private": false}}, {"node": {"full_name": "Doris Pin\u010di\u0107 Rogoznica", "profile_pic_url": "https://scontent-ber1-1.cdninstagram.com/v/t51.2885-19/s150x150/66142526_2421038914838865_5853605438750195712_n.jpg?_nc_ht=scontent-ber1-1.cdninstagram.com&_nc_ohc=ZF490GzirGwAX_6CMMJ&oh=f5b4d79a12f5eb2e89656dcb195050c4&oe=5FBED6B8", "is_verified": false, "id": "1741422208", "username": "dorispincicrogoznica_doda", "is_private": false}}, {"node": {"full_name": "Croatia Full Of life", "profile_pic_url": "https://scontent-ber1-1.cdninstagram.com/v/t51.2885-19/s150x150/94305595_1065089157207421_748873890754723840_n.jpg?_nc_ht=scontent-ber1-1.cdninstagram.com&_nc_ohc=IHvPWFGIuDgAX9mZ0xi&oh=5ec9cbaad1ce1dd6c38a782620e19a52&oe=5FBCD4AE", "is_verified": true, "id": "266897135", "username": "croatiafulloflife", "is_private": false}}, {"node": {"full_name": "InDizajn s Mirjanom Mikulec", "profile_pic_url": "https://scontent-ber1-1.cdninstagram.com/v/t51.2885-19/s150x150/90089550_672922440111606_1210971277557235712_n.jpg?_nc_ht=scontent-ber1-1.cdninstagram.com&_nc_ohc=-8tEvD3wjaAAX_b6Qj2&oh=3b3fff811f5324f3a2eee52baf3fa9fe&oe=5FBE192A", "is_verified": false, "id": "1649478342", "username": "in_dizajn", "is_private": false}}, {"node": {"full_name": "narodni", "profile_pic_url": "https://scontent-ber1-1.cdninstagram.com/v/t51.2885-19/s150x150/81123876_1589276027895434_2301354854288719872_n.jpg?_nc_ht=scontent-ber1-1.cdninstagram.com&_nc_ohc=fXUj0ioz14gAX8EPnb_&oh=cfea81cdcd94415da6c002eeabba283d&oe=5FBD55CB", "is_verified": false, "id": "2221584077", "username": "narodni.official", "is_private": false}}, {"node": {"full_name": "Mirjana Mikulec", "profile_pic_url": "https://scontent-ber1-1.cdninstagram.com/v/t51.2885-19/s150x150/102815003_1206467353028832_4707724248829919232_n.jpg?_nc_ht=scontent-ber1-1.cdninstagram.com&_nc_ohc=jgMai2edRqkAX8roxGa&oh=fc1649e3d0856251056843f2c36ab31c&oe=5FBD7FDC", "is_verified": false, "id": "286062997", "username": "mirjana_mikulec", "is_private": false}}, {"node": {"full_name": "punkufer.hr", "profile_pic_url": "https://scontent-ber1-1.cdninstagram.com/v/t51.2885-19/s150x150/116363760_2957924244333449_9203483095679003863_n.jpg?_nc_ht=scontent-ber1-1.cdninstagram.com&_nc_ohc=KhBHGPUDrWgAX-IRRC2&oh=8715188ff464a24c6dfc9029f3831779&oe=5FBE401C", "is_verified": false, "id": "2116355154", "username": "punkuferhr", "is_private": false}}, {"node": {"full_name": "Mass Shoes", "profile_pic_url": "https://scontent-ber1-1.cdninstagram.com/v/t51.2885-19/s150x150/11324524_546354635520529_1314266792_a.jpg?_nc_ht=scontent-ber1-1.cdninstagram.com&_nc_ohc=0WcUu9_x884AX_pDg9Q&oh=49aed05fc43360db691b5626086b9909&oe=5FBDCD74", "is_verified": false, "id": "2152902566", "username": "mass.shoes", "is_private": false}}, {"node": {"full_name": "Elegant.hr", "profile_pic_url": "https://scontent-ber1-1.cdninstagram.com/v/t51.2885-19/s150x150/14736161_1779777558976658_2615719681234829312_a.jpg?_nc_ht=scontent-ber1-1.cdninstagram.com&_nc_ohc=na3eSBLl21AAX-Ci6R1&oh=cb6f70160575810e5e05d2fe3788fc4c&oe=5FBCD267", "is_verified": false, "id": "2792921440", "username": "elegant.hr", "is_private": false}}, {"node": {"full_name": "old soul poet", "profile_pic_url": "https://scontent-ber1-1.cdninstagram.com/v/t51.2885-19/s150x150/12338468_1044754332242870_2098205948_a.jpg?_nc_ht=scontent-ber1-1.cdninstagram.com&_nc_ohc=plNq3aX-5MMAX_IVRRO&oh=6d2d533311c4623b9ace15f1b9015e3a&oe=5FBFC1BF", "is_verified": false, "id": "1017779819", "username": "ingrid_divkovic", "is_private": false}}, {"node": {"full_name": "Dom za mene", "profile_pic_url": "https://scontent-ber1-1.cdninstagram.com/v/t51.2885-19/s150x150/97314549_1553812744778712_6770898599342505984_n.jpg?_nc_ht=scontent-ber1-1.cdninstagram.com&_nc_ohc=OAF9oO_RZmAAX_KENjG&oh=2068b03d77d6d0befb2097bcd124b159&oe=5FBE31CB", "is_verified": false, "id": "5002202017", "username": "dom_za_mene", "is_private": false}}, {"node": {"full_name": "Femina.hr", "profile_pic_url": "https://scontent-ber1-1.cdninstagram.com/v/t51.2885-19/11243874_946761878678750_1629089664_a.jpg?_nc_ht=scontent-ber1-1.cdninstagram.com&_nc_ohc=IbLYVAB2hHoAX90mHRo&oh=775b77747a449857ef640e0a697c201a&oe=5FBCA686", "is_verified": false, "id": "1937266349", "username": "femina.hr", "is_private": false}}, {"node": {"full_name": "24sata", "profile_pic_url": "https://scontent-ber1-1.cdninstagram.com/v/t51.2885-19/s150x150/44877610_299460157336100_2458851420997156864_n.jpg?_nc_ht=scontent-ber1-1.cdninstagram.com&_nc_ohc=7r-uUDQEBycAX8WikVB&oh=5b29897e9acac6a547c06a1a69b34065&oe=5FBE75F5", "is_verified": false, "id": "2536359941", "username": "24sata.hr", "is_private": false}}, {"node": {"full_name": "PEPCO Hrvatska", "profile_pic_url": "https://scontent-ber1-1.cdninstagram.com/v/t51.2885-19/s150x150/70000570_484034055510143_2619117180754591744_n.jpg?_nc_ht=scontent-ber1-1.cdninstagram.com&_nc_ohc=-vvXpc9iTWsAX8fWLdw&oh=b97043e4b1b12c4ad05faf87848b9660&oe=5FBC7066", "is_verified": false, "id": "21863399576", "username": "pepcohr", "is_private": false}}, {"node": {"full_name": "Antonija Bla\u0107e", "profile_pic_url": "https://scontent-ber1-1.cdninstagram.com/v/t51.2885-19/s150x150/26872476_424734214614386_2636252231954857984_n.jpg?_nc_ht=scontent-ber1-1.cdninstagram.com&_nc_ohc=BHcCE1yjJA4AX-bF5G9&oh=b3594a947a345cff978cd57706cfa314&oe=5FBE1E3F", "is_verified": true, "id": "2559063", "username": "antonijablace", "is_private": false}}, {"node": {"full_name": "Dom i dizajn", "profile_pic_url": "https://scontent-ber1-1.cdninstagram.com/v/t51.2885-19/11117204_911344575588996_734852235_a.jpg?_nc_ht=scontent-ber1-1.cdninstagram.com&_nc_ohc=PQpoYYJixfMAX-6I42Q&oh=5cf93597a5aaa41367f8afeabe5a83d0&oe=5FBF6336", "is_verified": false, "id": "1979612227", "username": "domidizajn", "is_private": false}}, {"node": {"full_name": "IVA \u2022 RADIC\u0301", "profile_pic_url": "https://scontent-ber1-1.cdninstagram.com/v/t51.2885-19/s150x150/69036509_510837849734308_412386206957961216_n.jpg?_nc_ht=scontent-ber1-1.cdninstagram.com&_nc_ohc=m0XzigDg5_cAX-Legft&oh=86a0a7fbdc49b78583c6c4a549d04242&oe=5FBEE3DC", "is_verified": false, "id": "174154535", "username": "iva___radic", "is_private": false}}, {"node": {"full_name": "kik.hrvatska", "profile_pic_url": "https://scontent-ber1-1.cdninstagram.com/v/t51.2885-19/s150x150/22637006_1181268388640296_5615456906710614016_n.jpg?_nc_ht=scontent-ber1-1.cdninstagram.com&_nc_ohc=MAP4c61U9Y8AX_0lIGe&oh=fb8f6c1083e17deebb50bd30b0ee81db&oe=5FBD962A", "is_verified": false, "id": "6247053818", "username": "kik.hrvatska", "is_private": false}}, {"node": {"full_name": "NovaTV", "profile_pic_url": "https://scontent-ber1-1.cdninstagram.com/v/t51.2885-19/s150x150/100965295_547280752625591_5272194010788659200_n.jpg?_nc_ht=scontent-ber1-1.cdninstagram.com&_nc_ohc=Tba4i59w5fcAX8oGWKl&oh=55631647639a964f329383588d1373e1&oe=5FBE8FE8", "is_verified": true, "id": "401029751", "username": "novatv_", "is_private": false}}, {"node": {"full_name": "Diva.hr", "profile_pic_url": "https://scontent-ber1-1.cdninstagram.com/v/t51.2885-19/s150x150/71029651_409107603077366_4156980686953119744_n.jpg?_nc_ht=scontent-ber1-1.cdninstagram.com&_nc_ohc=flCco1XLPv4AX9QGbN8&oh=5dbf612ec7d002918afb352f5b26767e&oe=5FBC8B6D", "is_verified": false, "id": "4048520799", "username": "diva.hr", "is_private": false}}, {"node": {"full_name": "NOSI ME", "profile_pic_url": "https://scontent-ber1-1.cdninstagram.com/v/t51.2885-19/s150x150/42078486_1957854430941100_4663668510122049536_n.jpg?_nc_ht=scontent-ber1-1.cdninstagram.com&_nc_ohc=ig3bG_msiJAAX9VvVoH&oh=b56c47d3359bc1d75fce1e25d874c3e1&oe=5FBF1345", "is_verified": false, "id": "7189597536", "username": "torbe_nosi_me", "is_private": false}}, {"node": {"full_name": "Antena Zagreb | 89,7 Mhz", "profile_pic_url": "https://scontent-ber1-1.cdninstagram.com/v/t51.2885-19/s150x150/28753427_231503197411885_6637602897741742080_n.jpg?_nc_ht=scontent-ber1-1.cdninstagram.com&_nc_ohc=Dkqi2SFNJ9MAX8FdK-w&oh=01fd893b2de9972eed037f836facc195&oe=5FBEA17B", "is_verified": false, "id": "1386165318", "username": "antenazagreb", "is_private": false}}, {"node": {"full_name": "Jutarnji.hr", "profile_pic_url": "https://scontent-ber1-1.cdninstagram.com/v/t51.2885-19/s150x150/104134440_575449422999627_1416832692803974547_n.jpg?_nc_ht=scontent-ber1-1.cdninstagram.com&_nc_ohc=NHsuNN67pUoAX9ZLW1Y&oh=e796054f4792b9df26cdab042bdf1169&oe=5FBCBFFF", "is_verified": false, "id": "2160401362", "username": "jutarnji.hr", "is_private": false}}, {"node": {"full_name": "Nevena Rendeli", "profile_pic_url": "https://scontent-ber1-1.cdninstagram.com/v/t51.2885-19/s150x150/121505045_1196465027401515_7682468551924452783_n.jpg?_nc_ht=scontent-ber1-1.cdninstagram.com&_nc_ohc=vci_DBtn1g4AX8gyzh0&oh=107c5e3ab9613e89363fce717063ec82&oe=5FBCA3D6", "is_verified": false, "id": "181360306", "username": "nevenarendeli", "is_private": false}}, {"node": {"full_name": "IKEA Hrvatska", "profile_pic_url": "https://scontent-ber1-1.cdninstagram.com/v/t51.2885-19/s150x150/44852087_582442862179560_3206032733860003840_n.jpg?_nc_ht=scontent-ber1-1.cdninstagram.com&_nc_ohc=rZ72re12Z1QAX_vvSTS&oh=19923d520a8514432d516ef6c1b107d7&oe=5FBD9BC1", "is_verified": true, "id": "756307019", "username": "ikeahrvatska", "is_private": false}}, {"node": {"full_name": "", "profile_pic_url": "https://scontent-ber1-1.cdninstagram.com/v/t51.2885-19/s150x150/117439000_191869938971547_21664001807167046_n.jpg?_nc_ht=scontent-ber1-1.cdninstagram.com&_nc_ohc=840MM5pWtpMAX9m_WhS&oh=91c130f68b9525302a92e8f6e5f2ba00&oe=5FBEFB9E", "is_verified": false, "id": "330396214", "username": "jelenamarinovic", "is_private": false}}, {"node": {"full_name": "P A M E L A", "profile_pic_url": "https://scontent-ber1-1.cdninstagram.com/v/t51.2885-19/s150x150/90944799_1564954087013465_5572905415873658880_n.jpg?_nc_ht=scontent-ber1-1.cdninstagram.com&_nc_ohc=AUkOwmbVEJMAX-2qo0C&oh=435f201ecc9815682cfd35fbb92c4a83&oe=5FBE635C", "is_verified": true, "id": "6907389", "username": "pamelaramljak", "is_private": false}}, {"node": {"full_name": "\ud83c\udf35Marina Karatovi\u0107 Mi\u0161ura\ud83c\udf35", "profile_pic_url": "https://scontent-ber1-1.cdninstagram.com/v/t51.2885-19/s150x150/120246668_333413764586932_2124362545869117052_n.jpg?_nc_ht=scontent-ber1-1.cdninstagram.com&_nc_ohc=_Ai632hpJeQAX-1G2gQ&oh=94f3efe67bded7fd8de11bcadc73a734&oe=5FBCD65F", "is_verified": false, "id": "188311181", "username": "mkm.marina", "is_private": false}}, {"node": {"full_name": "Ivana Miseric", "profile_pic_url": "https://scontent-ber1-1.cdninstagram.com/v/t51.2885-19/s150x150/17881743_362521894141889_1085367978347724800_a.jpg?_nc_ht=scontent-ber1-1.cdninstagram.com&_nc_ohc=XiwmlBWcPRQAX-DyViw&oh=e12b6c88dba79e782e8d0e88a2a269d9&oe=5FBE8647", "is_verified": false, "id": "2735775", "username": "ivana_miseric", "is_private": false}}, {"node": {"full_name": "Sanja Mijac - blog Domac\u0301ica", "profile_pic_url": "https://scontent-ber1-1.cdninstagram.com/v/t51.2885-19/s150x150/121035846_178700967094099_1348593929611255705_n.jpg?_nc_ht=scontent-ber1-1.cdninstagram.com&_nc_ohc=8E81zy-0Tv0AX-r0g_o&oh=62bb8155f060d8f01b9581b83499cd9d&oe=5FBF91C2", "is_verified": false, "id": "12267209", "username": "domacica.sanja", "is_private": false}}, {"node": {"full_name": "Magic Whisperer", "profile_pic_url": "https://scontent-ber1-1.cdninstagram.com/v/t51.2885-19/s150x150/68695393_486713001899438_7602690875310735360_n.jpg?_nc_ht=scontent-ber1-1.cdninstagram.com&_nc_ohc=yX931xlNXX0AX9anN9t&oh=ad0feab8d18cfc05022294c2f61d4bcd&oe=5FBCB9DB", "is_verified": false, "id": "1604411724", "username": "magic.whisperer", "is_private": false}}, {"node": {"full_name": "Elle Croatia", "profile_pic_url": "https://scontent-ber1-1.cdninstagram.com/v/t51.2885-19/s150x150/121886340_1067172183713802_6296353711724137448_n.jpg?_nc_ht=scontent-ber1-1.cdninstagram.com&_nc_ohc=8pFtb7pHJksAX9skb4E&oh=b3a87c9f6e5001e18ab5ca4c39ecc227&oe=5FBDC6B8", "is_verified": false, "id": "1413563642", "username": "ellecroatia", "is_private": false}}, {"node": {"full_name": "missMAMA", "profile_pic_url": "https://scontent-ber1-1.cdninstagram.com/v/t51.2885-19/s150x150/41885925_907538156112632_6578587968330530816_n.jpg?_nc_ht=scontent-ber1-1.cdninstagram.com&_nc_ohc=Ab5GETAj_ZYAX9HMnSv&oh=febb4b51b15d32767548dd443f53c1c1&oe=5FBE8D39", "is_verified": false, "id": "1421122522", "username": "missmama_hr", "is_private": false}}, {"node": {"full_name": "missGASTRO", "profile_pic_url": "https://scontent-ber1-1.cdninstagram.com/v/t51.2885-19/s150x150/70398299_376830586300392_4438516446040948736_n.jpg?_nc_ht=scontent-ber1-1.cdninstagram.com&_nc_ohc=dw6vN3SfoXAAX8BQ72C&oh=6c8ef6ab4749632213c2906f456c1034&oe=5FBDA322", "is_verified": false, "id": "256695844", "username": "missgastro_hr", "is_private": false}}, {"node": {"full_name": "sandrotellingstories", "profile_pic_url": "https://scontent-ber1-1.cdninstagram.com/v/t51.2885-19/s150x150/70402047_395292471177096_7490797326458421248_n.jpg?_nc_ht=scontent-ber1-1.cdninstagram.com&_nc_ohc=NUwxOexoOFQAX845Brc&oh=6381c059a66ad923d9fcc47b097114ad&oe=5FBC362C", "is_verified": false, "id": "211601850", "username": "sandrotellingstories", "is_private": false}}, {"node": {"full_name": "Douglas Hrvatska", "profile_pic_url": "https://scontent-ber1-1.cdninstagram.com/v/t51.2885-19/s150x150/37862572_310983222779379_8338002728223506432_n.jpg?_nc_ht=scontent-ber1-1.cdninstagram.com&_nc_ohc=jQ1158sIKlMAX9BPzUL&oh=55055362ade69c61ddcb39bd60a550af&oe=5FBE9C5A", "is_verified": false, "id": "2179118539", "username": "douglas_hrvatska", "is_private": false}}, {"node": {"full_name": "Kreni zdravo", "profile_pic_url": "https://scontent-ber1-1.cdninstagram.com/v/t51.2885-19/s150x150/84094168_545529369650743_3262567925248163840_n.jpg?_nc_ht=scontent-ber1-1.cdninstagram.com&_nc_ohc=w_Hnoo4yyG4AX9zNNEq&oh=12aad6cfd23a5a09cdc49571e550c062&oe=5FBD76EC", "is_verified": false, "id": "5598218673", "username": "kreni_zdravo", "is_private": false}}, {"node": {"full_name": "Emmezeta Hrvatska", "profile_pic_url": "https://scontent-ber1-1.cdninstagram.com/v/t51.2885-19/s150x150/100949727_2672277896322075_1197190402541617152_n.jpg?_nc_ht=scontent-ber1-1.cdninstagram.com&_nc_ohc=enApSb7dq2kAX92Hkyb&oh=b840ea0e636957d614e05c4da199c39d&oe=5FBD9E8A", "is_verified": true, "id": "3559663395", "username": "emmezeta_hr", "is_private": false}}, {"node": {"full_name": "ispovesti", "profile_pic_url": "https://scontent-ber1-1.cdninstagram.com/v/t51.2885-19/11192899_445415775644942_1454134924_a.jpg?_nc_ht=scontent-ber1-1.cdninstagram.com&_nc_ohc=--VATNC8DRwAX9Cvei1&oh=0321379496091b44e55a14e60f9888d5&oe=5FBDF6F4", "is_verified": false, "id": "442289983", "username": "ispovesti", "is_private": false}}, {"node": {"full_name": "Happy Home gift &fashion store", "profile_pic_url": "https://scontent-ber1-1.cdninstagram.com/v/t51.2885-19/s150x150/14701200_344367935910543_3382967970362818560_a.jpg?_nc_ht=scontent-ber1-1.cdninstagram.com&_nc_ohc=A1Dj7ftOoEgAX8fE1lO&oh=cfc45c2e8fd6bb6e173dc24089eb9c22&oe=5FBD6A30", "is_verified": false, "id": "2231155794", "username": "happyhome_gift_fashion_store", "is_private": false}}, {"node": {"full_name": "Indira Levak Official", "profile_pic_url": "https://scontent-ber1-1.cdninstagram.com/v/t51.2885-19/s150x150/87331117_150822565938618_5258549831697170432_n.jpg?_nc_ht=scontent-ber1-1.cdninstagram.com&_nc_ohc=9BjIlsdjje4AX9iuWbT&oh=61daa3881080917d7baa139f7447ae34&oe=5FBD79F9", "is_verified": true, "id": "4755178782", "username": "indiralevak", "is_private": false}}, {"node": {"full_name": "Ivan Saric", "profile_pic_url": "https://scontent-ber1-1.cdninstagram.com/v/t51.2885-19/s150x150/90094453_139420884163870_2399051268485021696_n.jpg?_nc_ht=scontent-ber1-1.cdninstagram.com&_nc_ohc=dVEMHgbuaG4AX8-XOp8&oh=9ccbe1ace2e4473617098001969fbe01&oe=5FBDC1AC", "is_verified": true, "id": "28686516", "username": "ivansaric", "is_private": false}}, {"node": {"full_name": "BIPA Hrvatska", "profile_pic_url": "https://scontent-ber1-1.cdninstagram.com/v/t51.2885-19/14350840_1789993847937491_273822135263166464_a.jpg?_nc_ht=scontent-ber1-1.cdninstagram.com&_nc_ohc=o6LIAZU7ZMoAX-2ADtt&oh=5f59030b66fbe1e5c546d296baa2047e&oe=5FBCE1F0", "is_verified": false, "id": "476192824", "username": "bipahrvatska", "is_private": false}}, {"node": {"full_name": "Tatjana Juric\u0301", "profile_pic_url": "https://scontent-ber1-1.cdninstagram.com/v/t51.2885-19/s150x150/121415544_2812461172369387_6896259228880599116_n.jpg?_nc_ht=scontent-ber1-1.cdninstagram.com&_nc_ohc=RQwbOYCxIHMAX-UqwWA&oh=103ac6ffd7ae0d74dc4cd18ef5619021&oe=5FBCD09E", "is_verified": true, "id": "381977533", "username": "tatjana_juric", "is_private": false}}, {"node": {"full_name": "roberto shoes", "profile_pic_url": "https://scontent-ber1-1.cdninstagram.com/v/t51.2885-19/s150x150/12568921_591220857703739_1071636814_a.jpg?_nc_ht=scontent-ber1-1.cdninstagram.com&_nc_ohc=nukRDOIaMTQAX-PHchb&oh=51a49f5872a8fa3602a47d2d352f3e9c&oe=5FBC86C4", "is_verified": false, "id": "1941807319", "username": "roberto_shoes", "is_private": false}}, {"node": {"full_name": "Lidl Hrvatska", "profile_pic_url": "https://scontent-ber1-1.cdninstagram.com/v/t51.2885-19/s150x150/27891491_1444811872314659_2514035046306807808_n.jpg?_nc_ht=scontent-ber1-1.cdninstagram.com&_nc_ohc=df9gRyXAKc4AX95DRG-&oh=e17fa1d6132eb9e207da07e9b22123f6&oe=5FBCE195", "is_verified": true, "id": "1814934935", "username": "lidl_hrvatska", "is_private": false}}, {"node": {"full_name": "#S\u030cIKSIK", "profile_pic_url": "https://scontent-ber1-1.cdninstagram.com/v/t51.2885-19/s150x150/105939347_3314332261951355_826233216237325910_n.jpg?_nc_ht=scontent-ber1-1.cdninstagram.com&_nc_ohc=kOgeMRJSK1MAX_S85if&oh=f45496ac3d2fe216c7167ab6f0c3cad8&oe=5FBF0B1F", "is_verified": true, "id": "442625996", "username": "paulasik", "is_private": false}}, {"node": {"full_name": "VIKLER I RUZ\u030c", "profile_pic_url": "https://scontent-ber1-1.cdninstagram.com/v/t51.2885-19/s150x150/57417971_2263634550367559_3182751541509488640_n.jpg?_nc_ht=scontent-ber1-1.cdninstagram.com&_nc_ohc=afAow87x0vAAX95uu2h&oh=302eeaea169e819a998f45acb5aceb82&oe=5FBCACF4", "is_verified": false, "id": "5721273150", "username": "vikleriruz", "is_private": false}}, {"node": {"full_name": "JYSK Hrvatska", "profile_pic_url": "https://scontent-ber1-1.cdninstagram.com/v/t51.2885-19/20759320_327993747670824_2225239671502274560_a.jpg?_nc_ht=scontent-ber1-1.cdninstagram.com&_nc_ohc=w637ETaSXb4AX8lAQqQ&oh=938f2c8ce0d4bf2924f3312135af9372&oe=5FBC2066", "is_verified": true, "id": "1815543167", "username": "jyskhr", "is_private": false}}, {"node": {"full_name": "May", "profile_pic_url": "https://scontent-ber1-1.cdninstagram.com/v/t51.2885-19/s150x150/75288864_2427544777494315_4501717143204659200_n.jpg?_nc_ht=scontent-ber1-1.cdninstagram.com&_nc_ohc=axjnS6Oq3R8AX8lCwMW&oh=1ad742cdccfdb569ec4fd2b9a1df1773&oe=5FBFA3BF", "is_verified": false, "id": "23406138858", "username": "klosharenilo", "is_private": false}}, {"node": {"full_name": "Dalibor Petko", "profile_pic_url": "https://scontent-ber1-1.cdninstagram.com/v/t51.2885-19/s150x150/43539910_572414643193913_5031486563003924480_n.jpg?_nc_ht=scontent-ber1-1.cdninstagram.com&_nc_ohc=XikyHiKUEc8AX-mZfz5&oh=5d0620355314e197ea25fe4b257ea390&oe=5FBDE189", "is_verified": false, "id": "3281377400", "username": "daliborpetko", "is_private": false}}, {"node": {"full_name": "La Lana", "profile_pic_url": "https://scontent-ber1-1.cdninstagram.com/v/t51.2885-19/s150x150/82880762_166511374622504_288373252533780480_n.jpg?_nc_ht=scontent-ber1-1.cdninstagram.com&_nc_ohc=k0xQi-DuLlQAX-zlfoT&oh=013994e0fbcecf4b72af74bc8c35404a&oe=5FBD9819", "is_verified": true, "id": "300980130", "username": "lalana", "is_private": false}}, {"node": {"full_name": "Izabel Kovac\u030cic\u0301", "profile_pic_url": "https://scontent-ber1-1.cdninstagram.com/v/t51.2885-19/s150x150/88150132_663826210840907_2626075740738682880_n.jpg?_nc_ht=scontent-ber1-1.cdninstagram.com&_nc_ohc=xgRhsrWNaM0AX9eKtVj&oh=bca4490001db379cdac0f9049c92a6ce&oe=5FBC0A56", "is_verified": true, "id": "17264892", "username": "izabelandrijanic", "is_private": false}}, {"node": {"full_name": "Luka Ni\u017eeti\u0107", "profile_pic_url": "https://scontent-ber1-1.cdninstagram.com/v/t51.2885-19/s150x150/88207451_204153820668852_7939110797408468992_n.jpg?_nc_ht=scontent-ber1-1.cdninstagram.com&_nc_ohc=9tmnE4QRHtcAX9acVT2&oh=db772d6b1a599c60f6a44ab94a4e0aae&oe=5FBD20D2", "is_verified": true, "id": "14244301", "username": "lukanizetic", "is_private": false}}, {"node": {"full_name": "BOR\u0160A by \ud835\udcf6\ud835\udcea\ud835\udcf5\ud835\udcea \ud835\udcfb\ud835\udcea\ud835\udced\ud835\udcf7\ud835\udcf3\ud835\udcea \ud835\udced\ud835\udcf2\ud835\udd03\ud835\udcea\ud835\udcf3\ud835\udcf7\ud835\udcea \u00a9", "profile_pic_url": "https://scontent-ber1-1.cdninstagram.com/v/t51.2885-19/s150x150/92298803_717475362357678_589898944763396096_n.jpg?_nc_ht=scontent-ber1-1.cdninstagram.com&_nc_ohc=DVS-J9QrGMIAX8FxQet&oh=b4c3f6e6db105d3dd6882e2e0872d670&oe=5FBD9464", "is_verified": false, "id": "356396292", "username": "malaradnjadizajna", "is_private": false}}, {"node": {"full_name": "Jolie Petite by Ljupka Gojic", "profile_pic_url": "https://scontent-ber1-1.cdninstagram.com/v/t51.2885-19/s150x150/11875330_1637659459844723_1204243476_a.jpg?_nc_ht=scontent-ber1-1.cdninstagram.com&_nc_ohc=6unowp4TX30AX8S2Ueg&oh=8ace5d5afb9c7c256e411cf5067799eb&oe=5FBD25C2", "is_verified": false, "id": "184391200", "username": "joliepetitebyljupkagojic", "is_private": false}}, {"node": {"full_name": "Fashion Lover Croatia", "profile_pic_url": "https://scontent-ber1-1.cdninstagram.com/v/t51.2885-19/s150x150/16122386_2062203837340313_3303886468413390848_a.jpg?_nc_ht=scontent-ber1-1.cdninstagram.com&_nc_ohc=KICNAeQwYREAX9MhAll&oh=f54eb7596e4061b5c88f4f5bb8dc9565&oe=5FBD7C3D", "is_verified": false, "id": "324669786", "username": "fashionlovercroatia", "is_private": false}}]}, "id": "1428643188"}}, "logging_page_id": "profilePage_1428643188", "show_follow_dialog": false, "show_suggested_profiles": false}