{"profile_pic_edit_sync_props": null, "show_follow_dialog": false, "toast_content_on_load": null, "show_suggested_profiles": false, "seo_category_infos": [["Ljepota", "beauty"], ["Ples i nastup", "dance_and_performance"], ["Tjelovje\u017eba", "fitness"], ["Hrana i pi\u0107e", "food_and_drink"], ["Dom i vrt", "home_and_garden"], ["Glazba", "music"], ["Vizualne umjetnosti", "visual_arts"]], "show_view_shop": false, "logging_page_id": "profilePage_1428643188", "always_show_message_button_to_pro_account": false, "graphql": {"user": {"should_show_public_contacts": true, "connected_fb_page": null, "should_show_category": true, "fbid": "17841401055662322", "blocked_by_viewer": false, "username": "zadovoljnahr", "external_url": "https://akademija.zadovoljna.hr/", "requested_by_viewer": false, "business_email": "zadovoljna@novatv.hr", "has_ar_effects": false, "edge_saved_media": {"page_info": {"has_next_page": false, "end_cursor": null}, "count": 0, "edges": []}, "has_clips": true, "profile_pic_url": "https://scontent-prg1-1.cdninstagram.com/v/t51.2885-19/s150x150/135725420_424890665305541_5346172548367146031_n.jpg?tp=1&_nc_ht=scontent-prg1-1.cdninstagram.com&_nc_ohc=WgxiAuaBaXYAX8wSJZB&edm=ABfd0MgBAAAA&ccb=7-4&oh=520c92274a53601681034f4099eed90f&oe=60C1A880&_nc_sid=7bff83", "overall_category_name": null, "country_block": false, "biography": "Slu\u017ebeni instagram profil \u017eenskog lifestyle portala", "hide_like_and_view_counts": false, "is_private": false, "profile_pic_url_hd": "https://scontent-prg1-1.cdninstagram.com/v/t51.2885-19/s150x150/135725420_424890665305541_5346172548367146031_n.jpg?tp=1&_nc_ht=scontent-prg1-1.cdninstagram.com&_nc_ohc=WgxiAuaBaXYAX8wSJZB&edm=ABfd0MgBAAAA&ccb=7-4&oh=520c92274a53601681034f4099eed90f&oe=60C1A880&_nc_sid=7bff83", "edge_mutual_followed_by": {"count": 3, "edges": [{"node": {"username": "dnevnikhr"}}, {"node": {"username": "punkuferhr"}}, {"node": {"username": "teen385com"}}]}, "has_channel": false, "is_verified": true, "edge_media_collections": {"page_info": {"has_next_page": false, "end_cursor": null}, "count": 0, "edges": []}, "id": "1428643188", "highlight_reel_count": 9, "category_enum": "NEWS_SITE", "has_blocked_viewer": false, "has_requested_viewer": false, "is_business_account": true, "business_phone_number": null, "followed_by_viewer": true, "business_category_name": "Publishers", "business_contact_method": null, "edge_follow": {"count": 1633}, "category_name": null, "follows_viewer": false, "is_professional_account": true, "external_url_linkshimmed": "https://l.instagram.com/?u=https%3A%2F%2Fakademija.zadovoljna.hr%2F&e=ATPAbW_YR9Nnsig9pqizMWDI-D9U9TK_XvIqdECiKdbYkPtvL4ENEr3O0WSmuEmLz15urU9fnSOFW3RSvMNtyA&s=1", "has_guides": false, "is_joined_recently": false, "full_name": "zadovoljna.hr", "edge_felix_video_timeline": {"page_info": {"has_next_page": false, "end_cursor": null}, "count": 2, "edges": [{"node": {"dash_info": {"number_of_qualities": 4, "video_dash_manifest": "<MPD xmlns=\"urn:mpeg:dash:schema:mpd:2011\" minBufferTime=\"PT1.500S\" type=\"static\" mediaPresentationDuration=\"PT0H1M40.566S\" maxSegmentDuration=\"PT0H0M5.000S\" profiles=\"urn:mpeg:dash:profile:isoff-on-demand:2011,http://dashif.org/guidelines/dash264\">\n <Period duration=\"PT0H1M40.566S\">\n  <AdaptationSet segmentAlignment=\"true\" maxWidth=\"1280\" maxHeight=\"720\" maxFrameRate=\"30\" par=\"16:9\" lang=\"und\" subsegmentAlignment=\"true\" subsegmentStartsWithSAP=\"1\">\n   <Representation id=\"17899148011780467vd\" mimeType=\"video/mp4\" codecs=\"avc1.64001F\" width=\"1280\" height=\"720\" frameRate=\"30\" sar=\"1:1\" startWithSAP=\"1\" bandwidth=\"671762\" FBQualityClass=\"hd\" FBQualityLabel=\"1280w\" FBPlaybackResolutionMos=\"0:100.00,480:89.96,640:86.42,720:81.44\">\n    <BaseURL>https://scontent-prg1-1.cdninstagram.com/v/t50.16885-16/10000000_239527917772925_7240929727451169124_n.mp4?_nc_ht=scontent-prg1-1.cdninstagram.com&amp;_nc_cat=105&amp;_nc_ohc=DxFyzIcPo0MAX-IGjEr&amp;tn=Vcf8IfvvgXU4rjLb&amp;edm=ABfd0MgBAAAA&amp;ccb=7-4&amp;oh=718209d41f44e2db950516086253f09e&amp;oe=60BC9C79&amp;_nc_sid=7bff83</BaseURL>\n    <SegmentBase indexRangeExact=\"true\" indexRange=\"914-1197\" FBFirstSegmentRange=\"1198-516690\" FBSecondSegmentRange=\"516691-1012537\" FBPrefetchSegmentRange=\"1198-1012537\">\n      <Initialization range=\"0-913\"/>\n    </SegmentBase>\n   </Representation>\n  <Representation id=\"17899148533780467v\" mimeType=\"video/mp4\" codecs=\"avc1.64001F\" width=\"432\" height=\"244\" frameRate=\"30\" sar=\"1:1\" startWithSAP=\"1\" bandwidth=\"97948\" FBQualityClass=\"sd\" FBQualityLabel=\"432w\" FBPlaybackResolutionMos=\"0:100.00,480:44.30,640:38.76,720:33.82\">\n    <BaseURL>https://scontent-prg1-1.cdninstagram.com/v/t50.16885-16/144224832_249911843325361_6020400172200868738_n.mp4?_nc_ht=scontent-prg1-1.cdninstagram.com&amp;_nc_cat=101&amp;_nc_ohc=TJfab0WqRBoAX8VkzhJ&amp;tn=Vcf8IfvvgXU4rjLb&amp;edm=ABfd0MgBAAAA&amp;ccb=7-4&amp;oh=ea06eeb0fe8fad5259738af626b8e80c&amp;oe=60BC6F90&amp;_nc_sid=7bff83</BaseURL>\n    <SegmentBase indexRangeExact=\"true\" indexRange=\"915-1198\" FBFirstSegmentRange=\"1199-68378\" FBSecondSegmentRange=\"68379-133149\" FBPrefetchSegmentRange=\"1199-133149\">\n      <Initialization range=\"0-914\"/>\n    </SegmentBase>\n   </Representation>\n  <Representation id=\"17899148371780467v\" mimeType=\"video/mp4\" codecs=\"avc1.64001F\" width=\"576\" height=\"324\" frameRate=\"30\" sar=\"1:1\" startWithSAP=\"1\" bandwidth=\"201580\" FBQualityClass=\"sd\" FBQualityLabel=\"576w\" FBPlaybackResolutionMos=\"0:100.00,480:66.47,640:59.32,720:51.99\">\n    <BaseURL>https://scontent-prg1-1.cdninstagram.com/v/t50.16885-16/144371588_219801059798283_4396671990115351624_n.mp4?_nc_ht=scontent-prg1-1.cdninstagram.com&amp;_nc_cat=103&amp;_nc_ohc=YPrukSDNYMwAX_E6Zho&amp;edm=ABfd0MgBAAAA&amp;ccb=7-4&amp;oh=2d53553dff8f7e5c82f9fcc190bdf745&amp;oe=60BCB3C0&amp;_nc_sid=7bff83</BaseURL>\n    <SegmentBase indexRangeExact=\"true\" indexRange=\"916-1199\" FBFirstSegmentRange=\"1200-172170\" FBSecondSegmentRange=\"172171-331058\" FBPrefetchSegmentRange=\"1200-331058\">\n      <Initialization range=\"0-915\"/>\n    </SegmentBase>\n   </Representation>\n  <Representation id=\"17899148275780467v\" mimeType=\"video/mp4\" codecs=\"avc1.64001F\" width=\"916\" height=\"516\" frameRate=\"30\" sar=\"1:1\" startWithSAP=\"1\" bandwidth=\"363209\" FBQualityClass=\"hd\" FBQualityLabel=\"916w\" FBPlaybackResolutionMos=\"0:100.00,480:79.40,640:74.31,720:67.85\">\n    <BaseURL>https://scontent-prg1-1.cdninstagram.com/v/t50.16885-16/144086449_245399800448174_4946347116518782695_n.mp4?_nc_ht=scontent-prg1-1.cdninstagram.com&amp;_nc_cat=102&amp;_nc_ohc=hctnr5KUV74AX9_mpT2&amp;edm=ABfd0MgBAAAA&amp;ccb=7-4&amp;oh=7e91bb801c9c41669860da3cbc62f0e7&amp;oe=60BC53FA&amp;_nc_sid=7bff83</BaseURL>\n    <SegmentBase indexRangeExact=\"true\" indexRange=\"916-1199\" FBFirstSegmentRange=\"1200-306150\" FBSecondSegmentRange=\"306151-589899\" FBPrefetchSegmentRange=\"1200-589899\">\n      <Initialization range=\"0-915\"/>\n    </SegmentBase>\n   </Representation>\n  </AdaptationSet>\n <AdaptationSet segmentAlignment=\"true\" lang=\"und\" subsegmentAlignment=\"true\" subsegmentStartsWithSAP=\"1\">\n   <Representation id=\"17899147882780467ad\" mimeType=\"audio/mp4\" codecs=\"mp4a.40.5\" audioSamplingRate=\"44100\" startWithSAP=\"1\" bandwidth=\"89170\">\n    <AudioChannelConfiguration schemeIdUri=\"urn:mpeg:dash:23003:3:audio_channel_configuration:2011\" value=\"2\"/>\n    <BaseURL>https://scontent-prg1-1.cdninstagram.com/v/t50.16885-16/143534851_3705043349581593_852522442407031511_n.mp4?_nc_ht=scontent-prg1-1.cdninstagram.com&amp;_nc_cat=109&amp;_nc_ohc=lTPvIH-2lLsAX9iiIwz&amp;tn=Vcf8IfvvgXU4rjLb&amp;edm=ABfd0MgBAAAA&amp;ccb=7-4&amp;oh=50f3e8983fa8f9faa6720b707f9a0e0c&amp;oe=60BCA9BB&amp;_nc_sid=7bff83</BaseURL>\n    <SegmentBase indexRangeExact=\"true\" indexRange=\"868-1511\" FBFirstSegmentRange=\"1512-24497\" FBSecondSegmentRange=\"24498-46999\" FBPrefetchSegmentRange=\"1512-46999\">\n      <Initialization range=\"0-867\"/>\n    </SegmentBase>\n   </Representation>\n  </AdaptationSet>\n </Period>\n</MPD>", "is_dash_eligible": true}, "tracking_token": "eyJ2ZXJzaW9uIjo1LCJwYXlsb2FkIjp7ImlzX2FuYWx5dGljc190cmFja2VkIjp0cnVlLCJ1dWlkIjoiNDM5ZThjZDUxNDYxNGFlN2E0OWI4YzBhNjFhZDBjZTMyNDk3Mzg3NTY5MTI0MTM2MTIzIiwic2VydmVyX3Rva2VuIjoiMTYyMjgxNTUwMTk4N3wyNDk3Mzg3NTY5MTI0MTM2MTIzfDMxOTQ0OTc4NjZ8Y2Y1ZTlkNTQ2MDg0NjM0ZGM0YzRhOGRkOWQ4Njk2Y2M4NmE1NmQyZGM2NWY1MjczZTk5ZWM3N2UwYTYxNTQzNyJ9LCJzaWduYXR1cmUiOiIifQ==", "title": "Ni\u0161ta nas ne mo\u017ee slomiti \u2764\ufe0f", "encoding_status": null, "taken_at_timestamp": 1611931882, "has_audio": true, "shortcode": "CKogMMsHtS7", "id": "2497387569124136123", "owner": {"username": "zadovoljnahr", "id": "1428643188"}, "edge_liked_by": {"count": 507}, "edge_media_preview_like": {"count": 507}, "fact_check_overall_rating": null, "media_preview": "ABsqyT2qURFlL9gefarVnGHK8c+9X2txGxZcFW5I6c98ex9KRoc+RikzU5i3sdn3QeDURjI7VVnuTdbGnYnaGcdRgfQHrWiGTGDycc55rDgl8tgfXINXFuFZtpwD+n0zRFJ7sUpOKulcHwvAGM84/lVcDNPuJAvB/wA/SqQlYf8A6hW7aWn5GEU2rgR2qaU7hkDsP8artV+EZiB/2WrmOooYz1oooqzM/9k=", "sharing_friction_info": {"bloks_app_url": null, "should_have_sharing_friction": false}, "product_type": "igtv", "accessibility_caption": null, "video_duration": 100.533, "video_view_count": 10044, "__typename": "GraphVideo", "comments_disabled": false, "video_url": "https://scontent-prg1-1.cdninstagram.com/v/t50.16885-16/10000000_3974913235855263_8023193608733796675_n.mp4?efg=eyJ2ZW5jb2RlX3RhZyI6InZ0c192b2RfdXJsZ2VuLjEyODAuaWd0di5kZWZhdWx0IiwicWVfZ3JvdXBzIjoiW1wiaWdfd2ViX2RlbGl2ZXJ5X3Z0c19vdGZcIl0ifQ&_nc_ht=scontent-prg1-1.cdninstagram.com&_nc_cat=103&_nc_ohc=o9pYg8O2PuoAX9PpgJ-&edm=ABfd0MgBAAAA&vs=17899147999780467_1364013098&_nc_vs=HBksFQAYJEdJQ1dtQUNmcDJfYktSOE9BRU1wd3hRVUhGaHZidlZCQUFBRhUAAsgBABUAGCRHQU1yamdnWnI3cWd0eWtOQU5jeXVQNmt4TlFMYnZWQkFBQUYVAgLIAQAoABgAGwGIB3VzZV9vaWwBMRUAACbmjPe0wcvLPxUCKAJDMywXQFkiHKwIMScYEmRhc2hfYmFzZWxpbmVfMV92MREAdewHAA%3D%3D&ccb=7-4&oe=60BC59F0&oh=13413ea645cdeae086c8ad8fb6ebdb0f&_nc_sid=7bff83", "edge_media_to_tagged_user": {"edges": []}, "fact_check_information": null, "thumbnail_resources": [{"src": "https://scontent-prg1-1.cdninstagram.com/v/t51.2885-15/e35/p150x150/143723112_708929783157923_5580247199781149757_n.jpg?tp=1&_nc_ht=scontent-prg1-1.cdninstagram.com&_nc_cat=111&_nc_ohc=4tnUXKs_tNoAX940Y42&edm=ABfd0MgBAAAA&ccb=7-4&oh=f6394798c70fbd66205aa29a6fff5112&oe=60BC7C16&_nc_sid=7bff83", "config_width": 150, "config_height": 233}, {"src": "https://scontent-prg1-1.cdninstagram.com/v/t51.2885-15/e35/p240x240/143723112_708929783157923_5580247199781149757_n.jpg?tp=1&_nc_ht=scontent-prg1-1.cdninstagram.com&_nc_cat=111&_nc_ohc=4tnUXKs_tNoAX940Y42&edm=ABfd0MgBAAAA&ccb=7-4&oh=dd2719093d28cec621212f32498677a9&oe=60BC4D14&_nc_sid=7bff83", "config_width": 240, "config_height": 373}, {"src": "https://scontent-prg1-1.cdninstagram.com/v/t51.2885-15/e35/p320x320/143723112_708929783157923_5580247199781149757_n.jpg?tp=1&_nc_ht=scontent-prg1-1.cdninstagram.com&_nc_cat=111&_nc_ohc=4tnUXKs_tNoAX940Y42&edm=ABfd0MgBAAAA&ccb=7-4&oh=5fb994a1d9a46d5b2999e4659f3104ae&oe=60BC46EE&_nc_sid=7bff83", "config_width": 320, "config_height": 497}, {"src": "https://scontent-prg1-1.cdninstagram.com/v/t51.2885-15/e35/p480x480/143723112_708929783157923_5580247199781149757_n.jpg?tp=1&_nc_ht=scontent-prg1-1.cdninstagram.com&_nc_cat=111&_nc_ohc=4tnUXKs_tNoAX940Y42&tn=Vcf8IfvvgXU4rjLb&edm=ABfd0MgBAAAA&ccb=7-4&oh=4ccd07c660ca8c8d2a0fa5dbef295073&oe=60BC416B&_nc_sid=7bff83", "config_width": 480, "config_height": 746}, {"src": "https://scontent-prg1-1.cdninstagram.com/v/t51.2885-15/e35/143723112_708929783157923_5580247199781149757_n.jpg?tp=1&_nc_ht=scontent-prg1-1.cdninstagram.com&_nc_cat=111&_nc_ohc=4tnUXKs_tNoAX940Y42&edm=ABfd0MgBAAAA&ccb=7-4&oh=042041c1df00908e562e0f7e9538adb1&oe=60BC51BB&_nc_sid=7bff83", "config_width": 640, "config_height": 995}], "felix_profile_grid_crop": null, "edge_media_to_caption": {"edges": [{"node": {"text": "Kada je tog kobnog utorka, 29. prosinca 2020. godine u 12 sati i 19 minuta Stra\u0161nik kod Petrinje pogodio razorni potres od 6.4 stupnja po Richterovoj ljestvici, hrvatski su gra\u0111ani na trenutak ostali paralizirani od \u0161oka, panike i nevjerice.\n\nStrah i neizvjesnost nadvili su se nad Sisa\u010dko-moslava\u010dku \u017eupaniju poput nevidljiva pokriva\u010da, no nisu slomili duh ljudi koji tamo \u017eive. Zahvaljuju\u0107im velikim srcima volontera po\u010dela su se ra\u0161\u010di\u0161\u0107avati razorena podru\u010dja, popravljati krovovi, dopremati hrana, odje\u0107a i higijenske potrep\u0161tine.\n\nU svom tom kaosu i nemiru iskakali su dra\u017eesni oblici nade i optimizma koji su na o\u010di tjerali suze radosnice. Hvala svim koji ste pomagali i koji jo\u0161 uvijek poma\u017eete. \u2764\ufe0f #zadovoljnahr"}}]}, "media_overlay_info": null, "gating_info": null, "is_published": true, "dimensions": {"height": 995, "width": 640}, "thumbnail_src": "https://scontent-prg1-1.cdninstagram.com/v/t51.2885-15/e35/c0.150.540.540a/143723112_708929783157923_5580247199781149757_n.jpg?tp=1&_nc_ht=scontent-prg1-1.cdninstagram.com&_nc_cat=111&_nc_ohc=4tnUXKs_tNoAX940Y42&edm=ABfd0MgBAAAA&ccb=7-4&oh=c8be11c42934ee94e8c683acc600d1b8&oe=60BCA7C0&_nc_sid=7bff83", "display_url": "https://scontent-prg1-1.cdninstagram.com/v/t51.2885-15/e35/143723112_708929783157923_5580247199781149757_n.jpg?tp=1&_nc_ht=scontent-prg1-1.cdninstagram.com&_nc_cat=111&_nc_ohc=4tnUXKs_tNoAX940Y42&tn=Vcf8IfvvgXU4rjLb&edm=ABfd0MgBAAAA&ccb=7-4&oh=838d82e4989bb77b38c936bb201e35ea&oe=60BC51BB&_nc_sid=7bff83", "is_video": true, "location": null, "edge_media_to_comment": {"count": 5}}}, {"node": {"dash_info": {"number_of_qualities": 5, "video_dash_manifest": "<MPD xmlns=\"urn:mpeg:dash:schema:mpd:2011\" minBufferTime=\"PT1.500S\" type=\"static\" mediaPresentationDuration=\"PT0H1M47.008S\" maxSegmentDuration=\"PT0H0M5.000S\" profiles=\"urn:mpeg:dash:profile:isoff-on-demand:2011,http://dashif.org/guidelines/dash264\">\n <Period duration=\"PT0H1M47.008S\">\n  <AdaptationSet segmentAlignment=\"true\" maxWidth=\"1280\" maxHeight=\"720\" maxFrameRate=\"30\" par=\"16:9\" lang=\"eng\" subsegmentAlignment=\"true\" subsegmentStartsWithSAP=\"1\">\n   <Representation id=\"17903247421589351vd\" mimeType=\"video/mp4\" codecs=\"avc1.64001F\" width=\"1280\" height=\"720\" frameRate=\"30\" sar=\"1:1\" startWithSAP=\"1\" bandwidth=\"1974596\" FBQualityClass=\"hd\" FBQualityLabel=\"1280w\" FBPlaybackResolutionMos=\"0:100.00,480:88.19,640:83.41,1080:69.41\">\n    <BaseURL>https://scontent-prg1-1.cdninstagram.com/v/t50.16885-16/10000000_182451436814707_8020941750238943150_n.mp4?_nc_ht=scontent-prg1-1.cdninstagram.com&amp;_nc_cat=107&amp;_nc_ohc=-IFzTdIob2wAX9M3FlK&amp;edm=ABfd0MgBAAAA&amp;ccb=7-4&amp;oh=73dc0707ce56ad4e0a9cff89c690309e&amp;oe=60BC946D&amp;_nc_sid=7bff83</BaseURL>\n    <SegmentBase indexRangeExact=\"true\" indexRange=\"929-1224\" FBFirstSegmentRange=\"1225-990473\" FBSecondSegmentRange=\"990474-2056860\" FBPrefetchSegmentRange=\"1225-2056860\">\n      <Initialization range=\"0-928\"/>\n    </SegmentBase>\n   </Representation>\n  <Representation id=\"17903248270589351v\" mimeType=\"video/mp4\" codecs=\"avc1.64001F\" width=\"432\" height=\"244\" frameRate=\"30\" sar=\"244:243\" startWithSAP=\"1\" bandwidth=\"148470\" FBQualityClass=\"sd\" FBQualityLabel=\"432w\" FBPlaybackResolutionMos=\"0:100.00,480:25.84,640:21.65,1080:17.34\">\n    <BaseURL>https://scontent-prg1-1.cdninstagram.com/v/t50.16885-16/124337928_666751127321441_1286544785847475668_n.mp4?_nc_ht=scontent-prg1-1.cdninstagram.com&amp;_nc_cat=105&amp;_nc_ohc=BN1iHveMJvMAX9B2NNK&amp;tn=Vcf8IfvvgXU4rjLb&amp;edm=ABfd0MgBAAAA&amp;ccb=7-4&amp;oh=f9f5795ef787d64f214f65b977d4ac4c&amp;oe=60BCB7E7&amp;_nc_sid=7bff83</BaseURL>\n    <SegmentBase indexRangeExact=\"true\" indexRange=\"933-1228\" FBFirstSegmentRange=\"1229-93424\" FBSecondSegmentRange=\"93425-190606\" FBPrefetchSegmentRange=\"1229-190606\">\n      <Initialization range=\"0-932\"/>\n    </SegmentBase>\n   </Representation>\n  <Representation id=\"17903248018589351v\" mimeType=\"video/mp4\" codecs=\"avc1.64001F\" width=\"476\" height=\"268\" frameRate=\"30\" sar=\"1072:1071\" startWithSAP=\"1\" bandwidth=\"305585\" FBQualityClass=\"sd\" FBQualityLabel=\"476w\" FBPlaybackResolutionMos=\"0:100.00,480:43.43,640:35.03,1080:24.69\">\n    <BaseURL>https://scontent-prg1-1.cdninstagram.com/v/t50.16885-16/124807270_396491931714909_7570792712344719795_n.mp4?_nc_ht=scontent-prg1-1.cdninstagram.com&amp;_nc_cat=109&amp;_nc_ohc=vWkqxUrhgzgAX9cx5Oa&amp;edm=ABfd0MgBAAAA&amp;ccb=7-4&amp;oh=652ae421aa41baa1c81e1d46e6138bf2&amp;oe=60BC56B8&amp;_nc_sid=7bff83</BaseURL>\n    <SegmentBase indexRangeExact=\"true\" indexRange=\"933-1228\" FBFirstSegmentRange=\"1229-135436\" FBSecondSegmentRange=\"135437-312356\" FBPrefetchSegmentRange=\"1229-312356\">\n      <Initialization range=\"0-932\"/>\n    </SegmentBase>\n   </Representation>\n  <Representation id=\"17903247784589351v\" mimeType=\"video/mp4\" codecs=\"avc1.64001F\" width=\"756\" height=\"426\" frameRate=\"30\" sar=\"568:567\" startWithSAP=\"1\" bandwidth=\"635479\" FBQualityClass=\"hd\" FBQualityLabel=\"756w\" FBPlaybackResolutionMos=\"0:100.00,480:66.77,640:57.69,1080:41.07\">\n    <BaseURL>https://scontent-prg1-1.cdninstagram.com/v/t50.16885-16/10000000_387673275718548_6402765357625282393_n.mp4?_nc_ht=scontent-prg1-1.cdninstagram.com&amp;_nc_cat=100&amp;_nc_ohc=zjB60xWv2K4AX-S00VG&amp;edm=ABfd0MgBAAAA&amp;ccb=7-4&amp;oh=97ba041dd1f627bc96e941e6c10b1ead&amp;oe=60BCC19F&amp;_nc_sid=7bff83</BaseURL>\n    <SegmentBase indexRangeExact=\"true\" indexRange=\"934-1229\" FBFirstSegmentRange=\"1230-293997\" FBSecondSegmentRange=\"293998-646195\" FBPrefetchSegmentRange=\"1230-646195\">\n      <Initialization range=\"0-933\"/>\n    </SegmentBase>\n   </Representation>\n  <Representation id=\"17903247679589351v\" mimeType=\"video/mp4\" codecs=\"avc1.64001F\" width=\"1158\" height=\"652\" frameRate=\"30\" sar=\"5216:5211\" startWithSAP=\"1\" bandwidth=\"1177395\" FBQualityClass=\"hd\" FBQualityLabel=\"1158w\" FBPlaybackResolutionMos=\"0:100.00,480:79.67,640:73.78,1080:58.42\">\n    <BaseURL>https://scontent-prg1-1.cdninstagram.com/v/t50.16885-16/10000000_233177154810861_1435073486778116998_n.mp4?_nc_ht=scontent-prg1-1.cdninstagram.com&amp;_nc_cat=109&amp;_nc_ohc=qXEEGOewxKoAX8sKz8B&amp;edm=ABfd0MgBAAAA&amp;ccb=7-4&amp;oh=c4b5b66c877322c024f67d18d1ea0ed1&amp;oe=60BCC69A&amp;_nc_sid=7bff83</BaseURL>\n    <SegmentBase indexRangeExact=\"true\" indexRange=\"934-1229\" FBFirstSegmentRange=\"1230-544574\" FBSecondSegmentRange=\"544575-1186880\" FBPrefetchSegmentRange=\"1230-1186880\">\n      <Initialization range=\"0-933\"/>\n    </SegmentBase>\n   </Representation>\n  </AdaptationSet>\n <AdaptationSet segmentAlignment=\"true\" lang=\"eng\" subsegmentAlignment=\"true\" subsegmentStartsWithSAP=\"1\">\n   <Representation id=\"17903247178589351ad\" mimeType=\"audio/mp4\" codecs=\"mp4a.40.5\" audioSamplingRate=\"48000\" startWithSAP=\"1\" bandwidth=\"103373\">\n    <AudioChannelConfiguration schemeIdUri=\"urn:mpeg:dash:23003:3:audio_channel_configuration:2011\" value=\"2\"/>\n    <BaseURL>https://scontent-prg1-1.cdninstagram.com/v/t50.16885-16/123322009_424755631849142_3808321706520673119_n.mp4?_nc_ht=scontent-prg1-1.cdninstagram.com&amp;_nc_cat=102&amp;_nc_ohc=spOfyzHt-04AX9O4LM-&amp;tn=Vcf8IfvvgXU4rjLb&amp;edm=ABfd0MgBAAAA&amp;ccb=7-4&amp;oh=e216a3c0fb83727eb55acfe92841e986&amp;oe=60BC5DA8&amp;_nc_sid=7bff83</BaseURL>\n    <SegmentBase indexRangeExact=\"true\" indexRange=\"868-1547\" FBFirstSegmentRange=\"1548-27905\" FBSecondSegmentRange=\"27906-55200\" FBPrefetchSegmentRange=\"1548-55200\">\n      <Initialization range=\"0-867\"/>\n    </SegmentBase>\n   </Representation>\n  </AdaptationSet>\n </Period>\n</MPD>", "is_dash_eligible": true}, "tracking_token": "eyJ2ZXJzaW9uIjo1LCJwYXlsb2FkIjp7ImlzX2FuYWx5dGljc190cmFja2VkIjp0cnVlLCJ1dWlkIjoiNDM5ZThjZDUxNDYxNGFlN2E0OWI4YzBhNjFhZDBjZTMyNDM5MzE4Mzk2NTc4OTc1OTE1Iiwic2VydmVyX3Rva2VuIjoiMTYyMjgxNTUwMTk4OHwyNDM5MzE4Mzk2NTc4OTc1OTE1fDMxOTQ0OTc4NjZ8MTJkZmZhY2JhOGIwNWZhOGFmYzdkNTM5YmUwMGZlZDE1MTU4YThjZTQ3NTFiN2UzMDQ0NWY2M2Y5NTc2MmM1NSJ9LCJzaWduYXR1cmUiOiIifQ==", "title": "Bo\u017ei\u0107ni izlog Sa\u0161e \u0160ekoranje", "encoding_status": null, "taken_at_timestamp": 1605009461, "has_audio": true, "shortcode": "CHaMyhaKlCr", "id": "2439318396578975915", "owner": {"username": "zadovoljnahr", "id": "1428643188"}, "edge_liked_by": {"count": 413}, "edge_media_preview_like": {"count": 413}, "fact_check_overall_rating": null, "media_preview": "ABsqR5g8e08Eng8bsdcH056c88mmRxbQcemWyM49h6/WqbMqPx3555B9OtaYdUGG4AVT167u36Gosu5evRDPtUflmEkgtweD8o6/if8AGmqoAwDu9+mfzptwQzBl6D+eOme/FQiYqMYoWmw7dyp5TsB1J6dOlbRTzEjQj+AZP8v8aqMOOAW4OMdOOpJyKueaCoXoWGMjAHGeB7fTmk3bQEr6kc8WxVA+YAkk/h1qpt9s1rxtn09we4/of596aYIm5BxntSKv0ZRTerMhG0DqBk+nA9Qf/r1IXjP8JZl5GONuPrjP09qpLI3mKcnJPPJ5rUuRmJSeTyP1qfMPIpGYqeDikEh74zVeXr+FPjPyimM//9k=", "sharing_friction_info": {"bloks_app_url": null, "should_have_sharing_friction": false}, "product_type": "igtv", "accessibility_caption": null, "video_duration": 106.966, "video_view_count": 8455, "__typename": "GraphVideo", "comments_disabled": false, "video_url": "https://scontent-prg1-1.cdninstagram.com/v/t50.16885-16/10000000_377895680314501_5915768833542409966_n.mp4?efg=eyJ2ZW5jb2RlX3RhZyI6InZ0c192b2RfdXJsZ2VuLjEyODAuaWd0di5kZWZhdWx0IiwicWVfZ3JvdXBzIjoiW1wiaWdfd2ViX2RlbGl2ZXJ5X3Z0c19vdGZcIl0ifQ&_nc_ht=scontent-prg1-1.cdninstagram.com&_nc_cat=101&_nc_ohc=qz-_S1-iyr4AX9wW2AP&tn=Vcf8IfvvgXU4rjLb&edm=ABfd0MgBAAAA&vs=17903247391589351_1669047983&_nc_vs=HBksFQAYJEdJQ1dtQUNGak1teHNWY0JBTzVPbnpocENCbFNidlZCQUFBRhUAAsgBABUAGCRHSm1fV1FlMmZvMGdVSUlCQUYtN2tpdHE0TmswYnZWQkFBQUYVAgLIAQAoABgAGwGIB3VzZV9vaWwBMRUAACbOgpX9kLrNPxUCKAJDMywXQFq90vGp%2B%2BcYEmRhc2hfYmFzZWxpbmVfMV92MREAdewHAA%3D%3D&ccb=7-4&oe=60BCCB3A&oh=41564b4d59ba2fa65419969d0b4eb082&_nc_sid=7bff83", "edge_media_to_tagged_user": {"edges": []}, "fact_check_information": null, "thumbnail_resources": [{"src": "https://scontent-prg1-1.cdninstagram.com/v/t51.2885-15/e15/p150x150/124310268_195521312144582_4260407469223221134_n.jpg?tp=1&_nc_ht=scontent-prg1-1.cdninstagram.com&_nc_cat=102&_nc_ohc=N2LSpMKI_KsAX8Mqw8K&edm=ABfd0MgBAAAA&ccb=7-4&oh=2bdff8d1cb7330dc8c4f08c14db29ed8&oe=60BC357D&_nc_sid=7bff83", "config_width": 150, "config_height": 233}, {"src": "https://scontent-prg1-1.cdninstagram.com/v/t51.2885-15/e15/p240x240/124310268_195521312144582_4260407469223221134_n.jpg?tp=1&_nc_ht=scontent-prg1-1.cdninstagram.com&_nc_cat=102&_nc_ohc=N2LSpMKI_KsAX8Mqw8K&edm=ABfd0MgBAAAA&ccb=7-4&oh=8d2d2212e0f3a7a536c247da7da5d864&oe=60BC58BB&_nc_sid=7bff83", "config_width": 240, "config_height": 373}, {"src": "https://scontent-prg1-1.cdninstagram.com/v/t51.2885-15/e15/p320x320/124310268_195521312144582_4260407469223221134_n.jpg?tp=1&_nc_ht=scontent-prg1-1.cdninstagram.com&_nc_cat=102&_nc_ohc=N2LSpMKI_KsAX8Mqw8K&edm=ABfd0MgBAAAA&ccb=7-4&oh=260e34d6484b90338a8f1c34581c66e5&oe=60BCC505&_nc_sid=7bff83", "config_width": 320, "config_height": 497}, {"src": "https://scontent-prg1-1.cdninstagram.com/v/t51.2885-15/e15/p480x480/124310268_195521312144582_4260407469223221134_n.jpg?tp=1&_nc_ht=scontent-prg1-1.cdninstagram.com&_nc_cat=102&_nc_ohc=N2LSpMKI_KsAX8Mqw8K&edm=ABfd0MgBAAAA&ccb=7-4&oh=683549eb0b0e3b9a3c82e572057516e0&oe=60BCAD44&_nc_sid=7bff83", "config_width": 480, "config_height": 746}, {"src": "https://scontent-prg1-1.cdninstagram.com/v/t51.2885-15/e15/124310268_195521312144582_4260407469223221134_n.jpg?tp=1&_nc_ht=scontent-prg1-1.cdninstagram.com&_nc_cat=102&_nc_ohc=N2LSpMKI_KsAX8Mqw8K&edm=ABfd0MgBAAAA&ccb=7-4&oh=c901e68ab364ada631b51ad51f09a39d&oe=60BC4C88&_nc_sid=7bff83", "config_width": 640, "config_height": 995}], "felix_profile_grid_crop": null, "edge_media_to_caption": {"edges": [{"node": {"text": "Blagdanski optimizam i blje\u0161tavilo potrebniji su nam nego ikada pa smo se ove godine naro\u010dito veselili bo\u017ei\u0107nom ure\u0111enju izloga cvjetnog atelijera Sa\u0161e \u0160ekoranje. Cvjetni \u010darobnjak uvijek nas iznenadi s nekom novom \u010darolijom i pri\u010dom, a za ovogodi\u0161nje ure\u0111enje tema su bile \u2013 ptice. Sa\u0161a nam je otkrio za\u0161to ba\u0161 ptice te \u0161to nam svima u\u017easno fali u ovo vrijeme. Pro\u010ditajte na na\u0161em portalu #zadovoljnahr \u2764\ufe0f @sasasekoranja"}}]}, "media_overlay_info": null, "gating_info": null, "is_published": true, "dimensions": {"height": 952, "width": 612}, "thumbnail_src": "https://scontent-prg1-1.cdninstagram.com/v/t51.2885-15/e15/c0.170.612.612a/124310268_195521312144582_4260407469223221134_n.jpg?tp=1&_nc_ht=scontent-prg1-1.cdninstagram.com&_nc_cat=102&_nc_ohc=N2LSpMKI_KsAX8Mqw8K&edm=ABfd0MgBAAAA&ccb=7-4&oh=76eaecf5446c5e682a77573f4857f69c&oe=60BC3808&_nc_sid=7bff83", "display_url": "https://scontent-prg1-1.cdninstagram.com/v/t51.2885-15/e15/124310268_195521312144582_4260407469223221134_n.jpg?tp=1&_nc_ht=scontent-prg1-1.cdninstagram.com&_nc_cat=102&_nc_ohc=N2LSpMKI_KsAX8Mqw8K&tn=Vcf8IfvvgXU4rjLb&edm=ABfd0MgBAAAA&ccb=7-4&oh=99a6711dbbaf47d6dfdb67b3938dd2a1&oe=60BC4C88&_nc_sid=7bff83", "is_video": true, "location": null, "edge_media_to_comment": {"count": 16}}}]}, "edge_owner_to_timeline_media": {"page_info": {"has_next_page": true, "end_cursor": "QVFDbWhueVQ1RXZ4M3FlMWE0elc5SDBPQTZVZmhSNTMxc0E3Vm92a2hyY1g1LUJSTlBQMmFSLV9iVG5iZ0k3MlhWYUlfZkR3NFRsRGhrN3ZYbmVRZlpBSA=="}, "count": 14603, "edges": [{"node": {"taken_at_timestamp": 1622815007, "shortcode": "CPs2OU9Hr4-", "id": "2588682364915727934", "owner": {"username": "zadovoljnahr", "id": "1428643188"}, "edge_media_preview_like": {"count": 257}, "fact_check_overall_rating": null, "media_preview": "ACEqlAyoPFPK4pFfK4HFJ/noP6VutTllFx3FI/GmkHt/KnBc9v14pWwAfYZ60BGLbS7jN/vRUe8UVnzHb7KPclC/KQO2CMe/X8qVUbG7t09/8inrnIPRQKVZxjnjHAHQc+vfP/66nmsrEct3zMiIOeOc0FSwKjqR1/p9aso4OSAOPSq0rGJC69O598+nWkpaWZcr3TW6v8xfKHpRR57eoopfJmXvEYQoPlOA3Xvz6j0J/KpBER06Y5z3+tRRHIH4VM5OD9KRoCEgbQMe9LjcCp6c5FQgnb+VQyMeeT2/lSGS7KKhzRTEf//Z", "gating_info": null, "sharing_friction_info": {"bloks_app_url": null, "should_have_sharing_friction": false}, "accessibility_caption": "Photo shared by zadovoljna.hr on June 04, 2021 tagging @danijela.adler. May be an image of flower and outdoors.", "__typename": "GraphImage", "comments_disabled": false, "edge_media_to_tagged_user": {"edges": [{"node": {"x": 0.56199306, "user": {"is_verified": false, "username": "danijela.adler", "id": "1621120830", "full_name": "Danijela, Croatia", "profile_pic_url": "https://scontent-prg1-1.cdninstagram.com/v/t51.2885-19/s150x150/182760626_134940988652502_4014970661169890050_n.jpg?tp=1&_nc_ht=scontent-prg1-1.cdninstagram.com&_nc_ohc=HVNgnkNmm-gAX_tAH2N&edm=ABfd0MgBAAAA&ccb=7-4&oh=3bb2b2a93e51ecb00ec4ea0e39c2216e&oe=60C162D5&_nc_sid=7bff83"}, "y": 0.5462963}}]}, "fact_check_information": null, "thumbnail_resources": [{"src": "https://scontent.cdninstagram.com/v/t51.2885-15/e35/p320x320/196932653_893193907931057_634318059398028671_n.jpg?tp=1&_nc_ht=scontent.cdninstagram.com&_nc_cat=105&_nc_ohc=SskDVsvGRxIAX9K8VZf&edm=AMO9-JQAAAAA&ccb=7-4&oh=d625c273103ae44bc2960a7d75558589&oe=60C07E1B&_nc_sid=b9f2ee", "config_width": 150, "config_height": 150}, {"src": "https://scontent.cdninstagram.com/v/t51.2885-15/e35/p320x320/196932653_893193907931057_634318059398028671_n.jpg?tp=1&_nc_ht=scontent.cdninstagram.com&_nc_cat=105&_nc_ohc=SskDVsvGRxIAX9K8VZf&edm=AMO9-JQAAAAA&ccb=7-4&oh=d625c273103ae44bc2960a7d75558589&oe=60C07E1B&_nc_sid=b9f2ee", "config_width": 240, "config_height": 240}, {"src": "https://scontent.cdninstagram.com/v/t51.2885-15/e35/p320x320/196932653_893193907931057_634318059398028671_n.jpg?tp=1&_nc_ht=scontent.cdninstagram.com&_nc_cat=105&_nc_ohc=SskDVsvGRxIAX9K8VZf&edm=AMO9-JQAAAAA&ccb=7-4&oh=d625c273103ae44bc2960a7d75558589&oe=60C07E1B&_nc_sid=b9f2ee", "config_width": 320, "config_height": 320}, {"src": "https://scontent.cdninstagram.com/v/t51.2885-15/e35/p320x320/196932653_893193907931057_634318059398028671_n.jpg?tp=1&_nc_ht=scontent.cdninstagram.com&_nc_cat=105&_nc_ohc=SskDVsvGRxIAX9K8VZf&edm=AMO9-JQAAAAA&ccb=7-4&oh=d625c273103ae44bc2960a7d75558589&oe=60C07E1B&_nc_sid=b9f2ee", "config_width": 480, "config_height": 480}, {"src": "https://scontent.cdninstagram.com/v/t51.2885-15/e35/p320x320/196932653_893193907931057_634318059398028671_n.jpg?tp=1&_nc_ht=scontent.cdninstagram.com&_nc_cat=105&_nc_ohc=SskDVsvGRxIAX9K8VZf&edm=AMO9-JQAAAAA&ccb=7-4&oh=d625c273103ae44bc2960a7d75558589&oe=60C07E1B&_nc_sid=b9f2ee", "config_width": 640, "config_height": 640}], "edge_media_to_caption": {"edges": [{"node": {"text": "Jedna romanti\u010dna i izuzetno fotogeni\u010dna \"to\u010dka\" u Rovinju... \ud83e\udd70\ud83d\ude4c\ud83c\udffb\ud83c\udf38\n@danijela.adler\n#rovinj #romanticspot #zadovoljnahr"}}]}, "media_overlay_info": null, "edge_liked_by": {"count": 257}, "dimensions": {"height": 1350, "width": 1080}, "thumbnail_src": "https://scontent.cdninstagram.com/v/t51.2885-15/e35/p320x320/196932653_893193907931057_634318059398028671_n.jpg?tp=1&_nc_ht=scontent.cdninstagram.com&_nc_cat=105&_nc_ohc=SskDVsvGRxIAX9K8VZf&edm=AMO9-JQAAAAA&ccb=7-4&oh=d625c273103ae44bc2960a7d75558589&oe=60C07E1B&_nc_sid=b9f2ee", "display_url": "https://scontent.cdninstagram.com/v/t51.2885-15/e35/p320x320/196932653_893193907931057_634318059398028671_n.jpg?tp=1&_nc_ht=scontent.cdninstagram.com&_nc_cat=105&_nc_ohc=SskDVsvGRxIAX9K8VZf&edm=AMO9-JQAAAAA&ccb=7-4&oh=d625c273103ae44bc2960a7d75558589&oe=60C07E1B&_nc_sid=b9f2ee", "is_video": false, "location": null, "edge_media_to_comment": {"count": 0}}}, {"node": {"taken_at_timestamp": 1622802626, "shortcode": "CPsenDRHyV5", "id": "2588578510794597753", "owner": {"username": "zadovoljnahr", "id": "1428643188"}, "edge_media_preview_like": {"count": 637}, "fact_check_overall_rating": null, "media_preview": "ACEqubaQgDk8Uiux644+tN2gt83P+f5VXN2JUX1EMirSB2bB2kDuTx/PmgTAnapyQM4qRG3g564rPmbNFFIZ5p/u/qKKjzRRdjshwbd9f8+9WSijt1qGO3xy559BTmQy4C8YOCPp3oYlfqKLbYxIIwfTv3NLL8o4wc46datsAD71m/ZzvyeCABz0PuD/AJxQG4zcKKn8hvUUUihtxdeV8qfn1qB5pWIUAjGCxGB+R5/EVf2KSCQCR3xVaT/WY7Y6flTEXuT85wDjk+gqqXbdyOCOPX/D/wCvUp6n6f1oA+df92gRX8z6/p/jRS0Uhn//2Q==", "gating_info": null, "sharing_friction_info": {"bloks_app_url": null, "should_have_sharing_friction": false}, "accessibility_caption": "Photo shared by zadovoljna.hr on June 04, 2021 tagging @_tajana_j. May be an image of 1 person and outdoors.", "__typename": "GraphImage", "comments_disabled": false, "edge_media_to_tagged_user": {"edges": [{"node": {"x": 0.5520833, "user": {"is_verified": false, "username": "_tajana_j", "id": "297349278", "full_name": "_tajana_j", "profile_pic_url": "https://scontent-prg1-1.cdninstagram.com/v/t51.2885-19/s150x150/118922227_330868798148988_1277910442751652521_n.jpg?tp=1&_nc_ht=scontent-prg1-1.cdninstagram.com&_nc_ohc=G0ensBQgHH4AX9KqNPE&tn=Vcf8IfvvgXU4rjLb&edm=ABfd0MgBAAAA&ccb=7-4&oh=6d030fb60140b5600f7d1c3d29ff6ad2&oe=60C101B3&_nc_sid=7bff83"}, "y": 0.51111114}}]}, "fact_check_information": null, "thumbnail_resources": [{"src": "https://scontent.cdninstagram.com/v/t51.2885-15/e35/p320x320/195486291_338520331037418_4040503280874636513_n.jpg?tp=1&_nc_ht=scontent.cdninstagram.com&_nc_cat=1&_nc_ohc=XenX-DYVzvEAX8AykW6&edm=AMO9-JQAAAAA&ccb=7-4&oh=242520f493585c25387f56f461f15d6c&oe=60C19116&_nc_sid=b9f2ee", "config_width": 150, "config_height": 150}, {"src": "https://scontent.cdninstagram.com/v/t51.2885-15/e35/p320x320/195486291_338520331037418_4040503280874636513_n.jpg?tp=1&_nc_ht=scontent.cdninstagram.com&_nc_cat=1&_nc_ohc=XenX-DYVzvEAX8AykW6&edm=AMO9-JQAAAAA&ccb=7-4&oh=242520f493585c25387f56f461f15d6c&oe=60C19116&_nc_sid=b9f2ee", "config_width": 240, "config_height": 240}, {"src": "https://scontent.cdninstagram.com/v/t51.2885-15/e35/p320x320/195486291_338520331037418_4040503280874636513_n.jpg?tp=1&_nc_ht=scontent.cdninstagram.com&_nc_cat=1&_nc_ohc=XenX-DYVzvEAX8AykW6&edm=AMO9-JQAAAAA&ccb=7-4&oh=242520f493585c25387f56f461f15d6c&oe=60C19116&_nc_sid=b9f2ee", "config_width": 320, "config_height": 320}, {"src": "https://scontent.cdninstagram.com/v/t51.2885-15/e35/p320x320/195486291_338520331037418_4040503280874636513_n.jpg?tp=1&_nc_ht=scontent.cdninstagram.com&_nc_cat=1&_nc_ohc=XenX-DYVzvEAX8AykW6&edm=AMO9-JQAAAAA&ccb=7-4&oh=242520f493585c25387f56f461f15d6c&oe=60C19116&_nc_sid=b9f2ee", "config_width": 480, "config_height": 480}, {"src": "https://scontent.cdninstagram.com/v/t51.2885-15/e35/p320x320/195486291_338520331037418_4040503280874636513_n.jpg?tp=1&_nc_ht=scontent.cdninstagram.com&_nc_cat=1&_nc_ohc=XenX-DYVzvEAX8AykW6&edm=AMO9-JQAAAAA&ccb=7-4&oh=242520f493585c25387f56f461f15d6c&oe=60C19116&_nc_sid=b9f2ee", "config_width": 640, "config_height": 640}], "edge_media_to_caption": {"edges": [{"node": {"text": "Divna @_tajana_j  u stylish kombinaciji koju bi rado nosile. \ud83d\ude0d\u2728\n#styleinspo #instafashion #zadovoljnahr"}}]}, "media_overlay_info": null, "edge_liked_by": {"count": 637}, "dimensions": {"height": 1350, "width": 1080}, "thumbnail_src": "https://scontent.cdninstagram.com/v/t51.2885-15/e35/p320x320/195486291_338520331037418_4040503280874636513_n.jpg?tp=1&_nc_ht=scontent.cdninstagram.com&_nc_cat=1&_nc_ohc=XenX-DYVzvEAX8AykW6&edm=AMO9-JQAAAAA&ccb=7-4&oh=242520f493585c25387f56f461f15d6c&oe=60C19116&_nc_sid=b9f2ee", "display_url": "https://scontent.cdninstagram.com/v/t51.2885-15/e35/p320x320/195486291_338520331037418_4040503280874636513_n.jpg?tp=1&_nc_ht=scontent.cdninstagram.com&_nc_cat=1&_nc_ohc=XenX-DYVzvEAX8AykW6&edm=AMO9-JQAAAAA&ccb=7-4&oh=242520f493585c25387f56f461f15d6c&oe=60C19116&_nc_sid=b9f2ee", "is_video": false, "location": null, "edge_media_to_comment": {"count": 4}}}, {"node": {"taken_at_timestamp": 1622793693, "shortcode": "CPsNkfSHyzt", "id": "2588503567927028973", "owner": {"username": "zadovoljnahr", "id": "1428643188"}, "edge_media_preview_like": {"count": 984}, "fact_check_overall_rating": null, "media_preview": "ACEqhSQwNvxkdwK2on8xS2MZU01YYwM7R+VS+SPcduDikMr3AyBjrj/DrVGVXdgGAIP3uOgyO+f8/hWm1sjdc5+v/wBao2tv9pv0pgVsD+6KKk+zf7TfpRSGOmPlgKgI+XscHuTweSfb0qqrXG4AN+Jx0PQehqwIwWVt2QueDxnPuODjp2NQfZI4m3ucc55Jxnk/jUepXoaryKp2nrjNQidZCUGQR3IyOuP51nCfczEsuBgjHOef0/CnxAA7jkMwwc8gDrwe+cD86dxcpcxL6j/vj/7KiquYvT9P/r0UXCxWt5y0jRHJVScbjnuR1wD+eTmrcibxjgj0P+eKy4P+Plvq3/oVa1WQQFEb5ZBvHbLHI69s4/KpcR4/d4DLwAxIwfr9Ki7/AJ/zao0H7zHY44/CocblqVhvkXH+x+f/ANeio80VNvT7v+CVf+v6R//Z", "gating_info": null, "sharing_friction_info": {"bloks_app_url": null, "should_have_sharing_friction": false}, "accessibility_caption": "Photo shared by zadovoljna.hr on June 04, 2021 tagging @smyk_w_kuchni_blog. May be an image of indoor.", "__typename": "GraphImage", "comments_disabled": false, "edge_media_to_tagged_user": {"edges": [{"node": {"x": 0.46296296, "user": {"is_verified": false, "username": "smyk_w_kuchni_blog", "id": "2013024542", "full_name": "Karola Smyk \u2763\ufe0f", "profile_pic_url": "https://scontent-prg1-1.cdninstagram.com/v/t51.2885-19/s150x150/57751228_290273551850026_6876837395082248192_n.jpg?tp=1&_nc_ht=scontent-prg1-1.cdninstagram.com&_nc_ohc=8tUb8jU1EhQAX8_sIoF&edm=ABfd0MgBAAAA&ccb=7-4&oh=e8dfb0b078c079521e5336be78b0912f&oe=60C13894&_nc_sid=7bff83"}, "y": 0.5324074}}]}, "fact_check_information": null, "thumbnail_resources": [{"src": "https://scontent.cdninstagram.com/v/t51.2885-15/e35/p320x320/196227382_761052414578536_831714302300053069_n.jpg?tp=1&_nc_ht=scontent.cdninstagram.com&_nc_cat=1&_nc_ohc=2zHV9Bxomk4AX9eY75R&edm=AMO9-JQAAAAA&ccb=7-4&oh=53175547e2658cd7f86e18fdc11ab9f3&oe=60C216A8&_nc_sid=b9f2ee", "config_width": 150, "config_height": 150}, {"src": "https://scontent.cdninstagram.com/v/t51.2885-15/e35/p320x320/196227382_761052414578536_831714302300053069_n.jpg?tp=1&_nc_ht=scontent.cdninstagram.com&_nc_cat=1&_nc_ohc=2zHV9Bxomk4AX9eY75R&edm=AMO9-JQAAAAA&ccb=7-4&oh=53175547e2658cd7f86e18fdc11ab9f3&oe=60C216A8&_nc_sid=b9f2ee", "config_width": 240, "config_height": 240}, {"src": "https://scontent.cdninstagram.com/v/t51.2885-15/e35/p320x320/196227382_761052414578536_831714302300053069_n.jpg?tp=1&_nc_ht=scontent.cdninstagram.com&_nc_cat=1&_nc_ohc=2zHV9Bxomk4AX9eY75R&edm=AMO9-JQAAAAA&ccb=7-4&oh=53175547e2658cd7f86e18fdc11ab9f3&oe=60C216A8&_nc_sid=b9f2ee", "config_width": 320, "config_height": 320}, {"src": "https://scontent.cdninstagram.com/v/t51.2885-15/e35/p320x320/196227382_761052414578536_831714302300053069_n.jpg?tp=1&_nc_ht=scontent.cdninstagram.com&_nc_cat=1&_nc_ohc=2zHV9Bxomk4AX9eY75R&edm=AMO9-JQAAAAA&ccb=7-4&oh=53175547e2658cd7f86e18fdc11ab9f3&oe=60C216A8&_nc_sid=b9f2ee", "config_width": 480, "config_height": 480}, {"src": "https://scontent.cdninstagram.com/v/t51.2885-15/e35/p320x320/196227382_761052414578536_831714302300053069_n.jpg?tp=1&_nc_ht=scontent.cdninstagram.com&_nc_cat=1&_nc_ohc=2zHV9Bxomk4AX9eY75R&edm=AMO9-JQAAAAA&ccb=7-4&oh=53175547e2658cd7f86e18fdc11ab9f3&oe=60C216A8&_nc_sid=b9f2ee", "config_width": 640, "config_height": 640}], "edge_media_to_caption": {"edges": [{"node": {"text": "Najvi\u0161e volimo kada kuhinja miri\u0161e na kola\u010d... \ud83e\udd70\n@smyk_w_kuchni_blog\n#kitcheninspo #homedesign #zadovoljnahr"}}]}, "media_overlay_info": null, "edge_liked_by": {"count": 984}, "dimensions": {"height": 1350, "width": 1080}, "thumbnail_src": "https://scontent.cdninstagram.com/v/t51.2885-15/e35/p320x320/196227382_761052414578536_831714302300053069_n.jpg?tp=1&_nc_ht=scontent.cdninstagram.com&_nc_cat=1&_nc_ohc=2zHV9Bxomk4AX9eY75R&edm=AMO9-JQAAAAA&ccb=7-4&oh=53175547e2658cd7f86e18fdc11ab9f3&oe=60C216A8&_nc_sid=b9f2ee", "display_url": "https://scontent.cdninstagram.com/v/t51.2885-15/e35/p320x320/196227382_761052414578536_831714302300053069_n.jpg?tp=1&_nc_ht=scontent.cdninstagram.com&_nc_cat=1&_nc_ohc=2zHV9Bxomk4AX9eY75R&edm=AMO9-JQAAAAA&ccb=7-4&oh=53175547e2658cd7f86e18fdc11ab9f3&oe=60C216A8&_nc_sid=b9f2ee", "is_video": false, "location": null, "edge_media_to_comment": {"count": 2}}}, {"node": {"taken_at_timestamp": 1622747359, "shortcode": "CPq1MenHacN", "id": "2588114889845090061", "owner": {"username": "zadovoljnahr", "id": "1428643188"}, "edge_media_preview_like": {"count": 1107}, "fact_check_overall_rating": null, "media_preview": null, "gating_info": null, "sharing_friction_info": {"bloks_app_url": null, "should_have_sharing_friction": false}, "accessibility_caption": "Photo shared by zadovoljna.hr on June 03, 2021 tagging @jonnatykkaa. May be an image of outdoors.", "__typename": "GraphImage", "comments_disabled": false, "edge_media_to_tagged_user": {"edges": [{"node": {"x": 0.5532407, "user": {"is_verified": false, "username": "jonnatykkaa", "id": "1223129166", "full_name": "Jonna | BOHORUSTIC INTERIOR", "profile_pic_url": "https://scontent-prg1-1.cdninstagram.com/v/t51.2885-19/s150x150/71826618_1892274017585753_408138866554306560_n.jpg?tp=1&_nc_ht=scontent-prg1-1.cdninstagram.com&_nc_ohc=N4PTBARteqgAX-GJ1Lg&edm=ABfd0MgBAAAA&ccb=7-4&oh=4625e4e1efb916593fddd3e54d190e51&oe=60C06826&_nc_sid=7bff83"}, "y": 0.5074074}}]}, "fact_check_information": null, "thumbnail_resources": [{"src": "https://scontent.cdninstagram.com/v/t51.2885-15/e35/p320x320/196938725_1183217988808991_4431729942511457478_n.jpg?tp=1&_nc_ht=scontent.cdninstagram.com&_nc_cat=111&_nc_ohc=KAMf95GK38oAX9Zh_jU&edm=AMO9-JQAAAAA&ccb=7-4&oh=e0aa87d6def5078b42a934a1e688e369&oe=60C0EF2A&_nc_sid=b9f2ee", "config_width": 150, "config_height": 150}, {"src": "https://scontent.cdninstagram.com/v/t51.2885-15/e35/p320x320/196938725_1183217988808991_4431729942511457478_n.jpg?tp=1&_nc_ht=scontent.cdninstagram.com&_nc_cat=111&_nc_ohc=KAMf95GK38oAX9Zh_jU&edm=AMO9-JQAAAAA&ccb=7-4&oh=e0aa87d6def5078b42a934a1e688e369&oe=60C0EF2A&_nc_sid=b9f2ee", "config_width": 240, "config_height": 240}, {"src": "https://scontent.cdninstagram.com/v/t51.2885-15/e35/p320x320/196938725_1183217988808991_4431729942511457478_n.jpg?tp=1&_nc_ht=scontent.cdninstagram.com&_nc_cat=111&_nc_ohc=KAMf95GK38oAX9Zh_jU&edm=AMO9-JQAAAAA&ccb=7-4&oh=e0aa87d6def5078b42a934a1e688e369&oe=60C0EF2A&_nc_sid=b9f2ee", "config_width": 320, "config_height": 320}, {"src": "https://scontent.cdninstagram.com/v/t51.2885-15/e35/p320x320/196938725_1183217988808991_4431729942511457478_n.jpg?tp=1&_nc_ht=scontent.cdninstagram.com&_nc_cat=111&_nc_ohc=KAMf95GK38oAX9Zh_jU&edm=AMO9-JQAAAAA&ccb=7-4&oh=e0aa87d6def5078b42a934a1e688e369&oe=60C0EF2A&_nc_sid=b9f2ee", "config_width": 480, "config_height": 480}, {"src": "https://scontent.cdninstagram.com/v/t51.2885-15/e35/p320x320/196938725_1183217988808991_4431729942511457478_n.jpg?tp=1&_nc_ht=scontent.cdninstagram.com&_nc_cat=111&_nc_ohc=KAMf95GK38oAX9Zh_jU&edm=AMO9-JQAAAAA&ccb=7-4&oh=e0aa87d6def5078b42a934a1e688e369&oe=60C0EF2A&_nc_sid=b9f2ee", "config_width": 640, "config_height": 640}], "edge_media_to_caption": {"edges": [{"node": {"text": "Vidimo se na ovoj terasici, ba\u0161 bi nam bilo lijepo ovdje provesti ve\u010der... \u2764\ufe0f\n@jonnatykkaa\n#amazingterrace #outdoordesign #zadovoljnahr"}}]}, "media_overlay_info": null, "edge_liked_by": {"count": 1107}, "dimensions": {"height": 1350, "width": 1080}, "thumbnail_src": "https://scontent.cdninstagram.com/v/t51.2885-15/e35/p320x320/196938725_1183217988808991_4431729942511457478_n.jpg?tp=1&_nc_ht=scontent.cdninstagram.com&_nc_cat=111&_nc_ohc=KAMf95GK38oAX9Zh_jU&edm=AMO9-JQAAAAA&ccb=7-4&oh=e0aa87d6def5078b42a934a1e688e369&oe=60C0EF2A&_nc_sid=b9f2ee", "display_url": "https://scontent.cdninstagram.com/v/t51.2885-15/e35/p320x320/196938725_1183217988808991_4431729942511457478_n.jpg?tp=1&_nc_ht=scontent.cdninstagram.com&_nc_cat=111&_nc_ohc=KAMf95GK38oAX9Zh_jU&edm=AMO9-JQAAAAA&ccb=7-4&oh=e0aa87d6def5078b42a934a1e688e369&oe=60C0EF2A&_nc_sid=b9f2ee", "is_video": false, "location": null, "edge_media_to_comment": {"count": 3}}}, {"node": {"taken_at_timestamp": 1622735593, "shortcode": "CPqewRnnhEt", "id": "2588016194726269229", "owner": {"username": "zadovoljnahr", "id": "1428643188"}, "edge_media_preview_like": {"count": 2911}, "fact_check_overall_rating": null, "media_preview": "ACEq2SQoyTge9QtdRqMk+31qneuS+zHGOD/nrWespBI7A9T/AJ/SoNrG9HOjnapycZx7VNXNJO0J3Dgj9c/09a6NW3KG9RmmJqw6ikopCMm6by5TnnOD+FUGc5wwwD2PWti7tzNypwR2PQ8/zqm1tIBkkfQZoNE7FeLbK4Qng8cckHHp3rdiBVQD1FVLW3MQ3nGT+lXAaZLd9R9FJmikSMNRHk1IajH3qED2JTkLikFSP0/z61EKbFHYfmim0Uij/9k=", "gating_info": null, "sharing_friction_info": {"bloks_app_url": null, "should_have_sharing_friction": false}, "accessibility_caption": "Photo shared by zadovoljna.hr on June 03, 2021 tagging @flowerbowl. May be an image of flower.", "__typename": "GraphImage", "comments_disabled": false, "edge_media_to_tagged_user": {"edges": [{"node": {"x": 0.5034722, "user": {"is_verified": false, "username": "flowerbowl", "id": "25271811", "full_name": "Florists & Flower Lovers", "profile_pic_url": "https://scontent-prg1-1.cdninstagram.com/v/t51.2885-19/s150x150/38035136_515566662232547_8071567206565019648_n.jpg?tp=1&_nc_ht=scontent-prg1-1.cdninstagram.com&_nc_ohc=kZKFTj06YEAAX_kjzSv&edm=ABfd0MgBAAAA&ccb=7-4&oh=df154247895c04ef64bb34c7098bdaf2&oe=60C0F5D6&_nc_sid=7bff83"}, "y": 0.4722222}}]}, "fact_check_information": null, "thumbnail_resources": [{"src": "https://scontent-prg1-1.cdninstagram.com/v/t51.2885-15/e35/c0.135.1080.1080a/s150x150/195087969_236948471102093_8758734011375857645_n.jpg?tp=1&_nc_ht=scontent-prg1-1.cdninstagram.com&_nc_cat=105&_nc_ohc=R3bEjbqdt6MAX8EwFAi&edm=ABfd0MgBAAAA&ccb=7-4&oh=957d39ba23d5203c1b5bdde87783fba4&oe=60C099C4&_nc_sid=7bff83", "config_width": 150, "config_height": 150}, {"src": "https://scontent-prg1-1.cdninstagram.com/v/t51.2885-15/e35/c0.135.1080.1080a/s240x240/195087969_236948471102093_8758734011375857645_n.jpg?tp=1&_nc_ht=scontent-prg1-1.cdninstagram.com&_nc_cat=105&_nc_ohc=R3bEjbqdt6MAX8EwFAi&tn=Vcf8IfvvgXU4rjLb&edm=ABfd0MgBAAAA&ccb=7-4&oh=88d7d4fe98408629b10f217ab8bdc1f7&oe=60C16DC6&_nc_sid=7bff83", "config_width": 240, "config_height": 240}, {"src": "https://scontent-prg1-1.cdninstagram.com/v/t51.2885-15/e35/c0.135.1080.1080a/s320x320/195087969_236948471102093_8758734011375857645_n.jpg?tp=1&_nc_ht=scontent-prg1-1.cdninstagram.com&_nc_cat=105&_nc_ohc=R3bEjbqdt6MAX8EwFAi&edm=ABfd0MgBAAAA&ccb=7-4&oh=1ded73031fb2f91dbe84290e88572edc&oe=60C0D07C&_nc_sid=7bff83", "config_width": 320, "config_height": 320}, {"src": "https://scontent-prg1-1.cdninstagram.com/v/t51.2885-15/e35/c0.135.1080.1080a/s480x480/195087969_236948471102093_8758734011375857645_n.jpg?tp=1&_nc_ht=scontent-prg1-1.cdninstagram.com&_nc_cat=105&_nc_ohc=R3bEjbqdt6MAX8EwFAi&tn=Vcf8IfvvgXU4rjLb&edm=ABfd0MgBAAAA&ccb=7-4&oh=f5f6dd0924ca6991b52d277d1c2436b0&oe=60C0367D&_nc_sid=7bff83", "config_width": 480, "config_height": 480}, {"src": "https://scontent-prg1-1.cdninstagram.com/v/t51.2885-15/sh0.08/e35/c0.135.1080.1080a/s640x640/195087969_236948471102093_8758734011375857645_n.jpg?tp=1&_nc_ht=scontent-prg1-1.cdninstagram.com&_nc_cat=105&_nc_ohc=R3bEjbqdt6MAX8EwFAi&edm=ABfd0MgBAAAA&ccb=7-4&oh=d46577b430e848c416aa4314b0b97e50&oe=60C0E274&_nc_sid=7bff83", "config_width": 640, "config_height": 640}], "edge_media_to_caption": {"edges": [{"node": {"text": "\ud83d\ude0d\ud83d\ude0d\ud83d\ude0d\ud83d\ude0d\n@flowerbowl\n#flowerstagram #beautiful #zadovoljnahr"}}]}, "media_overlay_info": null, "edge_liked_by": {"count": 2911}, "dimensions": {"height": 1350, "width": 1080}, "thumbnail_src": "https://scontent-prg1-1.cdninstagram.com/v/t51.2885-15/sh0.08/e35/c0.135.1080.1080a/s640x640/195087969_236948471102093_8758734011375857645_n.jpg?tp=1&_nc_ht=scontent-prg1-1.cdninstagram.com&_nc_cat=105&_nc_ohc=R3bEjbqdt6MAX8EwFAi&edm=ABfd0MgBAAAA&ccb=7-4&oh=d46577b430e848c416aa4314b0b97e50&oe=60C0E274&_nc_sid=7bff83", "display_url": "https://scontent-prg1-1.cdninstagram.com/v/t51.2885-15/e35/195087969_236948471102093_8758734011375857645_n.jpg?tp=1&_nc_ht=scontent-prg1-1.cdninstagram.com&_nc_cat=105&_nc_ohc=R3bEjbqdt6MAX8EwFAi&edm=ABfd0MgBAAAA&ccb=7-4&oh=54d7b860ab55086e8b4400d3bf1f4763&oe=60C13AE5&_nc_sid=7bff83", "is_video": false, "location": null, "edge_media_to_comment": {"count": 16}}}, {"node": {"taken_at_timestamp": 1622720486, "shortcode": "CPqB8KuH14a", "id": "2587889468604112410", "owner": {"username": "zadovoljnahr", "id": "1428643188"}, "edge_media_preview_like": {"count": 4643}, "fact_check_overall_rating": null, "media_preview": "ACoq3iM03aafTS4HWgBNpo20eah7il3j1oGOAxRRRQIKjOc98d+Rx/jUlBGaAI+enP5ijn3/ADFPx/nFAFAxRRRRQIKKKKACijFNagYpYCm7qbRSA//Z", "gating_info": null, "sharing_friction_info": {"bloks_app_url": null, "should_have_sharing_friction": false}, "accessibility_caption": "Photo by zadovoljna.hr on June 03, 2021. May be an image of text.", "__typename": "GraphImage", "comments_disabled": false, "edge_media_to_tagged_user": {"edges": []}, "fact_check_information": null, "thumbnail_resources": [{"src": "https://scontent-prg1-1.cdninstagram.com/v/t51.2885-15/e35/s150x150/196284502_379749126802353_3938086582550997681_n.jpg?tp=1&_nc_ht=scontent-prg1-1.cdninstagram.com&_nc_cat=109&_nc_ohc=L6zl9_LYVgkAX9B2NTD&edm=ABfd0MgBAAAA&ccb=7-4&oh=3c91aa71bdcb72b41ce2c98796281a1a&oe=60C03089&_nc_sid=7bff83", "config_width": 150, "config_height": 150}, {"src": "https://scontent-prg1-1.cdninstagram.com/v/t51.2885-15/e35/s240x240/196284502_379749126802353_3938086582550997681_n.jpg?tp=1&_nc_ht=scontent-prg1-1.cdninstagram.com&_nc_cat=109&_nc_ohc=L6zl9_LYVgkAX9B2NTD&edm=ABfd0MgBAAAA&ccb=7-4&oh=87a8fcc5bfff23e21e5f7fbb10df0cd0&oe=60C1C54F&_nc_sid=7bff83", "config_width": 240, "config_height": 240}, {"src": "https://scontent-prg1-1.cdninstagram.com/v/t51.2885-15/e35/s320x320/196284502_379749126802353_3938086582550997681_n.jpg?tp=1&_nc_ht=scontent-prg1-1.cdninstagram.com&_nc_cat=109&_nc_ohc=L6zl9_LYVgkAX9B2NTD&edm=ABfd0MgBAAAA&ccb=7-4&oh=818d2b7252f136c68a86c6dd40881c65&oe=60C12971&_nc_sid=7bff83", "config_width": 320, "config_height": 320}, {"src": "https://scontent-prg1-1.cdninstagram.com/v/t51.2885-15/e35/s480x480/196284502_379749126802353_3938086582550997681_n.jpg?tp=1&_nc_ht=scontent-prg1-1.cdninstagram.com&_nc_cat=109&_nc_ohc=L6zl9_LYVgkAX9B2NTD&edm=ABfd0MgBAAAA&ccb=7-4&oh=8b4c57f0984032e3fd30dd220ec29ec2&oe=60C07BB8&_nc_sid=7bff83", "config_width": 480, "config_height": 480}, {"src": "https://scontent-prg1-1.cdninstagram.com/v/t51.2885-15/sh0.08/e35/s640x640/196284502_379749126802353_3938086582550997681_n.jpg?tp=1&_nc_ht=scontent-prg1-1.cdninstagram.com&_nc_cat=109&_nc_ohc=L6zl9_LYVgkAX9B2NTD&edm=ABfd0MgBAAAA&ccb=7-4&oh=be2d6a1870d9888fdd04d6687f3a2726&oe=60C1438E&_nc_sid=7bff83", "config_width": 640, "config_height": 640}], "edge_media_to_caption": {"edges": [{"node": {"text": "Ne penjite se po drve\u0107u i ne mijenjajte jastuke! \ud83d\ude00\ud83d\ude00\n#funny #youngandtough #zadovoljnahr"}}]}, "media_overlay_info": null, "edge_liked_by": {"count": 4643}, "dimensions": {"height": 1080, "width": 1080}, "thumbnail_src": "https://scontent-prg1-1.cdninstagram.com/v/t51.2885-15/sh0.08/e35/s640x640/196284502_379749126802353_3938086582550997681_n.jpg?tp=1&_nc_ht=scontent-prg1-1.cdninstagram.com&_nc_cat=109&_nc_ohc=L6zl9_LYVgkAX9B2NTD&edm=ABfd0MgBAAAA&ccb=7-4&oh=be2d6a1870d9888fdd04d6687f3a2726&oe=60C1438E&_nc_sid=7bff83", "display_url": "https://scontent-prg1-1.cdninstagram.com/v/t51.2885-15/e35/196284502_379749126802353_3938086582550997681_n.jpg?tp=1&_nc_ht=scontent-prg1-1.cdninstagram.com&_nc_cat=109&_nc_ohc=L6zl9_LYVgkAX9B2NTD&tn=Vcf8IfvvgXU4rjLb&edm=ABfd0MgBAAAA&ccb=7-4&oh=24dd597eb0113218d9e1e69b37d127c5&oe=60C214B8&_nc_sid=7bff83", "is_video": false, "location": null, "edge_media_to_comment": {"count": 100}}}, {"node": {"taken_at_timestamp": 1622706754, "shortcode": "CPpnv2THQjA", "id": "2587774272833128640", "owner": {"username": "zadovoljnahr", "id": "1428643188"}, "edge_media_preview_like": {"count": 1649}, "fact_check_overall_rating": null, "media_preview": "ACEqfcHLEdKgWNXfHBPTJ5GPYH/9dU552kkbOQATgfQ4pEzAQzZ55Xt/n0NNFI2dPVbXIJyz9fQY7e/1rTRQH3D+IH8+K5xcmYeWck9c9PX9P51rQOWAXeWcdQOMAY6dPxGeRUNq+hJp0U3C/wCz+lFMDk7zmYEZJP17fSnywyygs4Cqo+XOASR1wO5Pf/GoJ2cyb0zgDsfzp3ku4UIDIoJJOemcZHP6GlcuxKlurwiUMd46qPXp9ePWr0cAuVAUDAIJOSCezA55/p6VVihnifKgqvuwH58849u9bFsQgyuNvQep56c1NrktWG/2RB/tfnRV/wAxPUfnRVWQjko+ePcCtCIYOeOST+A4rPh+8PqKvxfdX6f+zVBsTSEInXB6A98/5/lWfZMZCUPJY5Lf5/nx1rQlGV59v61lWhIkwOMmjoQzpfs8fp+goqtuPqaKqxNz/9k=", "gating_info": null, "sharing_friction_info": {"bloks_app_url": null, "should_have_sharing_friction": false}, "accessibility_caption": "Photo shared by zadovoljna.hr on June 03, 2021 tagging @diaverphoto. May be an image of flower.", "__typename": "GraphImage", "comments_disabled": false, "edge_media_to_tagged_user": {"edges": [{"node": {"x": 0.5451389, "user": {"is_verified": false, "username": "diaverphoto", "id": "1926363049", "full_name": "\u2606\u0424\u043e\u0442\u043e \u0438 \u0416\u0438\u0437\u043d\u044c\u2606", "profile_pic_url": "https://scontent-prg1-1.cdninstagram.com/v/t51.2885-19/s150x150/110022040_932175757299495_6706782557314443972_n.jpg?tp=1&_nc_ht=scontent-prg1-1.cdninstagram.com&_nc_ohc=jzP_bTV2yF8AX-87Ttq&edm=ABfd0MgBAAAA&ccb=7-4&oh=9a91985b0ee4a6d4c6f6b04451e56b33&oe=60C1F162&_nc_sid=7bff83"}, "y": 0.46944445}}]}, "fact_check_information": null, "thumbnail_resources": [{"src": "https://scontent-prg1-1.cdninstagram.com/v/t51.2885-15/e35/c0.107.859.859a/s150x150/195472820_161819665914528_2248063168110384802_n.jpg?tp=1&_nc_ht=scontent-prg1-1.cdninstagram.com&_nc_cat=100&_nc_ohc=Mtot-bQtvQoAX_KBsDH&edm=ABfd0MgBAAAA&ccb=7-4&oh=5a71d67b37cb521d98a055a7a36428af&oe=60C0A713&_nc_sid=7bff83", "config_width": 150, "config_height": 150}, {"src": "https://scontent-prg1-1.cdninstagram.com/v/t51.2885-15/e35/c0.107.859.859a/s240x240/195472820_161819665914528_2248063168110384802_n.jpg?tp=1&_nc_ht=scontent-prg1-1.cdninstagram.com&_nc_cat=100&_nc_ohc=Mtot-bQtvQoAX_KBsDH&tn=Vcf8IfvvgXU4rjLb&edm=ABfd0MgBAAAA&ccb=7-4&oh=ed65c6a6cd87727ab3d5b58aac86b289&oe=60C14E95&_nc_sid=7bff83", "config_width": 240, "config_height": 240}, {"src": "https://scontent-prg1-1.cdninstagram.com/v/t51.2885-15/e35/c0.107.859.859a/s320x320/195472820_161819665914528_2248063168110384802_n.jpg?tp=1&_nc_ht=scontent-prg1-1.cdninstagram.com&_nc_cat=100&_nc_ohc=Mtot-bQtvQoAX_KBsDH&edm=ABfd0MgBAAAA&ccb=7-4&oh=bcdff8d7129b970d047a605cd9281730&oe=60C0AA6B&_nc_sid=7bff83", "config_width": 320, "config_height": 320}, {"src": "https://scontent-prg1-1.cdninstagram.com/v/t51.2885-15/e35/c0.107.859.859a/s480x480/195472820_161819665914528_2248063168110384802_n.jpg?tp=1&_nc_ht=scontent-prg1-1.cdninstagram.com&_nc_cat=100&_nc_ohc=Mtot-bQtvQoAX_KBsDH&edm=ABfd0MgBAAAA&ccb=7-4&oh=4ad9de52420a9667e78bad2936192f9f&oe=60C07A2E&_nc_sid=7bff83", "config_width": 480, "config_height": 480}, {"src": "https://scontent-prg1-1.cdninstagram.com/v/t51.2885-15/sh0.08/e35/c0.107.859.859a/s640x640/195472820_161819665914528_2248063168110384802_n.jpg?tp=1&_nc_ht=scontent-prg1-1.cdninstagram.com&_nc_cat=100&_nc_ohc=Mtot-bQtvQoAX_KBsDH&edm=ABfd0MgBAAAA&ccb=7-4&oh=d1b5ebd45ebe4016ce8d75a51444c920&oe=60C1B116&_nc_sid=7bff83", "config_width": 640, "config_height": 640}], "edge_media_to_caption": {"edges": [{"node": {"text": "Jutro! \ud83d\ude0d\ud83e\udd70 \ud83d\udc36\n#puppiesofinstagram #cutedoggo #goodmorning #zadovoljnahr\n@diaverphoto"}}]}, "media_overlay_info": null, "edge_liked_by": {"count": 1649}, "dimensions": {"height": 1349, "width": 1080}, "thumbnail_src": "https://scontent-prg1-1.cdninstagram.com/v/t51.2885-15/sh0.08/e35/c0.107.859.859a/s640x640/195472820_161819665914528_2248063168110384802_n.jpg?tp=1&_nc_ht=scontent-prg1-1.cdninstagram.com&_nc_cat=100&_nc_ohc=Mtot-bQtvQoAX_KBsDH&edm=ABfd0MgBAAAA&ccb=7-4&oh=d1b5ebd45ebe4016ce8d75a51444c920&oe=60C1B116&_nc_sid=7bff83", "display_url": "https://scontent-prg1-1.cdninstagram.com/v/t51.2885-15/e35/195472820_161819665914528_2248063168110384802_n.jpg?tp=1&_nc_ht=scontent-prg1-1.cdninstagram.com&_nc_cat=100&_nc_ohc=Mtot-bQtvQoAX_KBsDH&edm=ABfd0MgBAAAA&ccb=7-4&oh=f4944a9a83e1954882638f9af1c91415&oe=60C02407&_nc_sid=7bff83", "is_video": false, "location": null, "edge_media_to_comment": {"count": 0}}}, {"node": {"taken_at_timestamp": 1622659256, "shortcode": "CPoNJy4n7KX", "id": "2587375833641366167", "owner": {"username": "zadovoljnahr", "id": "1428643188"}, "edge_media_preview_like": {"count": 2365}, "fact_check_overall_rating": null, "media_preview": null, "gating_info": null, "sharing_friction_info": {"bloks_app_url": null, "should_have_sharing_friction": false}, "accessibility_caption": "Photo shared by zadovoljna.hr on June 02, 2021 tagging @gozdee81. May be an image of flower and tree.", "__typename": "GraphImage", "comments_disabled": false, "edge_media_to_tagged_user": {"edges": [{"node": {"x": 0.44212964, "user": {"is_verified": false, "username": "gozdee81", "id": "144991592", "full_name": "Decor \u2022 DIY \u2764\ufe0f Go\u0308zde", "profile_pic_url": "https://scontent-prg1-1.cdninstagram.com/v/t51.2885-19/s150x150/191807383_384132326246408_3691877086743298836_n.jpg?tp=1&_nc_ht=scontent-prg1-1.cdninstagram.com&_nc_ohc=JdkUE-CTldYAX_d0NXU&edm=ABfd0MgBAAAA&ccb=7-4&oh=befaa18d73d91bddd45febb3b92a1272&oe=60C0DB81&_nc_sid=7bff83"}, "y": 0.51296294}}]}, "fact_check_information": null, "thumbnail_resources": [{"src": "https://scontent-prg1-1.cdninstagram.com/v/t51.2885-15/e35/c0.135.1080.1080a/s150x150/194784631_203444271635577_1357437774905388299_n.jpg?tp=1&_nc_ht=scontent-prg1-1.cdninstagram.com&_nc_cat=109&_nc_ohc=KDZQqQINeaAAX_u7Fo6&edm=ABfd0MgBAAAA&ccb=7-4&oh=fe6b38352c5546acf6ca54ed0faa395b&oe=60C0D656&_nc_sid=7bff83", "config_width": 150, "config_height": 150}, {"src": "https://scontent-prg1-1.cdninstagram.com/v/t51.2885-15/e35/c0.135.1080.1080a/s240x240/194784631_203444271635577_1357437774905388299_n.jpg?tp=1&_nc_ht=scontent-prg1-1.cdninstagram.com&_nc_cat=109&_nc_ohc=KDZQqQINeaAAX_u7Fo6&edm=ABfd0MgBAAAA&ccb=7-4&oh=1e0214a7a33a1a85fece05c32ec51d38&oe=60C206D4&_nc_sid=7bff83", "config_width": 240, "config_height": 240}, {"src": "https://scontent-prg1-1.cdninstagram.com/v/t51.2885-15/e35/c0.135.1080.1080a/s320x320/194784631_203444271635577_1357437774905388299_n.jpg?tp=1&_nc_ht=scontent-prg1-1.cdninstagram.com&_nc_cat=109&_nc_ohc=KDZQqQINeaAAX_u7Fo6&edm=ABfd0MgBAAAA&ccb=7-4&oh=af9fa66a3df1e686cfb8a50ec8cb536d&oe=60C1086E&_nc_sid=7bff83", "config_width": 320, "config_height": 320}, {"src": "https://scontent-prg1-1.cdninstagram.com/v/t51.2885-15/e35/c0.135.1080.1080a/s480x480/194784631_203444271635577_1357437774905388299_n.jpg?tp=1&_nc_ht=scontent-prg1-1.cdninstagram.com&_nc_cat=109&_nc_ohc=KDZQqQINeaAAX_u7Fo6&edm=ABfd0MgBAAAA&ccb=7-4&oh=d53f2bad4615cef3aab4d58aa9144599&oe=60C1126B&_nc_sid=7bff83", "config_width": 480, "config_height": 480}, {"src": "https://scontent-prg1-1.cdninstagram.com/v/t51.2885-15/sh0.08/e35/c0.135.1080.1080a/s640x640/194784631_203444271635577_1357437774905388299_n.jpg?tp=1&_nc_ht=scontent-prg1-1.cdninstagram.com&_nc_cat=109&_nc_ohc=KDZQqQINeaAAX_u7Fo6&tn=Vcf8IfvvgXU4rjLb&edm=ABfd0MgBAAAA&ccb=7-4&oh=03c57f818f4353ee33c5e81e5871616c&oe=60C14926&_nc_sid=7bff83", "config_width": 640, "config_height": 640}], "edge_media_to_caption": {"edges": [{"node": {"text": "Ako vam je sutra neradni dan, u\u017eivajte i opustite se. \ud83e\udd17 Ugodnu ve\u010der i produ\u017eeni vikend \u017eeli vam va\u0161a #zadovoljnahr\n@gozdee81\n#cosyterrace #cosyliving #zadovoljnahr"}}]}, "media_overlay_info": null, "edge_liked_by": {"count": 2365}, "dimensions": {"height": 1350, "width": 1080}, "thumbnail_src": "https://scontent-prg1-1.cdninstagram.com/v/t51.2885-15/sh0.08/e35/c0.135.1080.1080a/s640x640/194784631_203444271635577_1357437774905388299_n.jpg?tp=1&_nc_ht=scontent-prg1-1.cdninstagram.com&_nc_cat=109&_nc_ohc=KDZQqQINeaAAX_u7Fo6&edm=ABfd0MgBAAAA&ccb=7-4&oh=ffa043128bf25853013ea7d71ba9f933&oe=60C14926&_nc_sid=7bff83", "display_url": "https://scontent-prg1-1.cdninstagram.com/v/t51.2885-15/e35/194784631_203444271635577_1357437774905388299_n.jpg?tp=1&_nc_ht=scontent-prg1-1.cdninstagram.com&_nc_cat=109&_nc_ohc=KDZQqQINeaAAX_u7Fo6&edm=ABfd0MgBAAAA&ccb=7-4&oh=5cea0262e401686f84742475840a2216&oe=60C13D33&_nc_sid=7bff83", "is_video": false, "location": null, "edge_media_to_comment": {"count": 3}}}, {"node": {"taken_at_timestamp": 1622650708, "shortcode": "CPn82VsHMfS", "id": "2587304127878711250", "owner": {"username": "zadovoljnahr", "id": "1428643188"}, "edge_media_preview_like": {"count": 911}, "fact_check_overall_rating": null, "media_preview": null, "gating_info": null, "sharing_friction_info": {"bloks_app_url": null, "should_have_sharing_friction": false}, "accessibility_caption": "Photo by zadovoljna.hr on June 02, 2021. May be an image of flower and nature.", "__typename": "GraphImage", "comments_disabled": false, "edge_media_to_tagged_user": {"edges": []}, "fact_check_information": null, "thumbnail_resources": [{"src": "https://scontent-prg1-1.cdninstagram.com/v/t51.2885-15/e35/s150x150/194777017_1331911820527711_7274414788537363416_n.jpg?tp=1&_nc_ht=scontent-prg1-1.cdninstagram.com&_nc_cat=107&_nc_ohc=PfEPP0XjrFMAX-ACTza&edm=ABfd0MgBAAAA&ccb=7-4&oh=2502dfabcfaadd580615beb2072d4ede&oe=60C10CB5&_nc_sid=7bff83", "config_width": 150, "config_height": 150}, {"src": "https://scontent-prg1-1.cdninstagram.com/v/t51.2885-15/e35/s240x240/194777017_1331911820527711_7274414788537363416_n.jpg?tp=1&_nc_ht=scontent-prg1-1.cdninstagram.com&_nc_cat=107&_nc_ohc=PfEPP0XjrFMAX-ACTza&tn=Vcf8IfvvgXU4rjLb&edm=ABfd0MgBAAAA&ccb=7-4&oh=4353ddf117442990a847961d4eb2d726&oe=60C20C7D&_nc_sid=7bff83", "config_width": 240, "config_height": 240}, {"src": "https://scontent-prg1-1.cdninstagram.com/v/t51.2885-15/e35/s320x320/194777017_1331911820527711_7274414788537363416_n.jpg?tp=1&_nc_ht=scontent-prg1-1.cdninstagram.com&_nc_cat=107&_nc_ohc=PfEPP0XjrFMAX-ACTza&edm=ABfd0MgBAAAA&ccb=7-4&oh=26d775e4c79fdc799ec79d171a22e674&oe=60C15C64&_nc_sid=7bff83", "config_width": 320, "config_height": 320}, {"src": "https://scontent-prg1-1.cdninstagram.com/v/t51.2885-15/e35/s480x480/194777017_1331911820527711_7274414788537363416_n.jpg?tp=1&_nc_ht=scontent-prg1-1.cdninstagram.com&_nc_cat=107&_nc_ohc=PfEPP0XjrFMAX-ACTza&edm=ABfd0MgBAAAA&ccb=7-4&oh=1b11a02b22110a275d9e5aba2fc872da&oe=60C14162&_nc_sid=7bff83", "config_width": 480, "config_height": 480}, {"src": "https://scontent-prg1-1.cdninstagram.com/v/t51.2885-15/sh0.08/e35/s640x640/194777017_1331911820527711_7274414788537363416_n.jpg?tp=1&_nc_ht=scontent-prg1-1.cdninstagram.com&_nc_cat=107&_nc_ohc=PfEPP0XjrFMAX-ACTza&edm=ABfd0MgBAAAA&ccb=7-4&oh=55268de9e677156efcc210de6cb4f59c&oe=60C1E282&_nc_sid=7bff83", "config_width": 640, "config_height": 640}], "edge_media_to_caption": {"edges": [{"node": {"text": "Priroda nam svojom ljepotom u svakom trenutku mo\u017ee izmamiti osmjeh na lice. Ovo predivno polje ljubi\u010dastog maka nalazi se u Baranji a vi\u0161e o njemu mo\u017eete pogledati i pro\u010ditati na na\u0161em portalu #zadovoljnahr \ud83d\udc9c\n#poppyfield #beautifulnature #zadovoljnahr\n\ud83d\udcf8 Dubravka Petric/ PIXELL"}}]}, "media_overlay_info": null, "edge_liked_by": {"count": 911}, "dimensions": {"height": 1080, "width": 1080}, "thumbnail_src": "https://scontent-prg1-1.cdninstagram.com/v/t51.2885-15/sh0.08/e35/s640x640/194777017_1331911820527711_7274414788537363416_n.jpg?tp=1&_nc_ht=scontent-prg1-1.cdninstagram.com&_nc_cat=107&_nc_ohc=PfEPP0XjrFMAX-ACTza&edm=ABfd0MgBAAAA&ccb=7-4&oh=55268de9e677156efcc210de6cb4f59c&oe=60C1E282&_nc_sid=7bff83", "display_url": "https://scontent-prg1-1.cdninstagram.com/v/t51.2885-15/e35/s1080x1080/194777017_1331911820527711_7274414788537363416_n.jpg?tp=1&_nc_ht=scontent-prg1-1.cdninstagram.com&_nc_cat=107&_nc_ohc=PfEPP0XjrFMAX-ACTza&edm=ABfd0MgBAAAA&ccb=7-4&oh=f02dbd9533a0796b40dea3316ef57ba8&oe=60C0BA29&_nc_sid=7bff83", "is_video": false, "location": null, "edge_media_to_comment": {"count": 1}}}, {"node": {"taken_at_timestamp": 1622639513, "shortcode": "CPnnfsjKVkC", "id": "2587210212899903746", "owner": {"username": "zadovoljnahr", "id": "1428643188"}, "edge_media_preview_like": {"count": 753}, "fact_check_overall_rating": null, "media_preview": "ACoq3qKKKRQoBNNpwbFNoAKKKMUABNMyff8ASn03aKAE59/0o59/0pcCl2igYg/GnUUUCCiiigAxRRRQAUUtFAH/2Q==", "gating_info": null, "sharing_friction_info": {"bloks_app_url": null, "should_have_sharing_friction": false}, "accessibility_caption": "Photo shared by zadovoljna.hr on June 02, 2021 tagging @algebra_university_college. May be an image of text.", "__typename": "GraphImage", "comments_disabled": false, "edge_media_to_tagged_user": {"edges": [{"node": {"x": 0.7337037325, "user": {"is_verified": false, "username": "algebra_university_college", "id": "2280279311", "full_name": "Algebra university college", "profile_pic_url": "https://scontent-prg1-1.cdninstagram.com/v/t51.2885-19/s150x150/23823722_129349274406747_7665878352565108736_n.jpg?tp=1&_nc_ht=scontent-prg1-1.cdninstagram.com&_nc_ohc=hBT-ncFhvTAAX9BudIk&tn=Vcf8IfvvgXU4rjLb&edm=ABfd0MgBAAAA&ccb=7-4&oh=71ac8e5f56c4d2f18e0df9aba1534007&oe=60C0D0B5&_nc_sid=7bff83"}, "y": 0.4462963045}}]}, "fact_check_information": null, "thumbnail_resources": [{"src": "https://scontent-prg1-1.cdninstagram.com/v/t51.2885-15/e15/s150x150/194704693_492620248646265_8562663805338032901_n.jpg?tp=1&_nc_ht=scontent-prg1-1.cdninstagram.com&_nc_cat=109&_nc_ohc=Hrjp0sLVJu4AX-CKST3&edm=ABfd0MgBAAAA&ccb=7-4&oh=716fa77aef09a3dc52fe3834e4d41627&oe=60C0B93F&_nc_sid=7bff83", "config_width": 150, "config_height": 150}, {"src": "https://scontent-prg1-1.cdninstagram.com/v/t51.2885-15/e15/s240x240/194704693_492620248646265_8562663805338032901_n.jpg?tp=1&_nc_ht=scontent-prg1-1.cdninstagram.com&_nc_cat=109&_nc_ohc=Hrjp0sLVJu4AX-CKST3&edm=ABfd0MgBAAAA&ccb=7-4&oh=0bf81ce4640e1a01add81c8772c95ea8&oe=60C1B3F9&_nc_sid=7bff83", "config_width": 240, "config_height": 240}, {"src": "https://scontent-prg1-1.cdninstagram.com/v/t51.2885-15/e15/s320x320/194704693_492620248646265_8562663805338032901_n.jpg?tp=1&_nc_ht=scontent-prg1-1.cdninstagram.com&_nc_cat=109&_nc_ohc=Hrjp0sLVJu4AX-CKST3&tn=Vcf8IfvvgXU4rjLb&edm=ABfd0MgBAAAA&ccb=7-4&oh=32241865482d8ccdb52f9072e37e54cd&oe=60C1D9C7&_nc_sid=7bff83", "config_width": 320, "config_height": 320}, {"src": "https://scontent-prg1-1.cdninstagram.com/v/t51.2885-15/e15/s480x480/194704693_492620248646265_8562663805338032901_n.jpg?tp=1&_nc_ht=scontent-prg1-1.cdninstagram.com&_nc_cat=109&_nc_ohc=Hrjp0sLVJu4AX-CKST3&edm=ABfd0MgBAAAA&ccb=7-4&oh=e94bd95330166202e0c5c5725907ef50&oe=60C0F482&_nc_sid=7bff83", "config_width": 480, "config_height": 480}, {"src": "https://scontent-prg1-1.cdninstagram.com/v/t51.2885-15/sh0.08/e35/s640x640/194704693_492620248646265_8562663805338032901_n.jpg?tp=1&_nc_ht=scontent-prg1-1.cdninstagram.com&_nc_cat=109&_nc_ohc=Hrjp0sLVJu4AX-CKST3&edm=ABfd0MgBAAAA&ccb=7-4&oh=bf3a3fbd1c72b8f5d6c72a47d3ce24d0&oe=60C0BD44&_nc_sid=7bff83", "config_width": 640, "config_height": 640}], "edge_media_to_caption": {"edges": [{"node": {"text": "Prijavite se i sudjelujte u jednoj od 50 online edukacija Zadovoljna akademije! \n#rastemoZAjedno #Zadovoljnaakademija #Algebracjelo\u017eivotnoobrazovanje #google #zadovoljnahr"}}]}, "media_overlay_info": null, "edge_liked_by": {"count": 753}, "dimensions": {"height": 1080, "width": 1080}, "thumbnail_src": "https://scontent-prg1-1.cdninstagram.com/v/t51.2885-15/sh0.08/e35/s640x640/194704693_492620248646265_8562663805338032901_n.jpg?tp=1&_nc_ht=scontent-prg1-1.cdninstagram.com&_nc_cat=109&_nc_ohc=Hrjp0sLVJu4AX-CKST3&edm=ABfd0MgBAAAA&ccb=7-4&oh=bf3a3fbd1c72b8f5d6c72a47d3ce24d0&oe=60C0BD44&_nc_sid=7bff83", "display_url": "https://scontent-prg1-1.cdninstagram.com/v/t51.2885-15/fr/e15/s1080x1080/194704693_492620248646265_8562663805338032901_n.jpg?tp=1&_nc_ht=scontent-prg1-1.cdninstagram.com&_nc_cat=109&_nc_ohc=Hrjp0sLVJu4AX-CKST3&tn=Vcf8IfvvgXU4rjLb&edm=ABfd0MgBAAAA&ccb=7-4&oh=609d8f156dbd94ad99197507c5c2eab8&oe=60C13E4B&_nc_sid=7bff83", "is_video": false, "location": null, "edge_media_to_comment": {"count": 0}}}, {"node": {"taken_at_timestamp": 1622629867, "shortcode": "CPnVGPvnMeJ", "id": "2587129299146164105", "owner": {"username": "zadovoljnahr", "id": "1428643188"}, "edge_media_preview_like": {"count": 1366}, "fact_check_overall_rating": null, "media_preview": null, "gating_info": null, "sharing_friction_info": {"bloks_app_url": null, "should_have_sharing_friction": false}, "accessibility_caption": "Photo shared by zadovoljna.hr on June 02, 2021 tagging @ritafarhifinds. May be an image of outdoors and tree.", "__typename": "GraphImage", "comments_disabled": false, "edge_media_to_tagged_user": {"edges": [{"node": {"x": 0.6493056, "user": {"is_verified": false, "username": "ritafarhifinds", "id": "340445032", "full_name": "Rita Farhi | Ritafarhifinds", "profile_pic_url": "https://scontent-prg1-1.cdninstagram.com/v/t51.2885-19/s150x150/176128702_1419792471712217_490061025432908729_n.jpg?tp=1&_nc_ht=scontent-prg1-1.cdninstagram.com&_nc_ohc=Ca-1682xpS4AX8R9XCc&edm=ABfd0MgBAAAA&ccb=7-4&oh=84a404200ad16fcb80361449d34e286c&oe=60C1DA0A&_nc_sid=7bff83"}, "y": 0.40833333}}]}, "fact_check_information": null, "thumbnail_resources": [{"src": "https://scontent-prg1-1.cdninstagram.com/v/t51.2885-15/e35/c0.135.1080.1080a/s150x150/194819331_482048352910199_8274823718130741091_n.jpg?tp=1&_nc_ht=scontent-prg1-1.cdninstagram.com&_nc_cat=111&_nc_ohc=uEUXHMSX9TYAX9qgw5x&edm=ABfd0MgBAAAA&ccb=7-4&oh=2688f5e79ce06ee55339e573ebf8d4ae&oe=60C1AE78&_nc_sid=7bff83", "config_width": 150, "config_height": 150}, {"src": "https://scontent-prg1-1.cdninstagram.com/v/t51.2885-15/e35/c0.135.1080.1080a/s240x240/194819331_482048352910199_8274823718130741091_n.jpg?tp=1&_nc_ht=scontent-prg1-1.cdninstagram.com&_nc_cat=111&_nc_ohc=uEUXHMSX9TYAX9qgw5x&tn=Vcf8IfvvgXU4rjLb&edm=ABfd0MgBAAAA&ccb=7-4&oh=c708fd91bcedcb63cfe8d001296c513d&oe=60C08132&_nc_sid=7bff83", "config_width": 240, "config_height": 240}, {"src": "https://scontent-prg1-1.cdninstagram.com/v/t51.2885-15/e35/c0.135.1080.1080a/s320x320/194819331_482048352910199_8274823718130741091_n.jpg?tp=1&_nc_ht=scontent-prg1-1.cdninstagram.com&_nc_cat=111&_nc_ohc=uEUXHMSX9TYAX9qgw5x&edm=ABfd0MgBAAAA&ccb=7-4&oh=e2db56ffae93f11efb290932302106ec&oe=60C14B50&_nc_sid=7bff83", "config_width": 320, "config_height": 320}, {"src": "https://scontent-prg1-1.cdninstagram.com/v/t51.2885-15/e35/c0.135.1080.1080a/s480x480/194819331_482048352910199_8274823718130741091_n.jpg?tp=1&_nc_ht=scontent-prg1-1.cdninstagram.com&_nc_cat=111&_nc_ohc=uEUXHMSX9TYAX9qgw5x&edm=ABfd0MgBAAAA&ccb=7-4&oh=2dd3b70cbbd55c3cf76eaa1d33876e74&oe=60C0B089&_nc_sid=7bff83", "config_width": 480, "config_height": 480}, {"src": "https://scontent-prg1-1.cdninstagram.com/v/t51.2885-15/sh0.08/e35/c0.135.1080.1080a/s640x640/194819331_482048352910199_8274823718130741091_n.jpg?tp=1&_nc_ht=scontent-prg1-1.cdninstagram.com&_nc_cat=111&_nc_ohc=uEUXHMSX9TYAX9qgw5x&edm=ABfd0MgBAAAA&ccb=7-4&oh=0d7f96b3ef855c41597df6e0f53ec0da&oe=60C15F88&_nc_sid=7bff83", "config_width": 640, "config_height": 640}], "edge_media_to_caption": {"edges": [{"node": {"text": "\ud83d\ude0d\ud83d\ude0d\ud83d\ude0d\ud83d\ude0d Odmor za o\u010di.. \ud83c\udf38\n#bloomingtrees #colors #zadovoljnahr\n@ritafarhifinds"}}]}, "media_overlay_info": null, "edge_liked_by": {"count": 1366}, "dimensions": {"height": 1350, "width": 1080}, "thumbnail_src": "https://scontent-prg1-1.cdninstagram.com/v/t51.2885-15/sh0.08/e35/c0.135.1080.1080a/s640x640/194819331_482048352910199_8274823718130741091_n.jpg?tp=1&_nc_ht=scontent-prg1-1.cdninstagram.com&_nc_cat=111&_nc_ohc=uEUXHMSX9TYAX9qgw5x&edm=ABfd0MgBAAAA&ccb=7-4&oh=0d7f96b3ef855c41597df6e0f53ec0da&oe=60C15F88&_nc_sid=7bff83", "display_url": "https://scontent-prg1-1.cdninstagram.com/v/t51.2885-15/e35/194819331_482048352910199_8274823718130741091_n.jpg?tp=1&_nc_ht=scontent-prg1-1.cdninstagram.com&_nc_cat=111&_nc_ohc=uEUXHMSX9TYAX9qgw5x&edm=ABfd0MgBAAAA&ccb=7-4&oh=70d9eb007137df32719c6f95ebb3cf4b&oe=60C1D511&_nc_sid=7bff83", "is_video": false, "location": null, "edge_media_to_comment": {"count": 3}}}, {"node": {"taken_at_timestamp": 1622620429, "shortcode": "CPnDGJ0H922", "id": "2587050127942213046", "owner": {"username": "zadovoljnahr", "id": "1428643188"}, "edge_media_preview_like": {"count": 4956}, "fact_check_overall_rating": null, "media_preview": "ACoq36KKKACg0UUAQ0U9x3plIompme2f0p9Jg+ppkifj+lGff9KPxP5UuD6mgYo/OjAoooEJuFLUNFIdiaikXkUtMAooooEf/9k=", "gating_info": null, "sharing_friction_info": {"bloks_app_url": null, "should_have_sharing_friction": false}, "accessibility_caption": "Photo by zadovoljna.hr on June 02, 2021. May be an image of text.", "__typename": "GraphImage", "comments_disabled": false, "edge_media_to_tagged_user": {"edges": []}, "fact_check_information": null, "thumbnail_resources": [{"src": "https://scontent-prg1-1.cdninstagram.com/v/t51.2885-15/e35/s150x150/195127086_4219969881397456_7370145062450954287_n.jpg?tp=1&_nc_ht=scontent-prg1-1.cdninstagram.com&_nc_cat=104&_nc_ohc=gEN4Zn_x-jAAX_1CjEV&edm=ABfd0MgBAAAA&ccb=7-4&oh=c9efae200169b1e8e8f1be33b08f489e&oe=60C1A46D&_nc_sid=7bff83", "config_width": 150, "config_height": 150}, {"src": "https://scontent-prg1-1.cdninstagram.com/v/t51.2885-15/e35/s240x240/195127086_4219969881397456_7370145062450954287_n.jpg?tp=1&_nc_ht=scontent-prg1-1.cdninstagram.com&_nc_cat=104&_nc_ohc=gEN4Zn_x-jAAX_1CjEV&tn=Vcf8IfvvgXU4rjLb&edm=ABfd0MgBAAAA&ccb=7-4&oh=140ee130c5cfbe61f21df013adb69d89&oe=60C03C65&_nc_sid=7bff83", "config_width": 240, "config_height": 240}, {"src": "https://scontent-prg1-1.cdninstagram.com/v/t51.2885-15/e35/s320x320/195127086_4219969881397456_7370145062450954287_n.jpg?tp=1&_nc_ht=scontent-prg1-1.cdninstagram.com&_nc_cat=104&_nc_ohc=gEN4Zn_x-jAAX_1CjEV&edm=ABfd0MgBAAAA&ccb=7-4&oh=874a43783a57301e2cc5e3d359ffb22f&oe=60C17AFC&_nc_sid=7bff83", "config_width": 320, "config_height": 320}, {"src": "https://scontent-prg1-1.cdninstagram.com/v/t51.2885-15/e35/s480x480/195127086_4219969881397456_7370145062450954287_n.jpg?tp=1&_nc_ht=scontent-prg1-1.cdninstagram.com&_nc_cat=104&_nc_ohc=gEN4Zn_x-jAAX_1CjEV&edm=ABfd0MgBAAAA&ccb=7-4&oh=624a07bdd3166839c172bcb3e3586fbf&oe=60C1427A&_nc_sid=7bff83", "config_width": 480, "config_height": 480}, {"src": "https://scontent-prg1-1.cdninstagram.com/v/t51.2885-15/sh0.08/e35/s640x640/195127086_4219969881397456_7370145062450954287_n.jpg?tp=1&_nc_ht=scontent-prg1-1.cdninstagram.com&_nc_cat=104&_nc_ohc=gEN4Zn_x-jAAX_1CjEV&tn=Vcf8IfvvgXU4rjLb&edm=ABfd0MgBAAAA&ccb=7-4&oh=78c15aa7994280598fa19ba38ea18043&oe=60C1D85A&_nc_sid=7bff83", "config_width": 640, "config_height": 640}], "edge_media_to_caption": {"edges": [{"node": {"text": "Ususret ljetu, svake godine nam kroz glavu pro\u0111e ova misao.. \ud83d\ude05\ud83e\udd37\ud83c\udffc\u200d\u2640\ufe0f\n#staybeautiful #bodypositivity #zadovoljnahr"}}]}, "media_overlay_info": null, "edge_liked_by": {"count": 4956}, "dimensions": {"height": 1080, "width": 1080}, "thumbnail_src": "https://scontent-prg1-1.cdninstagram.com/v/t51.2885-15/sh0.08/e35/s640x640/195127086_4219969881397456_7370145062450954287_n.jpg?tp=1&_nc_ht=scontent-prg1-1.cdninstagram.com&_nc_cat=104&_nc_ohc=gEN4Zn_x-jAAX_1CjEV&edm=ABfd0MgBAAAA&ccb=7-4&oh=92af57e5bc1f3b69b522877d34ce6802&oe=60C1D85A&_nc_sid=7bff83", "display_url": "https://scontent-prg1-1.cdninstagram.com/v/t51.2885-15/e35/195127086_4219969881397456_7370145062450954287_n.jpg?tp=1&_nc_ht=scontent-prg1-1.cdninstagram.com&_nc_cat=104&_nc_ohc=gEN4Zn_x-jAAX_1CjEV&tn=Vcf8IfvvgXU4rjLb&edm=ABfd0MgBAAAA&ccb=7-4&oh=f392703cb7375d12c0faae483a2cb444&oe=60C0C9C1&_nc_sid=7bff83", "is_video": false, "location": null, "edge_media_to_comment": {"count": 164}}}]}, "restricted_by_viewer": false, "edge_followed_by": {"count": 161111}}}}